Workbook
Name table1C: posting!$P$4:$S$21
Name most_col_s: data2!$I$3:$I$250
Name PG2LC: data2!$AF$3:$AF$250
Name most_col_b: data2!$K$3:$K$250
Name JI: job!$D$2:$D$250
Name jd_C: key_job!$AZ$2:$AZ$41
Name JOBPROFILETO8: key!$J$3:$L$27
Name PG3CS: data2!$AI$3:$AI$250
Name jobdict: key_job!$A$2:$A$41
Name change_col_s: data2!$S$3:$S$250
Name change_col_c: data2!$T$3:$T$250
Name JPM3_: data2!$EY$3:$EY$250
Name Nama: data2!$A$3:$A$250
Name table3I: posting!$F$55:$I$92
Name tableI1: posting!$F$4:$I$23
Name jd_I: key_job!$AX$2:$AX$41
Name jd_D: key_job!$AW$2:$AW$41
Name PG1MS: data2!$AA$3:$AA$250
Name cek1_: data2!$BJ$3:$BJ$250
Name unique: data2!$DQ$3:$DQ$250
Name most_col_i: data2!$H$3:$H$250
Name KELEMAHAN: profile!$A$57:$Y$60
Name PG1MC: data2!$AB$3:$AB$250
Name MmExcelLinker_2BEC1165_5F5C_43B8_AB34_B520A81EDF06: dash_mjpm!$A$2:$L$14
Name lead_styles: profile!$A$133:$R$136
Name Posisi: data2!$E$3:$E$250
Name onejob1: onejob!$A$1:$A$250
Name table1S: posting!$K$4:$N$24
Name PG2LS: data2!$AE$3:$AE$250
Name tableD1: posting!$A$4:$D$25
Name table2I: posting!$F$30:$I$49
Name table3S: posting!$K$55:$N$94
Name kekuatan_e: profile_eng!$A$51:$J$54
Name KEKUATAN: profile!$A$51:$Y$54
Name most_col_d: data2!$G$3:$G$250
Name table2C: posting!$P$30:$S$47
Name most_col_c: data2!$J$3:$J$250
Name PG2LD: data2!$AC$3:$AC$250
Name IMJPM2: imjpm!$B$1:$B$250
Name jd_S: key_job!$AY$2:$AY$41
Name Tujuan: data2!$F$3:$F$250
Name CEKGRAF: data2!$DP$3:$DP$250
Name JPM2_: data2!$ES$3:$ES$250
Name MmExcelLinker_4BE19340_872D_4B1E_BE01_1898BB3742AA: main!$V$11
Name TABLE_D: profile_detail!$B$2:$L$13
Name tabel_jpm: tabeljpm!$A$4:$I$11
Name PG1MI: data2!$Z$3:$Z$250
Name prof3: data2!$DO$3:$DO$250
Name tabel_profil: profile!$A$3:$M$42
Name table3C: posting!$P$55:$S$94
Name Kelamin: data2!$B$3:$B$250
Name JC: job!$F$2:$F$250
Name karakteristik: profile!$A$139:$S$142
Name Job_Title: job!$B$2:$B$250
Name least_col_c: data2!$O$3:$O$250
Name least_col_i: data2!$M$3:$M$250
Name cek2_: data2!$CL$3:$CL$250
Name Z_0D9D62F5_B2A7_45DB_A015_044C4D3A4C2D_.wvu.PrintArea: graph!$A$4:$P$35
Name table2D: posting!$A$30:$D$50
Name profil_e: profile_eng!$A$3:$I$42

Sheet log
A1: username | B1: serial_no
A2: HRDBC | B2: BC2026

Sheet main
F13: Username | H13: =log!A2 -> HRDBC
F14: Serial No | H14: =log!B2 -> BC2026

Sheet data
B1: Jenis | D1: Tanggal | G1: Most | L1: Least | Q1: Change | V1: Cek | AA1: =MATCH(AA2,Job_Title,0) -> 13
A2: Nama | B2: Kelamin | C2: Nomor | D2: Tes | E2: Posisi | F2: Tujuan | G2: D | H2: I | I2: S | J2: C | K2: B | L2: D | M2: I | N2: S | O2: C | P2: B | Q2: D | R2: I | S2: S | T2: C | U2: B | V2: M | W2: L | X2: Grafik1 | Y2: Grafik2 | Z2: Grafik3 | AA2: Kepatuhan Internal
A3: Andre Setiawan | B3: Pria | D3: 44291 | F3: profiling | G3: 2 | H3: 0 | I3: 4 | J3: 10 | K3: 8 | L3: 6 | M3: 7 | N3: 3 | O3: 1 | P3: 7 | Q3: -4 | R3: -7 | S3: 1 | T3: 9 | V3: =SUM(G3:U3) -> 47 | W3: =SUM(L3:P3) -> 24 | X3: =IF(VLOOKUP(data2!BJ3,misc!$A$8:$B$11,2,0)="normal",data2!BK3,VLOOKUP(data2!BJ3,misc!$A$8:$B$11,2,0)) -> C | Y3: =IF(VLOOKUP(data2!CL3,misc!$A$8:$B$11,2,0)="normal",data2!CM3,VLOOKUP(data2!CL3,misc!$A$8:$B$11,2,0)) -> CS | Z3: =IF(VLOOKUP(data2!DN3,misc!$A$8:$B$11,2,0)="normal",data2!DO3,VLOOKUP(data2!DN3,misc!$A$8:$B$11,2,0)) -> CS | AA3: =IF(ISERROR(AVERAGE(INDEX(JPM1_,ROW(A3)-2),(INDEX(JPM2_,ROW(A3)-2),(INDEX(JPM3_,ROW(A3)-2)))))=TRUE,"N/A",AVERAGE(INDEX(JPM1_,ROW(A3)-2),(INDEX(JPM2_,ROW(A3)-2),(INDEX(JPM3_,ROW(A3)-2))))) -> #ERROR!
A4: Helmi Kurniawan | B4: Pria | F4: profiling | G4: 3 | H4: 3 | I4: 7 | J4: 4 | K4: 7 | L4: 7 | M4: 4 | N4: 2 | O4: 6 | P4: 5 | Q4: -4 | R4: -1 | S4: 5 | T4: -2 | V4: =SUM(G4:T4) -> 46 | W4: =SUM(L4:P4) -> 24 | X4: =IF(VLOOKUP(data2!BJ4,misc!$A$8:$B$11,2,0)="normal",data2!BK4,VLOOKUP(data2!BJ4,misc!$A$8:$B$11,2,0)) -> SC | Y4: =IF(VLOOKUP(data2!CL4,misc!$A$8:$B$11,2,0)="normal",data2!CM4,VLOOKUP(data2!CL4,misc!$A$8:$B$11,2,0)) -> SCI | Z4: =IF(VLOOKUP(data2!DN4,misc!$A$8:$B$11,2,0)="normal",data2!DO4,VLOOKUP(data2!DN4,misc!$A$8:$B$11,2,0)) -> SC | AA4: =IF(ISERROR(AVERAGE(INDEX(JPM1_,ROW(A4)-2),(INDEX(JPM2_,ROW(A4)-2),(INDEX(JPM3_,ROW(A4)-2)))))=TRUE,"N/A",AVERAGE(INDEX(JPM1_,ROW(A4)-2),(INDEX(JPM2_,ROW(A4)-2),(INDEX(JPM3_,ROW(A4)-2))))) -> #ERROR!
A5: Indah Nopitasari | B5: Wanita | F5: profiling | G5: 0 | H5: 1 | I5: 11 | J5: 4 | K5: 8 | L5: 16 | M5: 3 | N5: 0 | O5: 2 | P5: 3 | Q5: -16 | R5: -2 | S5: 11 | T5: 2 | V5: =SUM(G5:T5) -> 43 | W5: =SUM(L5:P5) -> 24 | X5: =IF(VLOOKUP(data2!BJ5,misc!$A$8:$B$11,2,0)="normal",data2!BK5,VLOOKUP(data2!BJ5,misc!$A$8:$B$11,2,0)) -> SC | Y5: =IF(VLOOKUP(data2!CL5,misc!$A$8:$B$11,2,0)="normal",data2!CM5,VLOOKUP(data2!CL5,misc!$A$8:$B$11,2,0)) -> SCI | Z5: =IF(VLOOKUP(data2!DN5,misc!$A$8:$B$11,2,0)="normal",data2!DO5,VLOOKUP(data2!DN5,misc!$A$8:$B$11,2,0)) -> SC | AA5: =IF(ISERROR(AVERAGE(INDEX(JPM1_,ROW(A5)-2),(INDEX(JPM2_,ROW(A5)-2),(INDEX(JPM3_,ROW(A5)-2)))))=TRUE,"N/A",AVERAGE(INDEX(JPM1_,ROW(A5)-2),(INDEX(JPM2_,ROW(A5)-2),(INDEX(JPM3_,ROW(A5)-2))))) -> #ERROR!
A6: Ayub Putra Utama | B6: Pria | F6: profiling | G6: 3 | H6: 4 | I6: 8 | J6: 2 | K6: 7 | L6: 7 | M6: 6 | N6: 1 | O6: 2 | P6: 8 | Q6: -4 | R6: -2 | S6: 7 | T6: 0 | V6: =SUM(G6:T6) -> 49 | W6: =SUM(L6:P6) -> 24 | X6: =IF(VLOOKUP(data2!BJ6,misc!$A$8:$B$11,2,0)="normal",data2!BK6,VLOOKUP(data2!BJ6,misc!$A$8:$B$11,2,0)) -> SI | Y6: =IF(VLOOKUP(data2!CL6,misc!$A$8:$B$11,2,0)="normal",data2!CM6,VLOOKUP(data2!CL6,misc!$A$8:$B$11,2,0)) -> SC | Z6: =IF(VLOOKUP(data2!DN6,misc!$A$8:$B$11,2,0)="normal",data2!DO6,VLOOKUP(data2!DN6,misc!$A$8:$B$11,2,0)) -> SC | AA6: =IF(ISERROR(AVERAGE(INDEX(JPM1_,ROW(A6)-2),(INDEX(JPM2_,ROW(A6)-2),(INDEX(JPM3_,ROW(A6)-2)))))=TRUE,"N/A",AVERAGE(INDEX(JPM1_,ROW(A6)-2),(INDEX(JPM2_,ROW(A6)-2),(INDEX(JPM3_,ROW(A6)-2))))) -> #ERROR!
X7: =IF(VLOOKUP(data2!BJ7,misc!$A$8:$B$11,2,0)="normal",data2!BK7,VLOOKUP(data2!BJ7,misc!$A$8:$B$11,2,0)) -> undershift | Y7: =IF(VLOOKUP(data2!CL7,misc!$A$8:$B$11,2,0)="normal",data2!CM7,VLOOKUP(data2!CL7,misc!$A$8:$B$11,2,0)) -> uppershift | Z7: =IF(VLOOKUP(data2!DN7,misc!$A$8:$B$11,2,0)="normal",data2!DO7,VLOOKUP(data2!DN7,misc!$A$8:$B$11,2,0)) -> tight profile | AA7: =IF(ISERROR(AVERAGE(INDEX(JPM1_,ROW(A7)-2),(INDEX(JPM2_,ROW(A7)-2),(INDEX(JPM3_,ROW(A7)-2)))))=TRUE,"N/A",AVERAGE(INDEX(JPM1_,ROW(A7)-2),(INDEX(JPM2_,ROW(A7)-2),(INDEX(JPM3_,ROW(A7)-2))))) -> #ERROR!
X8: =IF(VLOOKUP(data2!BJ8,misc!$A$8:$B$11,2,0)="normal",data2!BK8,VLOOKUP(data2!BJ8,misc!$A$8:$B$11,2,0)) -> undershift | Y8: =IF(VLOOKUP(data2!CL8,misc!$A$8:$B$11,2,0)="normal",data2!CM8,VLOOKUP(data2!CL8,misc!$A$8:$B$11,2,0)) -> uppershift | Z8: =IF(VLOOKUP(data2!DN8,misc!$A$8:$B$11,2,0)="normal",data2!DO8,VLOOKUP(data2!DN8,misc!$A$8:$B$11,2,0)) -> tight profile | AA8: =IF(ISERROR(AVERAGE(INDEX(JPM1_,ROW(A8)-2),(INDEX(JPM2_,ROW(A8)-2),(INDEX(JPM3_,ROW(A8)-2)))))=TRUE,"N/A",AVERAGE(INDEX(JPM1_,ROW(A8)-2),(INDEX(JPM2_,ROW(A8)-2),(INDEX(JPM3_,ROW(A8)-2))))) -> #ERROR!
X9: =IF(VLOOKUP(data2!BJ9,misc!$A$8:$B$11,2,0)="normal",data2!BK9,VLOOKUP(data2!BJ9,misc!$A$8:$B$11,2,0)) -> undershift | Y9: =IF(VLOOKUP(data2!CL9,misc!$A$8:$B$11,2,0)="normal",data2!CM9,VLOOKUP(data2!CL9,misc!$A$8:$B$11,2,0)) -> uppershift | Z9: =IF(VLOOKUP(data2!DN9,misc!$A$8:$B$11,2,0)="normal",data2!DO9,VLOOKUP(data2!DN9,misc!$A$8:$B$11,2,0)) -> tight profile | AA9: =IF(ISERROR(AVERAGE(INDEX(JPM1_,ROW(A9)-2),(INDEX(JPM2_,ROW(A9)-2),(INDEX(JPM3_,ROW(A9)-2)))))=TRUE,"N/A",AVERAGE(INDEX(JPM1_,ROW(A9)-2),(INDEX(JPM2_,ROW(A9)-2),(INDEX(JPM3_,ROW(A9)-2))))) -> #ERROR!
X10: =IF(VLOOKUP(data2!BJ10,misc!$A$8:$B$11,2,0)="normal",data2!BK10,VLOOKUP(data2!BJ10,misc!$A$8:$B$11,2,0)) -> undershift | Y10: =IF(VLOOKUP(data2!CL10,misc!$A$8:$B$11,2,0)="normal",data2!CM10,VLOOKUP(data2!CL10,misc!$A$8:$B$11,2,0)) -> uppershift | Z10: =IF(VLOOKUP(data2!DN10,misc!$A$8:$B$11,2,0)="normal",data2!DO10,VLOOKUP(data2!DN10,misc!$A$8:$B$11,2,0)) -> tight profile | AA10: =IF(ISERROR(AVERAGE(INDEX(JPM1_,ROW(A10)-2),(INDEX(JPM2_,ROW(A10)-2),(INDEX(JPM3_,ROW(A10)-2)))))=TRUE,"N/A",AVERAGE(INDEX(JPM1_,ROW(A10)-2),(INDEX(JPM2_,ROW(A10)-2),(INDEX(JPM3_,ROW(A10)-2))))) -> #ERROR!
X11: =IF(VLOOKUP(data2!BJ11,misc!$A$8:$B$11,2,0)="normal",data2!BK11,VLOOKUP(data2!BJ11,misc!$A$8:$B$11,2,0)) -> undershift | Y11: =IF(VLOOKUP(data2!CL11,misc!$A$8:$B$11,2,0)="normal",data2!CM11,VLOOKUP(data2!CL11,misc!$A$8:$B$11,2,0)) -> uppershift | Z11: =IF(VLOOKUP(data2!DN11,misc!$A$8:$B$11,2,0)="normal",data2!DO11,VLOOKUP(data2!DN11,misc!$A$8:$B$11,2,0)) -> tight profile | AA11: =IF(ISERROR(AVERAGE(INDEX(JPM1_,ROW(A11)-2),(INDEX(JPM2_,ROW(A11)-2),(INDEX(JPM3_,ROW(A11)-2)))))=TRUE,"N/A",AVERAGE(INDEX(JPM1_,ROW(A11)-2),(INDEX(JPM2_,ROW(A11)-2),(INDEX(JPM3_,ROW(A11)-2))))) -> #ERROR!
X12: =IF(VLOOKUP(data2!BJ12,misc!$A$8:$B$11,2,0)="normal",data2!BK12,VLOOKUP(data2!BJ12,misc!$A$8:$B$11,2,0)) -> undershift | Y12: =IF(VLOOKUP(data2!CL12,misc!$A$8:$B$11,2,0)="normal",data2!CM12,VLOOKUP(data2!CL12,misc!$A$8:$B$11,2,0)) -> uppershift | Z12: =IF(VLOOKUP(data2!DN12,misc!$A$8:$B$11,2,0)="normal",data2!DO12,VLOOKUP(data2!DN12,misc!$A$8:$B$11,2,0)) -> tight profile | AA12: =IF(ISERROR(AVERAGE(INDEX(JPM1_,ROW(A12)-2),(INDEX(JPM2_,ROW(A12)-2),(INDEX(JPM3_,ROW(A12)-2)))))=TRUE,"N/A",AVERAGE(INDEX(JPM1_,ROW(A12)-2),(INDEX(JPM2_,ROW(A12)-2),(INDEX(JPM3_,ROW(A12)-2))))) -> #ERROR!
X13: =IF(VLOOKUP(data2!BJ13,misc!$A$8:$B$11,2,0)="normal",data2!BK13,VLOOKUP(data2!BJ13,misc!$A$8:$B$11,2,0)) -> undershift | Y13: =IF(VLOOKUP(data2!CL13,misc!$A$8:$B$11,2,0)="normal",data2!CM13,VLOOKUP(data2!CL13,misc!$A$8:$B$11,2,0)) -> uppershift | Z13: =IF(VLOOKUP(data2!DN13,misc!$A$8:$B$11,2,0)="normal",data2!DO13,VLOOKUP(data2!DN13,misc!$A$8:$B$11,2,0)) -> tight profile | AA13: =IF(ISERROR(AVERAGE(INDEX(JPM1_,ROW(A13)-2),(INDEX(JPM2_,ROW(A13)-2),(INDEX(JPM3_,ROW(A13)-2)))))=TRUE,"N/A",AVERAGE(INDEX(JPM1_,ROW(A13)-2),(INDEX(JPM2_,ROW(A13)-2),(INDEX(JPM3_,ROW(A13)-2))))) -> #ERROR!
X14: =IF(VLOOKUP(data2!BJ14,misc!$A$8:$B$11,2,0)="normal",data2!BK14,VLOOKUP(data2!BJ14,misc!$A$8:$B$11,2,0)) -> undershift | Y14: =IF(VLOOKUP(data2!CL14,misc!$A$8:$B$11,2,0)="normal",data2!CM14,VLOOKUP(data2!CL14,misc!$A$8:$B$11,2,0)) -> uppershift | Z14: =IF(VLOOKUP(data2!DN14,misc!$A$8:$B$11,2,0)="normal",data2!DO14,VLOOKUP(data2!DN14,misc!$A$8:$B$11,2,0)) -> tight profile | AA14: =IF(ISERROR(AVERAGE(INDEX(JPM1_,ROW(A14)-2),(INDEX(JPM2_,ROW(A14)-2),(INDEX(JPM3_,ROW(A14)-2)))))=TRUE,"N/A",AVERAGE(INDEX(JPM1_,ROW(A14)-2),(INDEX(JPM2_,ROW(A14)-2),(INDEX(JPM3_,ROW(A14)-2))))) -> #ERROR!
X15: =IF(VLOOKUP(data2!BJ15,misc!$A$8:$B$11,2,0)="normal",data2!BK15,VLOOKUP(data2!BJ15,misc!$A$8:$B$11,2,0)) -> undershift | Y15: =IF(VLOOKUP(data2!CL15,misc!$A$8:$B$11,2,0)="normal",data2!CM15,VLOOKUP(data2!CL15,misc!$A$8:$B$11,2,0)) -> uppershift | Z15: =IF(VLOOKUP(data2!DN15,misc!$A$8:$B$11,2,0)="normal",data2!DO15,VLOOKUP(data2!DN15,misc!$A$8:$B$11,2,0)) -> tight profile | AA15: =IF(ISERROR(AVERAGE(INDEX(JPM1_,ROW(A15)-2),(INDEX(JPM2_,ROW(A15)-2),(INDEX(JPM3_,ROW(A15)-2)))))=TRUE,"N/A",AVERAGE(INDEX(JPM1_,ROW(A15)-2),(INDEX(JPM2_,ROW(A15)-2),(INDEX(JPM3_,ROW(A15)-2))))) -> #ERROR!
X16: =IF(VLOOKUP(data2!BJ16,misc!$A$8:$B$11,2,0)="normal",data2!BK16,VLOOKUP(data2!BJ16,misc!$A$8:$B$11,2,0)) -> undershift | Y16: =IF(VLOOKUP(data2!CL16,misc!$A$8:$B$11,2,0)="normal",data2!CM16,VLOOKUP(data2!CL16,misc!$A$8:$B$11,2,0)) -> uppershift | Z16: =IF(VLOOKUP(data2!DN16,misc!$A$8:$B$11,2,0)="normal",data2!DO16,VLOOKUP(data2!DN16,misc!$A$8:$B$11,2,0)) -> tight profile | AA16: =IF(ISERROR(AVERAGE(INDEX(JPM1_,ROW(A16)-2),(INDEX(JPM2_,ROW(A16)-2),(INDEX(JPM3_,ROW(A16)-2)))))=TRUE,"N/A",AVERAGE(INDEX(JPM1_,ROW(A16)-2),(INDEX(JPM2_,ROW(A16)-2),(INDEX(JPM3_,ROW(A16)-2))))) -> #ERROR!
X17: =IF(VLOOKUP(data2!BJ17,misc!$A$8:$B$11,2,0)="normal",data2!BK17,VLOOKUP(data2!BJ17,misc!$A$8:$B$11,2,0)) -> undershift | Y17: =IF(VLOOKUP(data2!CL17,misc!$A$8:$B$11,2,0)="normal",data2!CM17,VLOOKUP(data2!CL17,misc!$A$8:$B$11,2,0)) -> uppershift | Z17: =IF(VLOOKUP(data2!DN17,misc!$A$8:$B$11,2,0)="normal",data2!DO17,VLOOKUP(data2!DN17,misc!$A$8:$B$11,2,0)) -> tight profile | AA17: =IF(ISERROR(AVERAGE(INDEX(JPM1_,ROW(A17)-2),(INDEX(JPM2_,ROW(A17)-2),(INDEX(JPM3_,ROW(A17)-2)))))=TRUE,"N/A",AVERAGE(INDEX(JPM1_,ROW(A17)-2),(INDEX(JPM2_,ROW(A17)-2),(INDEX(JPM3_,ROW(A17)-2))))) -> #ERROR!
X18: =IF(VLOOKUP(data2!BJ18,misc!$A$8:$B$11,2,0)="normal",data2!BK18,VLOOKUP(data2!BJ18,misc!$A$8:$B$11,2,0)) -> undershift | Y18: =IF(VLOOKUP(data2!CL18,misc!$A$8:$B$11,2,0)="normal",data2!CM18,VLOOKUP(data2!CL18,misc!$A$8:$B$11,2,0)) -> uppershift | Z18: =IF(VLOOKUP(data2!DN18,misc!$A$8:$B$11,2,0)="normal",data2!DO18,VLOOKUP(data2!DN18,misc!$A$8:$B$11,2,0)) -> tight profile | AA18: =IF(ISERROR(AVERAGE(INDEX(JPM1_,ROW(A18)-2),(INDEX(JPM2_,ROW(A18)-2),(INDEX(JPM3_,ROW(A18)-2)))))=TRUE,"N/A",AVERAGE(INDEX(JPM1_,ROW(A18)-2),(INDEX(JPM2_,ROW(A18)-2),(INDEX(JPM3_,ROW(A18)-2))))) -> #ERROR!
... X38: =IF(VLOOKUP(data2!BJ38,misc!$A$8:$B$11,2,0)="normal",data2!BK38,VLOOKUP(data2!BJ38,misc!$A$8:$B$11,2,0)) -> undershift | Y38: =IF(VLOOKUP(data2!CL38,misc!$A$8:$B$11,2,0)="normal",data2!CM38,VLOOKUP(data2!CL38,misc!$A$8:$B$11,2,0)) -> uppershift | Z38: =IF(VLOOKUP(data2!DN38,misc!$A$8:$B$11,2,0)="normal",data2!DO38,VLOOKUP(data2!DN38,misc!$A$8:$B$11,2,0)) -> tight profile | AA38: =IF(ISERROR(AVERAGE(INDEX(JPM1_,ROW(A38)-2),(INDEX(JPM2_,ROW(A38)-2),(INDEX(JPM3_,ROW(A38)-2)))))=TRUE,"N/A",AVERAGE(INDEX(JPM1_,ROW(A38)-2),(INDEX(JPM2_,ROW(A38)-2),(INDEX(JPM3_,ROW(A38)-2))))) -> #ERROR!
X39: =IF(VLOOKUP(data2!BJ39,misc!$A$8:$B$11,2,0)="normal",data2!BK39,VLOOKUP(data2!BJ39,misc!$A$8:$B$11,2,0)) -> #ERROR! | Y39: =IF(VLOOKUP(data2!CL39,misc!$A$8:$B$11,2,0)="normal",data2!CM39,VLOOKUP(data2!CL39,misc!$A$8:$B$11,2,0)) -> #ERROR! | Z39: =IF(VLOOKUP(data2!DN39,misc!$A$8:$B$11,2,0)="normal",data2!DO39,VLOOKUP(data2!DN39,misc!$A$8:$B$11,2,0)) -> #ERROR! | AA39: =IF(ISERROR(AVERAGE(INDEX(JPM1_,ROW(#REF!)-2),(INDEX(JPM2_,ROW(#REF!)-2),(INDEX(JPM3_,ROW(#REF!)-2)))))=TRUE,"N/A",AVERAGE(INDEX(JPM1_,ROW(#REF!)-2),(INDEX(JPM2_,ROW(#REF!)-2),(INDEX(JPM3_,ROW(#REF!)-2))))) -> #ERROR!
X40: =IF(VLOOKUP(data2!BJ40,misc!$A$8:$B$11,2,0)="normal",data2!BK40,VLOOKUP(data2!BJ40,misc!$A$8:$B$11,2,0)) -> undershift | Y40: =IF(VLOOKUP(data2!CL40,misc!$A$8:$B$11,2,0)="normal",data2!CM40,VLOOKUP(data2!CL40,misc!$A$8:$B$11,2,0)) -> uppershift | Z40: =IF(VLOOKUP(data2!DN40,misc!$A$8:$B$11,2,0)="normal",data2!DO40,VLOOKUP(data2!DN40,misc!$A$8:$B$11,2,0)) -> tight profile | AA40: =IF(ISERROR(AVERAGE(INDEX(JPM1_,ROW(A40)-2),(INDEX(JPM2_,ROW(A40)-2),(INDEX(JPM3_,ROW(A40)-2)))))=TRUE,"N/A",AVERAGE(INDEX(JPM1_,ROW(A40)-2),(INDEX(JPM2_,ROW(A40)-2),(INDEX(JPM3_,ROW(A40)-2))))) -> #ERROR!
X41: =IF(VLOOKUP(data2!BJ41,misc!$A$8:$B$11,2,0)="normal",data2!BK41,VLOOKUP(data2!BJ41,misc!$A$8:$B$11,2,0)) -> undershift | Y41: =IF(VLOOKUP(data2!CL41,misc!$A$8:$B$11,2,0)="normal",data2!CM41,VLOOKUP(data2!CL41,misc!$A$8:$B$11,2,0)) -> uppershift | Z41: =IF(VLOOKUP(data2!DN41,misc!$A$8:$B$11,2,0)="normal",data2!DO41,VLOOKUP(data2!DN41,misc!$A$8:$B$11,2,0)) -> tight profile | AA41: =IF(ISERROR(AVERAGE(INDEX(JPM1_,ROW(A41)-2),(INDEX(JPM2_,ROW(A41)-2),(INDEX(JPM3_,ROW(A41)-2)))))=TRUE,"N/A",AVERAGE(INDEX(JPM1_,ROW(A41)-2),(INDEX(JPM2_,ROW(A41)-2),(INDEX(JPM3_,ROW(A41)-2))))) -> #ERROR!
X42: =IF(VLOOKUP(data2!BJ42,misc!$A$8:$B$11,2,0)="normal",data2!BK42,VLOOKUP(data2!BJ42,misc!$A$8:$B$11,2,0)) -> undershift | Y42: =IF(VLOOKUP(data2!CL42,misc!$A$8:$B$11,2,0)="normal",data2!CM42,VLOOKUP(data2!CL42,misc!$A$8:$B$11,2,0)) -> uppershift | Z42: =IF(VLOOKUP(data2!DN42,misc!$A$8:$B$11,2,0)="normal",data2!DO42,VLOOKUP(data2!DN42,misc!$A$8:$B$11,2,0)) -> tight profile | AA42: =IF(ISERROR(AVERAGE(INDEX(JPM1_,ROW(A42)-2),(INDEX(JPM2_,ROW(A42)-2),(INDEX(JPM3_,ROW(A42)-2)))))=TRUE,"N/A",AVERAGE(INDEX(JPM1_,ROW(A42)-2),(INDEX(JPM2_,ROW(A42)-2),(INDEX(JPM3_,ROW(A42)-2))))) -> #ERROR!
X43: =IF(VLOOKUP(data2!BJ43,misc!$A$8:$B$11,2,0)="normal",data2!BK43,VLOOKUP(data2!BJ43,misc!$A$8:$B$11,2,0)) -> undershift | Y43: =IF(VLOOKUP(data2!CL43,misc!$A$8:$B$11,2,0)="normal",data2!CM43,VLOOKUP(data2!CL43,misc!$A$8:$B$11,2,0)) -> uppershift | Z43: =IF(VLOOKUP(data2!DN43,misc!$A$8:$B$11,2,0)="normal",data2!DO43,VLOOKUP(data2!DN43,misc!$A$8:$B$11,2,0)) -> tight profile | AA43: =IF(ISERROR(AVERAGE(INDEX(JPM1_,ROW(A43)-2),(INDEX(JPM2_,ROW(A43)-2),(INDEX(JPM3_,ROW(A43)-2)))))=TRUE,"N/A",AVERAGE(INDEX(JPM1_,ROW(A43)-2),(INDEX(JPM2_,ROW(A43)-2),(INDEX(JPM3_,ROW(A43)-2))))) -> #ERROR!
X44: =IF(VLOOKUP(data2!BJ44,misc!$A$8:$B$11,2,0)="normal",data2!BK44,VLOOKUP(data2!BJ44,misc!$A$8:$B$11,2,0)) -> undershift | Y44: =IF(VLOOKUP(data2!CL44,misc!$A$8:$B$11,2,0)="normal",data2!CM44,VLOOKUP(data2!CL44,misc!$A$8:$B$11,2,0)) -> uppershift | Z44: =IF(VLOOKUP(data2!DN44,misc!$A$8:$B$11,2,0)="normal",data2!DO44,VLOOKUP(data2!DN44,misc!$A$8:$B$11,2,0)) -> tight profile | AA44: =IF(ISERROR(AVERAGE(INDEX(JPM1_,ROW(A44)-2),(INDEX(JPM2_,ROW(A44)-2),(INDEX(JPM3_,ROW(A44)-2)))))=TRUE,"N/A",AVERAGE(INDEX(JPM1_,ROW(A44)-2),(INDEX(JPM2_,ROW(A44)-2),(INDEX(JPM3_,ROW(A44)-2))))) -> #ERROR!
F45: profiling | V45: =SUM(G45:T45) -> 0 | W45: =SUM(L45:P45) -> 0 | X45: =IF(VLOOKUP(data2!BJ45,misc!$A$8:$B$11,2,0)="normal",data2!BK45,VLOOKUP(data2!BJ45,misc!$A$8:$B$11,2,0)) -> undershift | Y45: =IF(VLOOKUP(data2!CL45,misc!$A$8:$B$11,2,0)="normal",data2!CM45,VLOOKUP(data2!CL45,misc!$A$8:$B$11,2,0)) -> uppershift | Z45: =IF(VLOOKUP(data2!DN45,misc!$A$8:$B$11,2,0)="normal",data2!DO45,VLOOKUP(data2!DN45,misc!$A$8:$B$11,2,0)) -> tight profile | AA45: =IF(ISERROR(AVERAGE(INDEX(JPM1_,ROW(A45)-2),(INDEX(JPM2_,ROW(A45)-2),(INDEX(JPM3_,ROW(A45)-2)))))=TRUE,"N/A",AVERAGE(INDEX(JPM1_,ROW(A45)-2),(INDEX(JPM2_,ROW(A45)-2),(INDEX(JPM3_,ROW(A45)-2))))) -> #ERROR!
F46: profiling | V46: =SUM(G46:T46) -> 0 | W46: =SUM(L46:P46) -> 0 | X46: =IF(VLOOKUP(data2!BJ46,misc!$A$8:$B$11,2,0)="normal",data2!BK46,VLOOKUP(data2!BJ46,misc!$A$8:$B$11,2,0)) -> undershift | Y46: =IF(VLOOKUP(data2!CL46,misc!$A$8:$B$11,2,0)="normal",data2!CM46,VLOOKUP(data2!CL46,misc!$A$8:$B$11,2,0)) -> uppershift | Z46: =IF(VLOOKUP(data2!DN46,misc!$A$8:$B$11,2,0)="normal",data2!DO46,VLOOKUP(data2!DN46,misc!$A$8:$B$11,2,0)) -> tight profile | AA46: =IF(ISERROR(AVERAGE(INDEX(JPM1_,ROW(A46)-2),(INDEX(JPM2_,ROW(A46)-2),(INDEX(JPM3_,ROW(A46)-2)))))=TRUE,"N/A",AVERAGE(INDEX(JPM1_,ROW(A46)-2),(INDEX(JPM2_,ROW(A46)-2),(INDEX(JPM3_,ROW(A46)-2))))) -> #ERROR!
F47: profiling | V47: =SUM(G47:T47) -> 0 | W47: =SUM(L47:P47) -> 0 | X47: =IF(VLOOKUP(data2!BJ47,misc!$A$8:$B$11,2,0)="normal",data2!BK47,VLOOKUP(data2!BJ47,misc!$A$8:$B$11,2,0)) -> undershift | Y47: =IF(VLOOKUP(data2!CL47,misc!$A$8:$B$11,2,0)="normal",data2!CM47,VLOOKUP(data2!CL47,misc!$A$8:$B$11,2,0)) -> uppershift | Z47: =IF(VLOOKUP(data2!DN47,misc!$A$8:$B$11,2,0)="normal",data2!DO47,VLOOKUP(data2!DN47,misc!$A$8:$B$11,2,0)) -> tight profile | AA47: =IF(ISERROR(AVERAGE(INDEX(JPM1_,ROW(A47)-2),(INDEX(JPM2_,ROW(A47)-2),(INDEX(JPM3_,ROW(A47)-2)))))=TRUE,"N/A",AVERAGE(INDEX(JPM1_,ROW(A47)-2),(INDEX(JPM2_,ROW(A47)-2),(INDEX(JPM3_,ROW(A47)-2))))) -> #ERROR!
F48: profiling | V48: =SUM(G48:T48) -> 0 | W48: =SUM(L48:P48) -> 0 | X48: =IF(VLOOKUP(data2!BJ48,misc!$A$8:$B$11,2,0)="normal",data2!BK48,VLOOKUP(data2!BJ48,misc!$A$8:$B$11,2,0)) -> undershift | Y48: =IF(VLOOKUP(data2!CL48,misc!$A$8:$B$11,2,0)="normal",data2!CM48,VLOOKUP(data2!CL48,misc!$A$8:$B$11,2,0)) -> uppershift | Z48: =IF(VLOOKUP(data2!DN48,misc!$A$8:$B$11,2,0)="normal",data2!DO48,VLOOKUP(data2!DN48,misc!$A$8:$B$11,2,0)) -> tight profile | AA48: =IF(ISERROR(AVERAGE(INDEX(JPM1_,ROW(A48)-2),(INDEX(JPM2_,ROW(A48)-2),(INDEX(JPM3_,ROW(A48)-2)))))=TRUE,"N/A",AVERAGE(INDEX(JPM1_,ROW(A48)-2),(INDEX(JPM2_,ROW(A48)-2),(INDEX(JPM3_,ROW(A48)-2))))) -> #ERROR!
F49: profiling | V49: =SUM(G49:T49) -> 0 | W49: =SUM(L49:P49) -> 0 | X49: =IF(VLOOKUP(data2!BJ49,misc!$A$8:$B$11,2,0)="normal",data2!BK49,VLOOKUP(data2!BJ49,misc!$A$8:$B$11,2,0)) -> undershift | Y49: =IF(VLOOKUP(data2!CL49,misc!$A$8:$B$11,2,0)="normal",data2!CM49,VLOOKUP(data2!CL49,misc!$A$8:$B$11,2,0)) -> uppershift | Z49: =IF(VLOOKUP(data2!DN49,misc!$A$8:$B$11,2,0)="normal",data2!DO49,VLOOKUP(data2!DN49,misc!$A$8:$B$11,2,0)) -> tight profile | AA49: =IF(ISERROR(AVERAGE(INDEX(JPM1_,ROW(A49)-2),(INDEX(JPM2_,ROW(A49)-2),(INDEX(JPM3_,ROW(A49)-2)))))=TRUE,"N/A",AVERAGE(INDEX(JPM1_,ROW(A49)-2),(INDEX(JPM2_,ROW(A49)-2),(INDEX(JPM3_,ROW(A49)-2))))) -> #ERROR!
F50: profiling | V50: =SUM(G50:T50) -> 0 | W50: =SUM(L50:P50) -> 0 | X50: =IF(VLOOKUP(data2!BJ50,misc!$A$8:$B$11,2,0)="normal",data2!BK50,VLOOKUP(data2!BJ50,misc!$A$8:$B$11,2,0)) -> undershift | Y50: =IF(VLOOKUP(data2!CL50,misc!$A$8:$B$11,2,0)="normal",data2!CM50,VLOOKUP(data2!CL50,misc!$A$8:$B$11,2,0)) -> uppershift | Z50: =IF(VLOOKUP(data2!DN50,misc!$A$8:$B$11,2,0)="normal",data2!DO50,VLOOKUP(data2!DN50,misc!$A$8:$B$11,2,0)) -> tight profile | AA50: =IF(ISERROR(AVERAGE(INDEX(JPM1_,ROW(A50)-2),(INDEX(JPM2_,ROW(A50)-2),(INDEX(JPM3_,ROW(A50)-2)))))=TRUE,"N/A",AVERAGE(INDEX(JPM1_,ROW(A50)-2),(INDEX(JPM2_,ROW(A50)-2),(INDEX(JPM3_,ROW(A50)-2))))) -> #ERROR!
F51: profiling | V51: =SUM(G51:T51) -> 0 | W51: =SUM(L51:P51) -> 0 | X51: =IF(VLOOKUP(data2!BJ51,misc!$A$8:$B$11,2,0)="normal",data2!BK51,VLOOKUP(data2!BJ51,misc!$A$8:$B$11,2,0)) -> undershift | Y51: =IF(VLOOKUP(data2!CL51,misc!$A$8:$B$11,2,0)="normal",data2!CM51,VLOOKUP(data2!CL51,misc!$A$8:$B$11,2,0)) -> uppershift | Z51: =IF(VLOOKUP(data2!DN51,misc!$A$8:$B$11,2,0)="normal",data2!DO51,VLOOKUP(data2!DN51,misc!$A$8:$B$11,2,0)) -> tight profile | AA51: =IF(ISERROR(AVERAGE(INDEX(JPM1_,ROW(A51)-2),(INDEX(JPM2_,ROW(A51)-2),(INDEX(JPM3_,ROW(A51)-2)))))=TRUE,"N/A",AVERAGE(INDEX(JPM1_,ROW(A51)-2),(INDEX(JPM2_,ROW(A51)-2),(INDEX(JPM3_,ROW(A51)-2))))) -> #ERROR!
F52: profiling | V52: =SUM(G52:T52) -> 0 | W52: =SUM(L52:P52) -> 0 | X52: =IF(VLOOKUP(data2!BJ52,misc!$A$8:$B$11,2,0)="normal",data2!BK52,VLOOKUP(data2!BJ52,misc!$A$8:$B$11,2,0)) -> undershift | Y52: =IF(VLOOKUP(data2!CL52,misc!$A$8:$B$11,2,0)="normal",data2!CM52,VLOOKUP(data2!CL52,misc!$A$8:$B$11,2,0)) -> uppershift | Z52: =IF(VLOOKUP(data2!DN52,misc!$A$8:$B$11,2,0)="normal",data2!DO52,VLOOKUP(data2!DN52,misc!$A$8:$B$11,2,0)) -> tight profile | AA52: =IF(ISERROR(AVERAGE(INDEX(JPM1_,ROW(A52)-2),(INDEX(JPM2_,ROW(A52)-2),(INDEX(JPM3_,ROW(A52)-2)))))=TRUE,"N/A",AVERAGE(INDEX(JPM1_,ROW(A52)-2),(INDEX(JPM2_,ROW(A52)-2),(INDEX(JPM3_,ROW(A52)-2))))) -> #ERROR!
F53: profiling | V53: =SUM(G53:T53) -> 0 | W53: =SUM(L53:P53) -> 0 | X53: =IF(VLOOKUP(data2!BJ53,misc!$A$8:$B$11,2,0)="normal",data2!BK53,VLOOKUP(data2!BJ53,misc!$A$8:$B$11,2,0)) -> undershift | Y53: =IF(VLOOKUP(data2!CL53,misc!$A$8:$B$11,2,0)="normal",data2!CM53,VLOOKUP(data2!CL53,misc!$A$8:$B$11,2,0)) -> uppershift | Z53: =IF(VLOOKUP(data2!DN53,misc!$A$8:$B$11,2,0)="normal",data2!DO53,VLOOKUP(data2!DN53,misc!$A$8:$B$11,2,0)) -> tight profile | AA53: =IF(ISERROR(AVERAGE(INDEX(JPM1_,ROW(A53)-2),(INDEX(JPM2_,ROW(A53)-2),(INDEX(JPM3_,ROW(A53)-2)))))=TRUE,"N/A",AVERAGE(INDEX(JPM1_,ROW(A53)-2),(INDEX(JPM2_,ROW(A53)-2),(INDEX(JPM3_,ROW(A53)-2))))) -> #ERROR!
F54: profiling | V54: =SUM(G54:T54) -> 0 | W54: =SUM(L54:P54) -> 0 | X54: =IF(VLOOKUP(data2!BJ54,misc!$A$8:$B$11,2,0)="normal",data2!BK54,VLOOKUP(data2!BJ54,misc!$A$8:$B$11,2,0)) -> undershift | Y54: =IF(VLOOKUP(data2!CL54,misc!$A$8:$B$11,2,0)="normal",data2!CM54,VLOOKUP(data2!CL54,misc!$A$8:$B$11,2,0)) -> uppershift | Z54: =IF(VLOOKUP(data2!DN54,misc!$A$8:$B$11,2,0)="normal",data2!DO54,VLOOKUP(data2!DN54,misc!$A$8:$B$11,2,0)) -> tight profile | AA54: =IF(ISERROR(AVERAGE(INDEX(JPM1_,ROW(A54)-2),(INDEX(JPM2_,ROW(A54)-2),(INDEX(JPM3_,ROW(A54)-2)))))=TRUE,"N/A",AVERAGE(INDEX(JPM1_,ROW(A54)-2),(INDEX(JPM2_,ROW(A54)-2),(INDEX(JPM3_,ROW(A54)-2))))) -> #ERROR!
F55: profiling | V55: =SUM(G55:T55) -> 0 | W55: =SUM(L55:P55) -> 0 | X55: =IF(VLOOKUP(data2!BJ55,misc!$A$8:$B$11,2,0)="normal",data2!BK55,VLOOKUP(data2!BJ55,misc!$A$8:$B$11,2,0)) -> undershift | Y55: =IF(VLOOKUP(data2!CL55,misc!$A$8:$B$11,2,0)="normal",data2!CM55,VLOOKUP(data2!CL55,misc!$A$8:$B$11,2,0)) -> uppershift | Z55: =IF(VLOOKUP(data2!DN55,misc!$A$8:$B$11,2,0)="normal",data2!DO55,VLOOKUP(data2!DN55,misc!$A$8:$B$11,2,0)) -> tight profile | AA55: =IF(ISERROR(AVERAGE(INDEX(JPM1_,ROW(A55)-2),(INDEX(JPM2_,ROW(A55)-2),(INDEX(JPM3_,ROW(A55)-2)))))=TRUE,"N/A",AVERAGE(INDEX(JPM1_,ROW(A55)-2),(INDEX(JPM2_,ROW(A55)-2),(INDEX(JPM3_,ROW(A55)-2))))) -> #ERROR!
F56: profiling | V56: =SUM(G56:T56) -> 0 | W56: =SUM(L56:P56) -> 0 | X56: =IF(VLOOKUP(data2!BJ56,misc!$A$8:$B$11,2,0)="normal",data2!BK56,VLOOKUP(data2!BJ56,misc!$A$8:$B$11,2,0)) -> undershift | Y56: =IF(VLOOKUP(data2!CL56,misc!$A$8:$B$11,2,0)="normal",data2!CM56,VLOOKUP(data2!CL56,misc!$A$8:$B$11,2,0)) -> uppershift | Z56: =IF(VLOOKUP(data2!DN56,misc!$A$8:$B$11,2,0)="normal",data2!DO56,VLOOKUP(data2!DN56,misc!$A$8:$B$11,2,0)) -> tight profile | AA56: =IF(ISERROR(AVERAGE(INDEX(JPM1_,ROW(A56)-2),(INDEX(JPM2_,ROW(A56)-2),(INDEX(JPM3_,ROW(A56)-2)))))=TRUE,"N/A",AVERAGE(INDEX(JPM1_,ROW(A56)-2),(INDEX(JPM2_,ROW(A56)-2),(INDEX(JPM3_,ROW(A56)-2))))) -> #ERROR!
... F71: profiling | V71: =SUM(G71:T71) -> 0 | W71: =SUM(L71:P71) -> 0 | X71: =IF(VLOOKUP(data2!BJ71,misc!$A$8:$B$11,2,0)="normal",data2!BK71,VLOOKUP(data2!BJ71,misc!$A$8:$B$11,2,0)) -> undershift | Y71: =IF(VLOOKUP(data2!CL71,misc!$A$8:$B$11,2,0)="normal",data2!CM71,VLOOKUP(data2!CL71,misc!$A$8:$B$11,2,0)) -> uppershift | Z71: =IF(VLOOKUP(data2!DN71,misc!$A$8:$B$11,2,0)="normal",data2!DO71,VLOOKUP(data2!DN71,misc!$A$8:$B$11,2,0)) -> tight profile | AA71: =IF(ISERROR(AVERAGE(INDEX(JPM1_,ROW(A71)-2),(INDEX(JPM2_,ROW(A71)-2),(INDEX(JPM3_,ROW(A71)-2)))))=TRUE,"N/A",AVERAGE(INDEX(JPM1_,ROW(A71)-2),(INDEX(JPM2_,ROW(A71)-2),(INDEX(JPM3_,ROW(A71)-2))))) -> #ERROR!
F72: profiling | V72: =SUM(G72:K72) -> 0 | W72: =SUM(L72:P72) -> 0 | X72: =IF(VLOOKUP(data2!BJ72,misc!$A$8:$B$11,2,0)="normal",data2!BK72,VLOOKUP(data2!BJ72,misc!$A$8:$B$11,2,0)) -> undershift | Y72: =IF(VLOOKUP(data2!CL72,misc!$A$8:$B$11,2,0)="normal",data2!CM72,VLOOKUP(data2!CL72,misc!$A$8:$B$11,2,0)) -> uppershift | Z72: =IF(VLOOKUP(data2!DN72,misc!$A$8:$B$11,2,0)="normal",data2!DO72,VLOOKUP(data2!DN72,misc!$A$8:$B$11,2,0)) -> tight profile | AA72: =IF(ISERROR(AVERAGE(INDEX(JPM1_,ROW(A72)-2),(INDEX(JPM2_,ROW(A72)-2),(INDEX(JPM3_,ROW(A72)-2)))))=TRUE,"N/A",AVERAGE(INDEX(JPM1_,ROW(A72)-2),(INDEX(JPM2_,ROW(A72)-2),(INDEX(JPM3_,ROW(A72)-2))))) -> #ERROR!
F73: profiling | V73: =SUM(G73:K73) -> 0 | W73: =SUM(L73:P73) -> 0 | X73: =IF(VLOOKUP(data2!BJ73,misc!$A$8:$B$11,2,0)="normal",data2!BK73,VLOOKUP(data2!BJ73,misc!$A$8:$B$11,2,0)) -> undershift | Y73: =IF(VLOOKUP(data2!CL73,misc!$A$8:$B$11,2,0)="normal",data2!CM73,VLOOKUP(data2!CL73,misc!$A$8:$B$11,2,0)) -> uppershift | Z73: =IF(VLOOKUP(data2!DN73,misc!$A$8:$B$11,2,0)="normal",data2!DO73,VLOOKUP(data2!DN73,misc!$A$8:$B$11,2,0)) -> tight profile | AA73: =IF(ISERROR(AVERAGE(INDEX(JPM1_,ROW(A73)-2),(INDEX(JPM2_,ROW(A73)-2),(INDEX(JPM3_,ROW(A73)-2)))))=TRUE,"N/A",AVERAGE(INDEX(JPM1_,ROW(A73)-2),(INDEX(JPM2_,ROW(A73)-2),(INDEX(JPM3_,ROW(A73)-2))))) -> #ERROR!
F74: profiling | V74: =SUM(G74:K74) -> 0 | W74: =SUM(L74:P74) -> 0 | X74: =IF(VLOOKUP(data2!BJ74,misc!$A$8:$B$11,2,0)="normal",data2!BK74,VLOOKUP(data2!BJ74,misc!$A$8:$B$11,2,0)) -> undershift | Y74: =IF(VLOOKUP(data2!CL74,misc!$A$8:$B$11,2,0)="normal",data2!CM74,VLOOKUP(data2!CL74,misc!$A$8:$B$11,2,0)) -> uppershift | Z74: =IF(VLOOKUP(data2!DN74,misc!$A$8:$B$11,2,0)="normal",data2!DO74,VLOOKUP(data2!DN74,misc!$A$8:$B$11,2,0)) -> tight profile | AA74: =IF(ISERROR(AVERAGE(INDEX(JPM1_,ROW(A74)-2),(INDEX(JPM2_,ROW(A74)-2),(INDEX(JPM3_,ROW(A74)-2)))))=TRUE,"N/A",AVERAGE(INDEX(JPM1_,ROW(A74)-2),(INDEX(JPM2_,ROW(A74)-2),(INDEX(JPM3_,ROW(A74)-2))))) -> #ERROR!
F75: profiling | V75: =SUM(G75:K75) -> 0 | W75: =SUM(L75:P75) -> 0 | X75: =IF(VLOOKUP(data2!BJ75,misc!$A$8:$B$11,2,0)="normal",data2!BK75,VLOOKUP(data2!BJ75,misc!$A$8:$B$11,2,0)) -> undershift | Y75: =IF(VLOOKUP(data2!CL75,misc!$A$8:$B$11,2,0)="normal",data2!CM75,VLOOKUP(data2!CL75,misc!$A$8:$B$11,2,0)) -> uppershift | Z75: =IF(VLOOKUP(data2!DN75,misc!$A$8:$B$11,2,0)="normal",data2!DO75,VLOOKUP(data2!DN75,misc!$A$8:$B$11,2,0)) -> tight profile | AA75: =IF(ISERROR(AVERAGE(INDEX(JPM1_,ROW(A75)-2),(INDEX(JPM2_,ROW(A75)-2),(INDEX(JPM3_,ROW(A75)-2)))))=TRUE,"N/A",AVERAGE(INDEX(JPM1_,ROW(A75)-2),(INDEX(JPM2_,ROW(A75)-2),(INDEX(JPM3_,ROW(A75)-2))))) -> #ERROR!
F76: profiling | V76: =SUM(G76:K76) -> 0 | W76: =SUM(L76:P76) -> 0 | X76: =IF(VLOOKUP(data2!BJ76,misc!$A$8:$B$11,2,0)="normal",data2!BK76,VLOOKUP(data2!BJ76,misc!$A$8:$B$11,2,0)) -> undershift | Y76: =IF(VLOOKUP(data2!CL76,misc!$A$8:$B$11,2,0)="normal",data2!CM76,VLOOKUP(data2!CL76,misc!$A$8:$B$11,2,0)) -> uppershift | Z76: =IF(VLOOKUP(data2!DN76,misc!$A$8:$B$11,2,0)="normal",data2!DO76,VLOOKUP(data2!DN76,misc!$A$8:$B$11,2,0)) -> tight profile | AA76: =IF(ISERROR(AVERAGE(INDEX(JPM1_,ROW(A76)-2),(INDEX(JPM2_,ROW(A76)-2),(INDEX(JPM3_,ROW(A76)-2)))))=TRUE,"N/A",AVERAGE(INDEX(JPM1_,ROW(A76)-2),(INDEX(JPM2_,ROW(A76)-2),(INDEX(JPM3_,ROW(A76)-2))))) -> #ERROR!
F77: profiling | V77: =SUM(G77:K77) -> 0 | W77: =SUM(L77:P77) -> 0 | X77: =IF(VLOOKUP(data2!BJ77,misc!$A$8:$B$11,2,0)="normal",data2!BK77,VLOOKUP(data2!BJ77,misc!$A$8:$B$11,2,0)) -> undershift | Y77: =IF(VLOOKUP(data2!CL77,misc!$A$8:$B$11,2,0)="normal",data2!CM77,VLOOKUP(data2!CL77,misc!$A$8:$B$11,2,0)) -> uppershift | Z77: =IF(VLOOKUP(data2!DN77,misc!$A$8:$B$11,2,0)="normal",data2!DO77,VLOOKUP(data2!DN77,misc!$A$8:$B$11,2,0)) -> tight profile | AA77: =IF(ISERROR(AVERAGE(INDEX(JPM1_,ROW(A77)-2),(INDEX(JPM2_,ROW(A77)-2),(INDEX(JPM3_,ROW(A77)-2)))))=TRUE,"N/A",AVERAGE(INDEX(JPM1_,ROW(A77)-2),(INDEX(JPM2_,ROW(A77)-2),(INDEX(JPM3_,ROW(A77)-2))))) -> #ERROR!
F78: profiling | V78: =SUM(G78:K78) -> 0 | W78: =SUM(L78:P78) -> 0 | X78: =IF(VLOOKUP(data2!BJ78,misc!$A$8:$B$11,2,0)="normal",data2!BK78,VLOOKUP(data2!BJ78,misc!$A$8:$B$11,2,0)) -> undershift | Y78: =IF(VLOOKUP(data2!CL78,misc!$A$8:$B$11,2,0)="normal",data2!CM78,VLOOKUP(data2!CL78,misc!$A$8:$B$11,2,0)) -> uppershift | Z78: =IF(VLOOKUP(data2!DN78,misc!$A$8:$B$11,2,0)="normal",data2!DO78,VLOOKUP(data2!DN78,misc!$A$8:$B$11,2,0)) -> tight profile | AA78: =IF(ISERROR(AVERAGE(INDEX(JPM1_,ROW(A78)-2),(INDEX(JPM2_,ROW(A78)-2),(INDEX(JPM3_,ROW(A78)-2)))))=TRUE,"N/A",AVERAGE(INDEX(JPM1_,ROW(A78)-2),(INDEX(JPM2_,ROW(A78)-2),(INDEX(JPM3_,ROW(A78)-2))))) -> #ERROR!
F79: profiling | V79: =SUM(G79:K79) -> 0 | W79: =SUM(L79:P79) -> 0 | X79: =IF(VLOOKUP(data2!BJ79,misc!$A$8:$B$11,2,0)="normal",data2!BK79,VLOOKUP(data2!BJ79,misc!$A$8:$B$11,2,0)) -> undershift | Y79: =IF(VLOOKUP(data2!CL79,misc!$A$8:$B$11,2,0)="normal",data2!CM79,VLOOKUP(data2!CL79,misc!$A$8:$B$11,2,0)) -> uppershift | Z79: =IF(VLOOKUP(data2!DN79,misc!$A$8:$B$11,2,0)="normal",data2!DO79,VLOOKUP(data2!DN79,misc!$A$8:$B$11,2,0)) -> tight profile | AA79: =IF(ISERROR(AVERAGE(INDEX(JPM1_,ROW(A79)-2),(INDEX(JPM2_,ROW(A79)-2),(INDEX(JPM3_,ROW(A79)-2)))))=TRUE,"N/A",AVERAGE(INDEX(JPM1_,ROW(A79)-2),(INDEX(JPM2_,ROW(A79)-2),(INDEX(JPM3_,ROW(A79)-2))))) -> #ERROR!
F80: profiling | V80: =SUM(G80:K80) -> 0 | W80: =SUM(L80:P80) -> 0 | X80: =IF(VLOOKUP(data2!BJ80,misc!$A$8:$B$11,2,0)="normal",data2!BK80,VLOOKUP(data2!BJ80,misc!$A$8:$B$11,2,0)) -> undershift | Y80: =IF(VLOOKUP(data2!CL80,misc!$A$8:$B$11,2,0)="normal",data2!CM80,VLOOKUP(data2!CL80,misc!$A$8:$B$11,2,0)) -> uppershift | Z80: =IF(VLOOKUP(data2!DN80,misc!$A$8:$B$11,2,0)="normal",data2!DO80,VLOOKUP(data2!DN80,misc!$A$8:$B$11,2,0)) -> tight profile | AA80: =IF(ISERROR(AVERAGE(INDEX(JPM1_,ROW(A80)-2),(INDEX(JPM2_,ROW(A80)-2),(INDEX(JPM3_,ROW(A80)-2)))))=TRUE,"N/A",AVERAGE(INDEX(JPM1_,ROW(A80)-2),(INDEX(JPM2_,ROW(A80)-2),(INDEX(JPM3_,ROW(A80)-2))))) -> #ERROR!
F81: profiling | V81: =SUM(G81:K81) -> 0 | W81: =SUM(L81:P81) -> 0 | X81: =IF(VLOOKUP(data2!BJ81,misc!$A$8:$B$11,2,0)="normal",data2!BK81,VLOOKUP(data2!BJ81,misc!$A$8:$B$11,2,0)) -> undershift | Y81: =IF(VLOOKUP(data2!CL81,misc!$A$8:$B$11,2,0)="normal",data2!CM81,VLOOKUP(data2!CL81,misc!$A$8:$B$11,2,0)) -> uppershift | Z81: =IF(VLOOKUP(data2!DN81,misc!$A$8:$B$11,2,0)="normal",data2!DO81,VLOOKUP(data2!DN81,misc!$A$8:$B$11,2,0)) -> tight profile | AA81: =IF(ISERROR(AVERAGE(INDEX(JPM1_,ROW(A81)-2),(INDEX(JPM2_,ROW(A81)-2),(INDEX(JPM3_,ROW(A81)-2)))))=TRUE,"N/A",AVERAGE(INDEX(JPM1_,ROW(A81)-2),(INDEX(JPM2_,ROW(A81)-2),(INDEX(JPM3_,ROW(A81)-2))))) -> #ERROR!
F82: profiling | V82: =SUM(G82:K82) -> 0 | W82: =SUM(L82:P82) -> 0 | X82: =IF(VLOOKUP(data2!BJ82,misc!$A$8:$B$11,2,0)="normal",data2!BK82,VLOOKUP(data2!BJ82,misc!$A$8:$B$11,2,0)) -> undershift | Y82: =IF(VLOOKUP(data2!CL82,misc!$A$8:$B$11,2,0)="normal",data2!CM82,VLOOKUP(data2!CL82,misc!$A$8:$B$11,2,0)) -> uppershift | Z82: =IF(VLOOKUP(data2!DN82,misc!$A$8:$B$11,2,0)="normal",data2!DO82,VLOOKUP(data2!DN82,misc!$A$8:$B$11,2,0)) -> tight profile | AA82: =IF(ISERROR(AVERAGE(INDEX(JPM1_,ROW(A82)-2),(INDEX(JPM2_,ROW(A82)-2),(INDEX(JPM3_,ROW(A82)-2)))))=TRUE,"N/A",AVERAGE(INDEX(JPM1_,ROW(A82)-2),(INDEX(JPM2_,ROW(A82)-2),(INDEX(JPM3_,ROW(A82)-2))))) -> #ERROR!
F83: profiling | V83: =SUM(G83:K83) -> 0 | W83: =SUM(L83:P83) -> 0 | X83: =IF(VLOOKUP(data2!BJ83,misc!$A$8:$B$11,2,0)="normal",data2!BK83,VLOOKUP(data2!BJ83,misc!$A$8:$B$11,2,0)) -> undershift | Y83: =IF(VLOOKUP(data2!CL83,misc!$A$8:$B$11,2,0)="normal",data2!CM83,VLOOKUP(data2!CL83,misc!$A$8:$B$11,2,0)) -> uppershift | Z83: =IF(VLOOKUP(data2!DN83,misc!$A$8:$B$11,2,0)="normal",data2!DO83,VLOOKUP(data2!DN83,misc!$A$8:$B$11,2,0)) -> tight profile | AA83: =IF(ISERROR(AVERAGE(INDEX(JPM1_,ROW(A83)-2),(INDEX(JPM2_,ROW(A83)-2),(INDEX(JPM3_,ROW(A83)-2)))))=TRUE,"N/A",AVERAGE(INDEX(JPM1_,ROW(A83)-2),(INDEX(JPM2_,ROW(A83)-2),(INDEX(JPM3_,ROW(A83)-2))))) -> #ERROR!
... F123: profiling | V123: =SUM(G123:K123) -> 0 | W123: =SUM(L123:P123) -> 0 | X123: =IF(VLOOKUP(data2!BJ123,misc!$A$8:$B$11,2,0)="normal",data2!BK123,VLOOKUP(data2!BJ123,misc!$A$8:$B$11,2,0)) -> undershift | Y123: =IF(VLOOKUP(data2!CL123,misc!$A$8:$B$11,2,0)="normal",data2!CM123,VLOOKUP(data2!CL123,misc!$A$8:$B$11,2,0)) -> uppershift | Z123: =IF(VLOOKUP(data2!DN123,misc!$A$8:$B$11,2,0)="normal",data2!DO123,VLOOKUP(data2!DN123,misc!$A$8:$B$11,2,0)) -> tight profile | AA123: =IF(ISERROR(AVERAGE(INDEX(JPM1_,ROW(A123)-2),(INDEX(JPM2_,ROW(A123)-2),(INDEX(JPM3_,ROW(A123)-2)))))=TRUE,"N/A",AVERAGE(INDEX(JPM1_,ROW(A123)-2),(INDEX(JPM2_,ROW(A123)-2),(INDEX(JPM3_,ROW(A123)-2))))) -> #ERROR!
F124: profiling | Q124: =G124-L124 -> 0 | R124: =H124-M124 -> 0 | S124: =I124-N124 -> 0 | T124: =J124-O124 -> 0 | U124: =K124+P124 -> 0 | V124: =SUM(G124:K124) -> 0 | W124: =SUM(L124:P124) -> 0 | X124: =IF(VLOOKUP(data2!BJ124,misc!$A$8:$B$11,2,0)="normal",data2!BK124,VLOOKUP(data2!BJ124,misc!$A$8:$B$11,2,0)) -> undershift | Y124: =IF(VLOOKUP(data2!CL124,misc!$A$8:$B$11,2,0)="normal",data2!CM124,VLOOKUP(data2!CL124,misc!$A$8:$B$11,2,0)) -> uppershift | Z124: =IF(VLOOKUP(data2!DN124,misc!$A$8:$B$11,2,0)="normal",data2!DO124,VLOOKUP(data2!DN124,misc!$A$8:$B$11,2,0)) -> tight profile | AA124: =IF(ISERROR(AVERAGE(INDEX(JPM1_,ROW(A124)-2),(INDEX(JPM2_,ROW(A124)-2),(INDEX(JPM3_,ROW(A124)-2)))))=TRUE,"N/A",AVERAGE(INDEX(JPM1_,ROW(A124)-2),(INDEX(JPM2_,ROW(A124)-2),(INDEX(JPM3_,ROW(A124)-2))))) -> #ERROR!
Q125: =G125-L125 -> 0 | R125: =H125-M125 -> 0 | S125: =I125-N125 -> 0 | T125: =J125-O125 -> 0 | U125: =K125+P125 -> 0 | V125: =SUM(G125:K125) -> 0 | W125: =SUM(L125:P125) -> 0 | X125: =IF(VLOOKUP(data2!BJ125,misc!$A$8:$B$11,2,0)="normal",data2!BK125,VLOOKUP(data2!BJ125,misc!$A$8:$B$11,2,0)) -> undershift | Y125: =IF(VLOOKUP(data2!CL125,misc!$A$8:$B$11,2,0)="normal",data2!CM125,VLOOKUP(data2!CL125,misc!$A$8:$B$11,2,0)) -> uppershift | Z125: =IF(VLOOKUP(data2!DN125,misc!$A$8:$B$11,2,0)="normal",data2!DO125,VLOOKUP(data2!DN125,misc!$A$8:$B$11,2,0)) -> tight profile | AA125: =IF(ISERROR(AVERAGE(INDEX(JPM1_,ROW(A125)-2),(INDEX(JPM2_,ROW(A125)-2),(INDEX(JPM3_,ROW(A125)-2)))))=TRUE,"N/A",AVERAGE(INDEX(JPM1_,ROW(A125)-2),(INDEX(JPM2_,ROW(A125)-2),(INDEX(JPM3_,ROW(A125)-2))))) -> #ERROR!
Q126: =G126-L126 -> 0 | R126: =H126-M126 -> 0 | S126: =I126-N126 -> 0 | T126: =J126-O126 -> 0 | U126: =K126+P126 -> 0 | V126: =SUM(G126:K126) -> 0 | W126: =SUM(L126:P126) -> 0 | X126: =IF(VLOOKUP(data2!BJ126,misc!$A$8:$B$11,2,0)="normal",data2!BK126,VLOOKUP(data2!BJ126,misc!$A$8:$B$11,2,0)) -> undershift | Y126: =IF(VLOOKUP(data2!CL126,misc!$A$8:$B$11,2,0)="normal",data2!CM126,VLOOKUP(data2!CL126,misc!$A$8:$B$11,2,0)) -> uppershift | Z126: =IF(VLOOKUP(data2!DN126,misc!$A$8:$B$11,2,0)="normal",data2!DO126,VLOOKUP(data2!DN126,misc!$A$8:$B$11,2,0)) -> tight profile | AA126: =IF(ISERROR(AVERAGE(INDEX(JPM1_,ROW(A126)-2),(INDEX(JPM2_,ROW(A126)-2),(INDEX(JPM3_,ROW(A126)-2)))))=TRUE,"N/A",AVERAGE(INDEX(JPM1_,ROW(A126)-2),(INDEX(JPM2_,ROW(A126)-2),(INDEX(JPM3_,ROW(A126)-2))))) -> #ERROR!
Q127: =G127-L127 -> 0 | R127: =H127-M127 -> 0 | S127: =I127-N127 -> 0 | T127: =J127-O127 -> 0 | U127: =K127+P127 -> 0 | V127: =SUM(G127:K127) -> 0 | W127: =SUM(L127:P127) -> 0 | X127: =IF(VLOOKUP(data2!BJ127,misc!$A$8:$B$11,2,0)="normal",data2!BK127,VLOOKUP(data2!BJ127,misc!$A$8:$B$11,2,0)) -> undershift | Y127: =IF(VLOOKUP(data2!CL127,misc!$A$8:$B$11,2,0)="normal",data2!CM127,VLOOKUP(data2!CL127,misc!$A$8:$B$11,2,0)) -> uppershift | Z127: =IF(VLOOKUP(data2!DN127,misc!$A$8:$B$11,2,0)="normal",data2!DO127,VLOOKUP(data2!DN127,misc!$A$8:$B$11,2,0)) -> tight profile | AA127: =IF(ISERROR(AVERAGE(INDEX(JPM1_,ROW(A127)-2),(INDEX(JPM2_,ROW(A127)-2),(INDEX(JPM3_,ROW(A127)-2)))))=TRUE,"N/A",AVERAGE(INDEX(JPM1_,ROW(A127)-2),(INDEX(JPM2_,ROW(A127)-2),(INDEX(JPM3_,ROW(A127)-2))))) -> #ERROR!
Q128: =G128-L128 -> 0 | R128: =H128-M128 -> 0 | S128: =I128-N128 -> 0 | T128: =J128-O128 -> 0 | U128: =K128+P128 -> 0 | V128: =SUM(G128:K128) -> 0 | W128: =SUM(L128:P128) -> 0 | X128: =IF(VLOOKUP(data2!BJ128,misc!$A$8:$B$11,2,0)="normal",data2!BK128,VLOOKUP(data2!BJ128,misc!$A$8:$B$11,2,0)) -> undershift | Y128: =IF(VLOOKUP(data2!CL128,misc!$A$8:$B$11,2,0)="normal",data2!CM128,VLOOKUP(data2!CL128,misc!$A$8:$B$11,2,0)) -> uppershift | Z128: =IF(VLOOKUP(data2!DN128,misc!$A$8:$B$11,2,0)="normal",data2!DO128,VLOOKUP(data2!DN128,misc!$A$8:$B$11,2,0)) -> tight profile | AA128: =IF(ISERROR(AVERAGE(INDEX(JPM1_,ROW(A128)-2),(INDEX(JPM2_,ROW(A128)-2),(INDEX(JPM3_,ROW(A128)-2)))))=TRUE,"N/A",AVERAGE(INDEX(JPM1_,ROW(A128)-2),(INDEX(JPM2_,ROW(A128)-2),(INDEX(JPM3_,ROW(A128)-2))))) -> #ERROR!
Q129: =G129-L129 -> 0 | R129: =H129-M129 -> 0 | S129: =I129-N129 -> 0 | T129: =J129-O129 -> 0 | U129: =K129+P129 -> 0 | V129: =SUM(G129:K129) -> 0 | W129: =SUM(L129:P129) -> 0 | X129: =IF(VLOOKUP(data2!BJ129,misc!$A$8:$B$11,2,0)="normal",data2!BK129,VLOOKUP(data2!BJ129,misc!$A$8:$B$11,2,0)) -> undershift | Y129: =IF(VLOOKUP(data2!CL129,misc!$A$8:$B$11,2,0)="normal",data2!CM129,VLOOKUP(data2!CL129,misc!$A$8:$B$11,2,0)) -> uppershift | Z129: =IF(VLOOKUP(data2!DN129,misc!$A$8:$B$11,2,0)="normal",data2!DO129,VLOOKUP(data2!DN129,misc!$A$8:$B$11,2,0)) -> tight profile | AA129: =IF(ISERROR(AVERAGE(INDEX(JPM1_,ROW(A129)-2),(INDEX(JPM2_,ROW(A129)-2),(INDEX(JPM3_,ROW(A129)-2)))))=TRUE,"N/A",AVERAGE(INDEX(JPM1_,ROW(A129)-2),(INDEX(JPM2_,ROW(A129)-2),(INDEX(JPM3_,ROW(A129)-2))))) -> #ERROR!
Q130: =G130-L130 -> 0 | R130: =H130-M130 -> 0 | S130: =I130-N130 -> 0 | T130: =J130-O130 -> 0 | U130: =K130+P130 -> 0 | V130: =SUM(G130:K130) -> 0 | W130: =SUM(L130:P130) -> 0 | X130: =IF(VLOOKUP(data2!BJ130,misc!$A$8:$B$11,2,0)="normal",data2!BK130,VLOOKUP(data2!BJ130,misc!$A$8:$B$11,2,0)) -> undershift | Y130: =IF(VLOOKUP(data2!CL130,misc!$A$8:$B$11,2,0)="normal",data2!CM130,VLOOKUP(data2!CL130,misc!$A$8:$B$11,2,0)) -> uppershift | Z130: =IF(VLOOKUP(data2!DN130,misc!$A$8:$B$11,2,0)="normal",data2!DO130,VLOOKUP(data2!DN130,misc!$A$8:$B$11,2,0)) -> tight profile | AA130: =IF(ISERROR(AVERAGE(INDEX(JPM1_,ROW(A130)-2),(INDEX(JPM2_,ROW(A130)-2),(INDEX(JPM3_,ROW(A130)-2)))))=TRUE,"N/A",AVERAGE(INDEX(JPM1_,ROW(A130)-2),(INDEX(JPM2_,ROW(A130)-2),(INDEX(JPM3_,ROW(A130)-2))))) -> #ERROR!
Q131: =G131-L131 -> 0 | R131: =H131-M131 -> 0 | S131: =I131-N131 -> 0 | T131: =J131-O131 -> 0 | U131: =K131+P131 -> 0 | V131: =SUM(G131:K131) -> 0 | W131: =SUM(L131:P131) -> 0 | X131: =IF(VLOOKUP(data2!BJ131,misc!$A$8:$B$11,2,0)="normal",data2!BK131,VLOOKUP(data2!BJ131,misc!$A$8:$B$11,2,0)) -> undershift | Y131: =IF(VLOOKUP(data2!CL131,misc!$A$8:$B$11,2,0)="normal",data2!CM131,VLOOKUP(data2!CL131,misc!$A$8:$B$11,2,0)) -> uppershift | Z131: =IF(VLOOKUP(data2!DN131,misc!$A$8:$B$11,2,0)="normal",data2!DO131,VLOOKUP(data2!DN131,misc!$A$8:$B$11,2,0)) -> tight profile | AA131: =IF(ISERROR(AVERAGE(INDEX(JPM1_,ROW(A131)-2),(INDEX(JPM2_,ROW(A131)-2),(INDEX(JPM3_,ROW(A131)-2)))))=TRUE,"N/A",AVERAGE(INDEX(JPM1_,ROW(A131)-2),(INDEX(JPM2_,ROW(A131)-2),(INDEX(JPM3_,ROW(A131)-2))))) -> #ERROR!
Q132: =G132-L132 -> 0 | R132: =H132-M132 -> 0 | S132: =I132-N132 -> 0 | T132: =J132-O132 -> 0 | U132: =K132+P132 -> 0 | V132: =SUM(G132:K132) -> 0 | W132: =SUM(L132:P132) -> 0 | X132: =IF(VLOOKUP(data2!BJ132,misc!$A$8:$B$11,2,0)="normal",data2!BK132,VLOOKUP(data2!BJ132,misc!$A$8:$B$11,2,0)) -> undershift | Y132: =IF(VLOOKUP(data2!CL132,misc!$A$8:$B$11,2,0)="normal",data2!CM132,VLOOKUP(data2!CL132,misc!$A$8:$B$11,2,0)) -> uppershift | Z132: =IF(VLOOKUP(data2!DN132,misc!$A$8:$B$11,2,0)="normal",data2!DO132,VLOOKUP(data2!DN132,misc!$A$8:$B$11,2,0)) -> tight profile | AA132: =IF(ISERROR(AVERAGE(INDEX(JPM1_,ROW(A132)-2),(INDEX(JPM2_,ROW(A132)-2),(INDEX(JPM3_,ROW(A132)-2)))))=TRUE,"N/A",AVERAGE(INDEX(JPM1_,ROW(A132)-2),(INDEX(JPM2_,ROW(A132)-2),(INDEX(JPM3_,ROW(A132)-2))))) -> #ERROR!
Q133: =G133-L133 -> 0 | R133: =H133-M133 -> 0 | S133: =I133-N133 -> 0 | T133: =J133-O133 -> 0 | U133: =K133+P133 -> 0 | V133: =SUM(G133:K133) -> 0 | W133: =SUM(L133:P133) -> 0 | X133: =IF(VLOOKUP(data2!BJ133,misc!$A$8:$B$11,2,0)="normal",data2!BK133,VLOOKUP(data2!BJ133,misc!$A$8:$B$11,2,0)) -> undershift | Y133: =IF(VLOOKUP(data2!CL133,misc!$A$8:$B$11,2,0)="normal",data2!CM133,VLOOKUP(data2!CL133,misc!$A$8:$B$11,2,0)) -> uppershift | Z133: =IF(VLOOKUP(data2!DN133,misc!$A$8:$B$11,2,0)="normal",data2!DO133,VLOOKUP(data2!DN133,misc!$A$8:$B$11,2,0)) -> tight profile | AA133: =IF(ISERROR(AVERAGE(INDEX(JPM1_,ROW(A133)-2),(INDEX(JPM2_,ROW(A133)-2),(INDEX(JPM3_,ROW(A133)-2)))))=TRUE,"N/A",AVERAGE(INDEX(JPM1_,ROW(A133)-2),(INDEX(JPM2_,ROW(A133)-2),(INDEX(JPM3_,ROW(A133)-2))))) -> #ERROR!
Q134: =G134-L134 -> 0 | R134: =H134-M134 -> 0 | S134: =I134-N134 -> 0 | T134: =J134-O134 -> 0 | U134: =K134+P134 -> 0 | V134: =SUM(G134:K134) -> 0 | W134: =SUM(L134:P134) -> 0 | X134: =IF(VLOOKUP(data2!BJ134,misc!$A$8:$B$11,2,0)="normal",data2!BK134,VLOOKUP(data2!BJ134,misc!$A$8:$B$11,2,0)) -> undershift | Y134: =IF(VLOOKUP(data2!CL134,misc!$A$8:$B$11,2,0)="normal",data2!CM134,VLOOKUP(data2!CL134,misc!$A$8:$B$11,2,0)) -> uppershift | Z134: =IF(VLOOKUP(data2!DN134,misc!$A$8:$B$11,2,0)="normal",data2!DO134,VLOOKUP(data2!DN134,misc!$A$8:$B$11,2,0)) -> tight profile | AA134: =IF(ISERROR(AVERAGE(INDEX(JPM1_,ROW(A134)-2),(INDEX(JPM2_,ROW(A134)-2),(INDEX(JPM3_,ROW(A134)-2)))))=TRUE,"N/A",AVERAGE(INDEX(JPM1_,ROW(A134)-2),(INDEX(JPM2_,ROW(A134)-2),(INDEX(JPM3_,ROW(A134)-2))))) -> #ERROR!
Q135: =G135-L135 -> 0 | R135: =H135-M135 -> 0 | S135: =I135-N135 -> 0 | T135: =J135-O135 -> 0 | U135: =K135+P135 -> 0 | V135: =SUM(G135:K135) -> 0 | W135: =SUM(L135:P135) -> 0 | X135: =IF(VLOOKUP(data2!BJ135,misc!$A$8:$B$11,2,0)="normal",data2!BK135,VLOOKUP(data2!BJ135,misc!$A$8:$B$11,2,0)) -> undershift | Y135: =IF(VLOOKUP(data2!CL135,misc!$A$8:$B$11,2,0)="normal",data2!CM135,VLOOKUP(data2!CL135,misc!$A$8:$B$11,2,0)) -> uppershift | Z135: =IF(VLOOKUP(data2!DN135,misc!$A$8:$B$11,2,0)="normal",data2!DO135,VLOOKUP(data2!DN135,misc!$A$8:$B$11,2,0)) -> tight profile | AA135: =IF(ISERROR(AVERAGE(INDEX(JPM1_,ROW(A135)-2),(INDEX(JPM2_,ROW(A135)-2),(INDEX(JPM3_,ROW(A135)-2)))))=TRUE,"N/A",AVERAGE(INDEX(JPM1_,ROW(A135)-2),(INDEX(JPM2_,ROW(A135)-2),(INDEX(JPM3_,ROW(A135)-2))))) -> #ERROR!
Q136: =G136-L136 -> 0 | R136: =H136-M136 -> 0 | S136: =I136-N136 -> 0 | T136: =J136-O136 -> 0 | U136: =K136+P136 -> 0 | V136: =SUM(G136:K136) -> 0 | W136: =SUM(L136:P136) -> 0 | X136: =IF(VLOOKUP(data2!BJ136,misc!$A$8:$B$11,2,0)="normal",data2!BK136,VLOOKUP(data2!BJ136,misc!$A$8:$B$11,2,0)) -> undershift | Y136: =IF(VLOOKUP(data2!CL136,misc!$A$8:$B$11,2,0)="normal",data2!CM136,VLOOKUP(data2!CL136,misc!$A$8:$B$11,2,0)) -> uppershift | Z136: =IF(VLOOKUP(data2!DN136,misc!$A$8:$B$11,2,0)="normal",data2!DO136,VLOOKUP(data2!DN136,misc!$A$8:$B$11,2,0)) -> tight profile | AA136: =IF(ISERROR(AVERAGE(INDEX(JPM1_,ROW(A136)-2),(INDEX(JPM2_,ROW(A136)-2),(INDEX(JPM3_,ROW(A136)-2)))))=TRUE,"N/A",AVERAGE(INDEX(JPM1_,ROW(A136)-2),(INDEX(JPM2_,ROW(A136)-2),(INDEX(JPM3_,ROW(A136)-2))))) -> #ERROR!
... Q250: =G250-L250 -> 0 | R250: =H250-M250 -> 0 | S250: =I250-N250 -> 0 | T250: =J250-O250 -> 0 | U250: =K250+P250 -> 0 | V250: =SUM(G250:K250) -> 0 | W250: =SUM(L250:P250) -> 0 | X250: =IF(VLOOKUP(data2!BJ250,misc!$A$8:$B$11,2,0)="normal",data2!BK250,VLOOKUP(data2!BJ250,misc!$A$8:$B$11,2,0)) -> undershift | Y250: =IF(VLOOKUP(data2!CL250,misc!$A$8:$B$11,2,0)="normal",data2!CM250,VLOOKUP(data2!CL250,misc!$A$8:$B$11,2,0)) -> uppershift | Z250: =IF(VLOOKUP(data2!DN250,misc!$A$8:$B$11,2,0)="normal",data2!DO250,VLOOKUP(data2!DN250,misc!$A$8:$B$11,2,0)) -> tight profile | AA250: =IF(ISERROR(AVERAGE(INDEX(JPM1_,ROW(A250)-2),(INDEX(JPM2_,ROW(A250)-2),(INDEX(JPM3_,ROW(A250)-2)))))=TRUE,"N/A",AVERAGE(INDEX(JPM1_,ROW(A250)-2),(INDEX(JPM2_,ROW(A250)-2),(INDEX(JPM3_,ROW(A250)-2))))) -> #ERROR!

Sheet data2
A1: {=data!A1:W2} | B1: Jenis | D1: Tanggal | G1: Most | L1: Least | Q1: Change | V1: Cek | X1: tentukan koordinat grafiknya | Y1: D | Z1: I | AA1: S | AB1: C | AC1: D | AD1: I | AE1: S | AF1: C | AG1: D | AH1: I | AI1: S | AJ1: C | AK1: cari grafik 1 tertinggi | AP1: rank grafik 1 | AU1: profil graf 1 | AZ1: profil dom 1 | BE1: profil res 1 | BJ1: profil final 1 | BM1: cari grafik 2 tertinggi | BR1: rank grafik 2 | BW1: profil graf 2 | CB1: profil dom 2 | CG1: profil res 2 | CL1: profil final 2 | CO1: cari grafik 3 tertinggi | CT1: rank grafik 3 | CY1: profil graf 3 | DD1: profil dom 3 | DI1: profil res 3 | DN1: profil final 3 | DR1: buat individual jpm | ED1: pilihan job profile | EH1: compare job profile
A2: Nama | B2: Kelamin | C2: Nomor | D2: Tes | E2: Posisi | F2: Tujuan | G2: D | H2: I | I2: S | J2: C | K2: B | L2: D | M2: I | N2: S | O2: C | P2: B | Q2: D | R2: I | S2: S | T2: C | U2: B | V2: M | W2: L | Y2: PG1MD | Z2: PG1MI | AA2: PG1MS | AB2: PG1MC | AC2: PG2LD | AD2: PG2LI | AE2: PG2LS | AF2: PG2LC | AG2: PG3CD | AH2: PG3CI | AI2: PG3CS | AJ2: PG3CC | AL2: 1 | AM2: 2 | AN2: 3 | AO2: 4 | AQ2: 1 | AR2: 2 | AS2: 3 | AT2: 4 | AV2: 1 | AW2: 2 | AX2: 3 | AY2: 4 | BA2: 1 | BB2: 2 | BC2: 3 | BD2: 4 | BF2: 1 | BG2: 2 | BH2: 3 | BI2: 4 | BJ2: cek1 | BK2: prof1 | BN2: 1 | BO2: 2 | BP2: 3 | BQ2: 4 | BS2: 1 | BT2: 2 | BU2: 3 | BV2: 4 | BX2: 1 | BY2: 2 | BZ2: 3 | CA2: 4 | CC2: 1 | CD2: 2 | CE2: 3 | CF2: 4 | CH2: 1 | CI2: 2 | CJ2: 3 | CK2: 4 | CL2: cek2 | CM2: prof2 | CP2: 1 | CQ2: 2 | CR2: 3 | CS2: 4 | CU2: 1 | CV2: 2 | CW2: 3 | CX2: 4 | CZ2: 1 | DA2: 2 | DB2: 3 | DC2: 4 | DE2: 1 | DF2: 2 | DG2: 3 | DH2: 4 | DJ2: 1 | DK2: 2 | DL2: 3 | DM2: 4 | DN2: cek3 | DO2: prof3 | DP2: CEKGRAF | DQ2: unique | DR2: D1ijpm | DS2: I1ijpm | DT2: S1ijpm | DU2: C1ijpm | DV2: D2ijpm | DW2: I2ijpm | DX2: S2ijpm | DY2: C2ijpm | DZ2: D3ijpm | EA2: I3ijpm | EB2: S3ijpm | EC2: C3ijpm | ED2: JD | EE2: JI | EF2: JS | EG2: JC | EH2: c1D | EI2: c1I | EJ2: c1S | EK2: c1C | EL2: cJPM1 | EM2: JPM1 | EN2: c2D | EO2: c2I | EP2: c2S | EQ2: c2C | ER2: cJPM2 | ES2: JPM2 | ET2: c3D | EU2: c3I | EV2: c3S | EW2: c3C | EX2: cJPM3 | EY2: JPM3
A3: =data!A3 -> Andre Setiawan | B3: =data!B3 -> Pria | C3: =data!C3 | D3: =data!D3 -> 44291 | E3: =data!E3 | F3: =data!F3 -> profiling | G3: =data!G3 -> 2 | H3: =data!H3 -> 0 | ... W3: =data!W3 -> 24 | Y3: =VLOOKUP(G3,tableD1,2,0) -> 9 | Z3: =VLOOKUP(H3,tableI1,2,0) -> 3 | AA3: =VLOOKUP(I3,table1S,2,0) -> 15 | AB3: =VLOOKUP(J3,table1C,2,0) -> 28 | AC3: =VLOOKUP(L3,table2D,2,0) -> 16 | AD3: =VLOOKUP(M3,table2I,2,0) -> 9 | AE3: =VLOOKUP(N3,table2S,2,0) -> 24 | AF3: =VLOOKUP(O3,table2C,2,0) -> 31 | AG3: =VLOOKUP(Q3,table3D,2,0) -> 14 | AH3: =VLOOKUP(R3,table3I,2,0) -> 7 | AI3: =VLOOKUP(S3,table3S,2,0) -> 19 | AJ3: =VLOOKUP(T3,table3C,2,0) -> 30 | AL3: =VALUE(Y3&AL$2) -> 91 | AM3: =VALUE(Z3&AM$2) -> 32 | AN3: =VALUE(AA3&AN$2) -> 153 | AO3: =VALUE(AB3&AO$2) -> 284 | AQ3: =LARGE($AL3:$AO3,AQ$2) -> 284 | AR3: =LARGE($AL3:$AO3,AR$2) -> 153 | AS3: =LARGE($AL3:$AO3,AS$2) -> 91 | AT3: =LARGE($AL3:$AO3,AT$2) -> 32 | AV3: =VLOOKUP(VALUE(RIGHT(AQ3,1)),misc!$A$2:$B$5,2,0) -> C | AW3: =VLOOKUP(VALUE(RIGHT(AR3,1)),misc!$A$2:$B$5,2,0) -> S | AX3: =VLOOKUP(VALUE(RIGHT(AS3,1)),misc!$A$2:$B$5,2,0) -> D | AY3: =VLOOKUP(VALUE(RIGHT(AT3,1)),misc!$A$2:$B$5,2,0) -> I | BA3: =IF(VALUE(AQ3)>=170,AV3,"") -> C | BB3: =IF(VALUE(AR3)>=170,AW3,"") | BC3: =IF(VALUE(AS3)>=170,AX3,"") | BD3: =IF(VALUE(AT3)>=170,AY3,"") | BF3: =IF(VALUE(AQ3)<170,AV3,"") | BG3: =IF(VALUE(AR3)<170,AW3,"") -> S | BH3: =IF(VALUE(AS3)<170,AX3,"") -> D | BI3: =IF(VALUE(AT3)<170,AY3,"") -> I | BJ3: =IF(AND(Y3<17,Z3<17,AA3<17,AB3<17),1,IF(AND(Y3>=17,Z3>=17,AA3>=17,AB3>=17),2,IF(AND(Y3>12,Y3<21,Z3>12,Z3<21,AA3>12,AA3<21,AB3>12,AB3<21),3,4))) -> 4 | BK3: =TRIM(BA3&BB3&BC3&BD3) -> C | BN3: =VALUE(AC3&BN$2) -> 161 | BO3: =VALUE(AD3&BO$2) -> 92 | BP3: =VALUE(AE3&BP$2) -> 243 | BQ3: =VALUE(AF3&BQ$2) -> 314 | BS3: =LARGE($BN3:$BQ3,BS$2) -> 314 | BT3: =LARGE($BN3:$BQ3,BT$2) -> 243 | BU3: =LARGE($BN3:$BQ3,BU$2) -> 161 | BV3: =LARGE($BN3:$BQ3,BV$2) -> 92 | BX3: =VLOOKUP(VALUE(RIGHT(BS3,1)),misc!$A$2:$B$5,2,0) -> C | BY3: =VLOOKUP(VALUE(RIGHT(BT3,1)),misc!$A$2:$B$5,2,0) -> S | BZ3: =VLOOKUP(VALUE(RIGHT(BU3,1)),misc!$A$2:$B$5,2,0) -> D | CA3: =VLOOKUP(VALUE(RIGHT(BV3,1)),misc!$A$2:$B$5,2,0) -> I | CC3: =IF(VALUE(BS3)>=170,BX3,"") -> C | CD3: =IF(VALUE(BT3)>=170,BY3,"") -> S | CE3: =IF(VALUE(BU3)>=170,BZ3,"") | CF3: =IF(VALUE(BV3)>=170,CA3,"") | CH3: =IF(VALUE(BS3)<170,BX3,"") | CI3: =IF(VALUE(BT3)<170,BY3,"") | CJ3: =IF(VALUE(BU3)<170,BZ3,"") -> D | CK3: =IF(VALUE(BV3)<170,CA3,"") -> I | CL3: =IF(AND(AC3<17,AD3<17,AE3<17,AF3<17),1,IF(AND(AC3>=17,AD3>=17,AE3>=17,AF3>=17),2,IF(AND(AC3>12,AC3<21,AD3>12,AD3<21,AE3>12,AE3<21,AF3>12,AF3<21),3,4))) -> 4 | CM3: =TRIM(CC3&CD3&CE3&CF3) -> CS | CP3: =VALUE(AG3&CP$2) -> 141 | CQ3: =VALUE(AH3&CQ$2) -> 72 | CR3: =VALUE(AI3&CR$2) -> 193 | CS3: =VALUE(AJ3&CS$2) -> 304 | CU3: =LARGE($CP3:$CS3,CU$2) -> 304 | CV3: =LARGE($CP3:$CS3,CV$2) -> 193 | CW3: =LARGE($CP3:$CS3,CW$2) -> 141 | CX3: =LARGE($CP3:$CS3,CX$2) -> 72 | CZ3: =VLOOKUP(VALUE(RIGHT(CU3,1)),misc!$A$2:$B$5,2,0) -> C | DA3: =VLOOKUP(VALUE(RIGHT(CV3,1)),misc!$A$2:$B$5,2,0) -> S | DB3: =VLOOKUP(VALUE(RIGHT(CW3,1)),misc!$A$2:$B$5,2,0) -> D | DC3: =VLOOKUP(VALUE(RIGHT(CX3,1)),misc!$A$2:$B$5,2,0) -> I | DE3: =IF(VALUE(CU3)>=170,CZ3,"") -> C | DF3: =IF(VALUE(CV3)>=170,DA3,"") -> S | DG3: =IF(VALUE(CW3)>=170,DB3,"") | DH3: =IF(VALUE(CX3)>=170,DC3,"") | DJ3: =IF(VALUE(CU3)<170,CZ3,"") | DK3: =IF(VALUE(CV3)<170,DA3,"") | DL3: =IF(VALUE(CW3)<170,DB3,"") -> D | DM3: =IF(VALUE(CX3)<170,DC3,"") -> I | DN3: =IF(AND(AG3<17,AH3<17,AI3<17,AJ3<17),1,IF(AND(AG3>=17,AH3>=17,AI3>=17,AJ3>=17),2,IF(AND(AG3>12,AG3<21,AH3>12,AH3<21,AI3>12,AI3<21,AJ3>12,AJ3<21),3,4))) -> 4 | DO3: =TRIM(DE3&DF3&DG3&DH3) -> CS | DP3: =BJ3&CL3&DN3 -> 444 | DQ3: =A3&G3&H3&I3&J3&L3&M3&N3&O3 -> Andre Setiawan204106731 | DR3: =VLOOKUP(G3,tableD1,3,0) -> 3 | DS3: =VLOOKUP(H3,tableI1,3,0) -> 1 | DT3: =VLOOKUP(I3,table1S,3,0) -> 4 | DU3: =VLOOKUP(J3,table1C,3,0) -> 8 | DV3: =VLOOKUP(L3,table2D,3,0) -> 4 | DW3: =VLOOKUP(M3,table2I,3,0) -> 3 | DX3: =VLOOKUP(N3,table2S,3,0) -> 6 | DY3: =VLOOKUP(O3,table2C,3,0) -> 8 | DZ3: =VLOOKUP(Q3,table3D,3,0) -> 4 | EA3: =VLOOKUP(R3,table3I,3,0) -> 2 | EB3: =VLOOKUP(S3,table3S,3,0) -> 5 | EC3: =VLOOKUP(T3,table3C,3,0) -> 8 | ED3: {=VLOOKUP(INDEX(JD,data!$AA$1),key!$J$3:$L$27,3,0)} -> 6 | EE3: {=VLOOKUP(INDEX(JI,data!$AA$1),key!$J$3:$L$27,3,0)} -> 4 | EF3: {=VLOOKUP(INDEX(JS,data!$AA$1),key!$J$3:$L$27,3,0)} -> 4 | EG3: {=VLOOKUP(INDEX(JC,data!$AA$1),key!$J$3:$L$27,3,0)} -> 7 | EH3: =VLOOKUP(DR3,tabel_jpm,ED3+1,0) -> 16 | EI3: =VLOOKUP(DS3,tabel_jpm,EE3+1,0) -> 16 | EJ3: =VLOOKUP(DT3,tabel_jpm,EF3+1,0) -> 28 | EK3: =VLOOKUP(DU3,tabel_jpm,EG3+1,0) -> 24 | EL3: =IF(B3="Pria",VLOOKUP(AVERAGE(EH3:EK3),agreement_p,4),VLOOKUP(AVERAGE(EH3:EK3),agreement_w,4)) -> 62 | EM3: =IF(DP3<>"444","N/A",EL3) -> 62 | EN3: =VLOOKUP(DV3,tabel_jpm,ED3+1,0) -> 20 | EO3: =VLOOKUP(DW3,tabel_jpm,EE3+1,0) -> 24 | EP3: =VLOOKUP(DX3,tabel_jpm,EF3+1,0) -> 20 | EQ3: =VLOOKUP(DY3,tabel_jpm,EG3+1,0) -> 24 | ER3: =IF(B3="Pria",VLOOKUP(AVERAGE(EN3:EQ3),agreement_p,4),VLOOKUP(AVERAGE(EN3:EQ3),agreement_w,4)) -> 72 | ES3: =IF(DP3<>"444","N/A",ER3) -> 72 | ET3: =VLOOKUP(DZ3,tabel_jpm,ED3+1,0) -> 20 | EU3: =VLOOKUP(EA3,tabel_jpm,EE3+1,0) -> 20 | EV3: =VLOOKUP(EB3,tabel_jpm,EF3+1,0) -> 24 | EW3: =VLOOKUP(EC3,tabel_jpm,EG3+1,0) -> 24 | EX3: =IF(B3="Pria",VLOOKUP(AVERAGE(ET3:EW3),agreement_p,4),VLOOKUP(AVERAGE(ET3:EW3),agreement_w,4)) -> 72 | EY3: =IF(DP3<>"444","N/A",EX3) -> 72
A4: =data!A4 -> Helmi Kurniawan | B4: =data!B4 -> Pria | C4: =data!C4 | D4: =data!D4 | E4: =data!E4 | F4: =data!F4 -> profiling | G4: =data!G4 -> 3 | H4: =data!H4 -> 3 | ... W4: =data!W4 -> 24 | Y4: =VLOOKUP(G4,tableD1,2,0) -> 11 | Z4: =VLOOKUP(H4,tableI1,2,0) -> 15 | AA4: =VLOOKUP(I4,table1S,2,0) -> 22 | AB4: =VLOOKUP(J4,table1C,2,0) -> 18 | AC4: =VLOOKUP(L4,table2D,2,0) -> 15 | AD4: =VLOOKUP(M4,table2I,2,0) -> 18 | AE4: =VLOOKUP(N4,table2S,2,0) -> 28 | AF4: =VLOOKUP(O4,table2C,2,0) -> 18 | AG4: =VLOOKUP(Q4,table3D,2,0) -> 14 | AH4: =VLOOKUP(R4,table3I,2,0) -> 16 | AI4: =VLOOKUP(S4,table3S,2,0) -> 24 | AJ4: =VLOOKUP(T4,table3C,2,0) -> 18 | AL4: =VALUE(Y4&AL$2) -> 111 | AM4: =VALUE(Z4&AM$2) -> 152 | AN4: =VALUE(AA4&AN$2) -> 223 | AO4: =VALUE(AB4&AO$2) -> 184 | AQ4: =LARGE($AL4:$AO4,AQ$2) -> 223 | AR4: =LARGE($AL4:$AO4,AR$2) -> 184 | AS4: =LARGE($AL4:$AO4,AS$2) -> 152 | AT4: =LARGE($AL4:$AO4,AT$2) -> 111 | AV4: =VLOOKUP(VALUE(RIGHT(AQ4,1)),misc!$A$2:$B$5,2,0) -> S | AW4: =VLOOKUP(VALUE(RIGHT(AR4,1)),misc!$A$2:$B$5,2,0) -> C | AX4: =VLOOKUP(VALUE(RIGHT(AS4,1)),misc!$A$2:$B$5,2,0) -> I | AY4: =VLOOKUP(VALUE(RIGHT(AT4,1)),misc!$A$2:$B$5,2,0) -> D | BA4: =IF(VALUE(AQ4)>=170,AV4,"") -> S | BB4: =IF(VALUE(AR4)>=170,AW4,"") -> C | BC4: =IF(VALUE(AS4)>=170,AX4,"") | BD4: =IF(VALUE(AT4)>=170,AY4,"") | BF4: =IF(VALUE(AQ4)<170,AV4,"") | BG4: =IF(VALUE(AR4)<170,AW4,"") | BH4: =IF(VALUE(AS4)<170,AX4,"") -> I | BI4: =IF(VALUE(AT4)<170,AY4,"") -> D | BJ4: =IF(AND(Y4<17,Z4<17,AA4<17,AB4<17),1,IF(AND(Y4>=17,Z4>=17,AA4>=17,AB4>=17),2,IF(AND(Y4>12,Y4<21,Z4>12,Z4<21,AA4>12,AA4<21,AB4>12,AB4<21),3,4))) -> 4 | BK4: =TRIM(BA4&BB4&BC4&BD4) -> SC | BN4: =VALUE(AC4&BN$2) -> 151 | BO4: =VALUE(AD4&BO$2) -> 182 | BP4: =VALUE(AE4&BP$2) -> 283 | BQ4: =VALUE(AF4&BQ$2) -> 184 | BS4: =LARGE($BN4:$BQ4,BS$2) -> 283 | BT4: =LARGE($BN4:$BQ4,BT$2) -> 184 | BU4: =LARGE($BN4:$BQ4,BU$2) -> 182 | BV4: =LARGE($BN4:$BQ4,BV$2) -> 151 | BX4: =VLOOKUP(VALUE(RIGHT(BS4,1)),misc!$A$2:$B$5,2,0) -> S | BY4: =VLOOKUP(VALUE(RIGHT(BT4,1)),misc!$A$2:$B$5,2,0) -> C | BZ4: =VLOOKUP(VALUE(RIGHT(BU4,1)),misc!$A$2:$B$5,2,0) -> I | CA4: =VLOOKUP(VALUE(RIGHT(BV4,1)),misc!$A$2:$B$5,2,0) -> D | CC4: =IF(VALUE(BS4)>=170,BX4,"") -> S | CD4: =IF(VALUE(BT4)>=170,BY4,"") -> C | CE4: =IF(VALUE(BU4)>=170,BZ4,"") -> I | CF4: =IF(VALUE(BV4)>=170,CA4,"") | CH4: =IF(VALUE(BS4)<170,BX4,"") | CI4: =IF(VALUE(BT4)<170,BY4,"") | CJ4: =IF(VALUE(BU4)<170,BZ4,"") | CK4: =IF(VALUE(BV4)<170,CA4,"") -> D | CL4: =IF(AND(AC4<17,AD4<17,AE4<17,AF4<17),1,IF(AND(AC4>=17,AD4>=17,AE4>=17,AF4>=17),2,IF(AND(AC4>12,AC4<21,AD4>12,AD4<21,AE4>12,AE4<21,AF4>12,AF4<21),3,4))) -> 4 | CM4: =TRIM(CC4&CD4&CE4&CF4) -> SCI | CP4: =VALUE(AG4&CP$2) -> 141 | CQ4: =VALUE(AH4&CQ$2) -> 162 | CR4: =VALUE(AI4&CR$2) -> 243 | CS4: =VALUE(AJ4&CS$2) -> 184 | CU4: =LARGE($CP4:$CS4,CU$2) -> 243 | CV4: =LARGE($CP4:$CS4,CV$2) -> 184 | CW4: =LARGE($CP4:$CS4,CW$2) -> 162 | CX4: =LARGE($CP4:$CS4,CX$2) -> 141 | CZ4: =VLOOKUP(VALUE(RIGHT(CU4,1)),misc!$A$2:$B$5,2,0) -> S | DA4: =VLOOKUP(VALUE(RIGHT(CV4,1)),misc!$A$2:$B$5,2,0) -> C | DB4: =VLOOKUP(VALUE(RIGHT(CW4,1)),misc!$A$2:$B$5,2,0) -> I | DC4: =VLOOKUP(VALUE(RIGHT(CX4,1)),misc!$A$2:$B$5,2,0) -> D | DE4: =IF(VALUE(CU4)>=170,CZ4,"") -> S | DF4: =IF(VALUE(CV4)>=170,DA4,"") -> C | DG4: =IF(VALUE(CW4)>=170,DB4,"") | DH4: =IF(VALUE(CX4)>=170,DC4,"") | DJ4: =IF(VALUE(CU4)<170,CZ4,"") | DK4: =IF(VALUE(CV4)<170,DA4,"") | DL4: =IF(VALUE(CW4)<170,DB4,"") -> I | DM4: =IF(VALUE(CX4)<170,DC4,"") -> D | DN4: =IF(AND(AG4<17,AH4<17,AI4<17,AJ4<17),1,IF(AND(AG4>=17,AH4>=17,AI4>=17,AJ4>=17),2,IF(AND(AG4>12,AG4<21,AH4>12,AH4<21,AI4>12,AI4<21,AJ4>12,AJ4<21),3,4))) -> 4 | DO4: =TRIM(DE4&DF4&DG4&DH4) -> SC | DP4: =BJ4&CL4&DN4 -> 444 | DQ4: =A4&G4&H4&I4&J4&L4&M4&N4&O4 -> Helmi Kurniawan33747426 | DR4: =VLOOKUP(G4,tableD1,3,0) -> 3 | DS4: =VLOOKUP(H4,tableI1,3,0) -> 4 | DT4: =VLOOKUP(I4,table1S,3,0) -> 6 | DU4: =VLOOKUP(J4,table1C,3,0) -> 5 | DV4: =VLOOKUP(L4,table2D,3,0) -> 4 | DW4: =VLOOKUP(M4,table2I,3,0) -> 5 | DX4: =VLOOKUP(N4,table2S,3,0) -> 7 | DY4: =VLOOKUP(O4,table2C,3,0) -> 5 | DZ4: =VLOOKUP(Q4,table3D,3,0) -> 4 | EA4: =VLOOKUP(R4,table3I,3,0) -> 4 | EB4: =VLOOKUP(S4,table3S,3,0) -> 6 | EC4: =VLOOKUP(T4,table3C,3,0) -> 5 | ED4: {=VLOOKUP(INDEX(JD,data!$AA$1),key!$J$3:$L$27,3,0)} -> 6 | EE4: {=VLOOKUP(INDEX(JI,data!$AA$1),key!$J$3:$L$27,3,0)} -> 4 | EF4: {=VLOOKUP(INDEX(JS,data!$AA$1),key!$J$3:$L$27,3,0)} -> 4 | EG4: {=VLOOKUP(INDEX(JC,data!$AA$1),key!$J$3:$L$27,3,0)} -> 7 | EH4: =VLOOKUP(DR4,tabel_jpm,ED4+1,0) -> 16 | EI4: =VLOOKUP(DS4,tabel_jpm,EE4+1,0) -> 28 | EJ4: =VLOOKUP(DT4,tabel_jpm,EF4+1,0) -> 20 | EK4: =VLOOKUP(DU4,tabel_jpm,EG4+1,0) -> 20 | EL4: =IF(B4="Pria",VLOOKUP(AVERAGE(EH4:EK4),agreement_p,4),VLOOKUP(AVERAGE(EH4:EK4),agreement_w,4)) -> 62 | EM4: =IF(DP4<>"444","N/A",EL4) -> 62 | EN4: =VLOOKUP(DV4,tabel_jpm,ED4+1,0) -> 20 | EO4: =VLOOKUP(DW4,tabel_jpm,EE4+1,0) -> 24 | EP4: =VLOOKUP(DX4,tabel_jpm,EF4+1,0) -> 16 | EQ4: =VLOOKUP(DY4,tabel_jpm,EG4+1,0) -> 20 | ER4: =IF(B4="Pria",VLOOKUP(AVERAGE(EN4:EQ4),agreement_p,4),VLOOKUP(AVERAGE(EN4:EQ4),agreement_w,4)) -> 59 | ES4: =IF(DP4<>"444","N/A",ER4) -> 59 | ET4: =VLOOKUP(DZ4,tabel_jpm,ED4+1,0) -> 20 | EU4: =VLOOKUP(EA4,tabel_jpm,EE4+1,0) -> 28 | EV4: =VLOOKUP(EB4,tabel_jpm,EF4+1,0) -> 20 | EW4: =VLOOKUP(EC4,tabel_jpm,EG4+1,0) -> 20 | EX4: =IF(B4="Pria",VLOOKUP(AVERAGE(ET4:EW4),agreement_p,4),VLOOKUP(AVERAGE(ET4:EW4),agreement_w,4)) -> 72 | EY4: =IF(DP4<>"444","N/A",EX4) -> 72
A5: =data!A5 -> Indah Nopitasari | B5: =data!B5 -> Wanita | C5: =data!C5 | D5: =data!D5 | E5: =data!E5 | F5: =data!F5 -> profiling | G5: =data!G5 -> 0 | H5: =data!H5 -> 1 | ... W5: =data!W5 -> 24 | Y5: =VLOOKUP(G5,tableD1,2,0) -> 4 | Z5: =VLOOKUP(H5,tableI1,2,0) -> 7 | AA5: =VLOOKUP(I5,table1S,2,0) -> 26 | AB5: =VLOOKUP(J5,table1C,2,0) -> 18 | AC5: =VLOOKUP(L5,table2D,2,0) -> 3 | AD5: =VLOOKUP(M5,table2I,2,0) -> 22 | AE5: =VLOOKUP(N5,table2S,2,0) -> 32 | AF5: =VLOOKUP(O5,table2C,2,0) -> 28 | AG5: =VLOOKUP(Q5,table3D,2,0) -> 3 | AH5: =VLOOKUP(R5,table3I,2,0) -> 14 | AI5: =VLOOKUP(S5,table3S,2,0) -> 30 | AJ5: =VLOOKUP(T5,table3C,2,0) -> 24 | AL5: =VALUE(Y5&AL$2) -> 41 | AM5: =VALUE(Z5&AM$2) -> 72 | AN5: =VALUE(AA5&AN$2) -> 263 | AO5: =VALUE(AB5&AO$2) -> 184 | AQ5: =LARGE($AL5:$AO5,AQ$2) -> 263 | AR5: =LARGE($AL5:$AO5,AR$2) -> 184 | AS5: =LARGE($AL5:$AO5,AS$2) -> 72 | AT5: =LARGE($AL5:$AO5,AT$2) -> 41 | AV5: =VLOOKUP(VALUE(RIGHT(AQ5,1)),misc!$A$2:$B$5,2,0) -> S | AW5: =VLOOKUP(VALUE(RIGHT(AR5,1)),misc!$A$2:$B$5,2,0) -> C | AX5: =VLOOKUP(VALUE(RIGHT(AS5,1)),misc!$A$2:$B$5,2,0) -> I | AY5: =VLOOKUP(VALUE(RIGHT(AT5,1)),misc!$A$2:$B$5,2,0) -> D | BA5: =IF(VALUE(AQ5)>=170,AV5,"") -> S | BB5: =IF(VALUE(AR5)>=170,AW5,"") -> C | BC5: =IF(VALUE(AS5)>=170,AX5,"") | BD5: =IF(VALUE(AT5)>=170,AY5,"") | BF5: =IF(VALUE(AQ5)<170,AV5,"") | BG5: =IF(VALUE(AR5)<170,AW5,"") | BH5: =IF(VALUE(AS5)<170,AX5,"") -> I | BI5: =IF(VALUE(AT5)<170,AY5,"") -> D | BJ5: =IF(AND(Y5<17,Z5<17,AA5<17,AB5<17),1,IF(AND(Y5>=17,Z5>=17,AA5>=17,AB5>=17),2,IF(AND(Y5>12,Y5<21,Z5>12,Z5<21,AA5>12,AA5<21,AB5>12,AB5<21),3,4))) -> 4 | BK5: =TRIM(BA5&BB5&BC5&BD5) -> SC | BN5: =VALUE(AC5&BN$2) -> 31 | BO5: =VALUE(AD5&BO$2) -> 222 | BP5: =VALUE(AE5&BP$2) -> 323 | BQ5: =VALUE(AF5&BQ$2) -> 284 | BS5: =LARGE($BN5:$BQ5,BS$2) -> 323 | BT5: =LARGE($BN5:$BQ5,BT$2) -> 284 | BU5: =LARGE($BN5:$BQ5,BU$2) -> 222 | BV5: =LARGE($BN5:$BQ5,BV$2) -> 31 | BX5: =VLOOKUP(VALUE(RIGHT(BS5,1)),misc!$A$2:$B$5,2,0) -> S | BY5: =VLOOKUP(VALUE(RIGHT(BT5,1)),misc!$A$2:$B$5,2,0) -> C | BZ5: =VLOOKUP(VALUE(RIGHT(BU5,1)),misc!$A$2:$B$5,2,0) -> I | CA5: =VLOOKUP(VALUE(RIGHT(BV5,1)),misc!$A$2:$B$5,2,0) -> D | CC5: =IF(VALUE(BS5)>=170,BX5,"") -> S | CD5: =IF(VALUE(BT5)>=170,BY5,"") -> C | CE5: =IF(VALUE(BU5)>=170,BZ5,"") -> I | CF5: =IF(VALUE(BV5)>=170,CA5,"") | CH5: =IF(VALUE(BS5)<170,BX5,"") | CI5: =IF(VALUE(BT5)<170,BY5,"") | CJ5: =IF(VALUE(BU5)<170,BZ5,"") | CK5: =IF(VALUE(BV5)<170,CA5,"") -> D | CL5: =IF(AND(AC5<17,AD5<17,AE5<17,AF5<17),1,IF(AND(AC5>=17,AD5>=17,AE5>=17,AF5>=17),2,IF(AND(AC5>12,AC5<21,AD5>12,AD5<21,AE5>12,AE5<21,AF5>12,AF5<21),3,4))) -> 4 | CM5: =TRIM(CC5&CD5&CE5&CF5) -> SCI | CP5: =VALUE(AG5&CP$2) -> 31 | CQ5: =VALUE(AH5&CQ$2) -> 142 | CR5: =VALUE(AI5&CR$2) -> 303 | CS5: =VALUE(AJ5&CS$2) -> 244 | CU5: =LARGE($CP5:$CS5,CU$2) -> 303 | CV5: =LARGE($CP5:$CS5,CV$2) -> 244 | CW5: =LARGE($CP5:$CS5,CW$2) -> 142 | CX5: =LARGE($CP5:$CS5,CX$2) -> 31 | CZ5: =VLOOKUP(VALUE(RIGHT(CU5,1)),misc!$A$2:$B$5,2,0) -> S | DA5: =VLOOKUP(VALUE(RIGHT(CV5,1)),misc!$A$2:$B$5,2,0) -> C | DB5: =VLOOKUP(VALUE(RIGHT(CW5,1)),misc!$A$2:$B$5,2,0) -> I | DC5: =VLOOKUP(VALUE(RIGHT(CX5,1)),misc!$A$2:$B$5,2,0) -> D | DE5: =IF(VALUE(CU5)>=170,CZ5,"") -> S | DF5: =IF(VALUE(CV5)>=170,DA5,"") -> C | DG5: =IF(VALUE(CW5)>=170,DB5,"") | DH5: =IF(VALUE(CX5)>=170,DC5,"") | DJ5: =IF(VALUE(CU5)<170,CZ5,"") | DK5: =IF(VALUE(CV5)<170,DA5,"") | DL5: =IF(VALUE(CW5)<170,DB5,"") -> I | DM5: =IF(VALUE(CX5)<170,DC5,"") -> D | DN5: =IF(AND(AG5<17,AH5<17,AI5<17,AJ5<17),1,IF(AND(AG5>=17,AH5>=17,AI5>=17,AJ5>=17),2,IF(AND(AG5>12,AG5<21,AH5>12,AH5<21,AI5>12,AI5<21,AJ5>12,AJ5<21),3,4))) -> 4 | DO5: =TRIM(DE5&DF5&DG5&DH5) -> SC | DP5: =BJ5&CL5&DN5 -> 444 | DQ5: =A5&G5&H5&I5&J5&L5&M5&N5&O5 -> Indah Nopitasari0111416302 | DR5: =VLOOKUP(G5,tableD1,3,0) -> 1 | DS5: =VLOOKUP(H5,tableI1,3,0) -> 2 | DT5: =VLOOKUP(I5,table1S,3,0) -> 7 | DU5: =VLOOKUP(J5,table1C,3,0) -> 5 | DV5: =VLOOKUP(L5,table2D,3,0) -> 1 | DW5: =VLOOKUP(M5,table2I,3,0) -> 6 | DX5: =VLOOKUP(N5,table2S,3,0) -> 8 | DY5: =VLOOKUP(O5,table2C,3,0) -> 7 | DZ5: =VLOOKUP(Q5,table3D,3,0) -> 1 | EA5: =VLOOKUP(R5,table3I,3,0) -> 4 | EB5: =VLOOKUP(S5,table3S,3,0) -> 8 | EC5: =VLOOKUP(T5,table3C,3,0) -> 6 | ED5: {=VLOOKUP(INDEX(JD,data!$AA$1),key!$J$3:$L$27,3,0)} -> 6 | EE5: {=VLOOKUP(INDEX(JI,data!$AA$1),key!$J$3:$L$27,3,0)} -> 4 | EF5: {=VLOOKUP(INDEX(JS,data!$AA$1),key!$J$3:$L$27,3,0)} -> 4 | EG5: {=VLOOKUP(INDEX(JC,data!$AA$1),key!$J$3:$L$27,3,0)} -> 7 | EH5: =VLOOKUP(DR5,tabel_jpm,ED5+1,0) -> 8 | EI5: =VLOOKUP(DS5,tabel_jpm,EE5+1,0) -> 20 | EJ5: =VLOOKUP(DT5,tabel_jpm,EF5+1,0) -> 16 | EK5: =VLOOKUP(DU5,tabel_jpm,EG5+1,0) -> 20 | EL5: =IF(B5="Pria",VLOOKUP(AVERAGE(EH5:EK5),agreement_p,4),VLOOKUP(AVERAGE(EH5:EK5),agreement_w,4)) -> 48 | EM5: =IF(DP5<>"444","N/A",EL5) -> 48 | EN5: =VLOOKUP(DV5,tabel_jpm,ED5+1,0) -> 8 | EO5: =VLOOKUP(DW5,tabel_jpm,EE5+1,0) -> 20 | EP5: =VLOOKUP(DX5,tabel_jpm,EF5+1,0) -> 12 | EQ5: =VLOOKUP(DY5,tabel_jpm,EG5+1,0) -> 28 | ER5: =IF(B5="Pria",VLOOKUP(AVERAGE(EN5:EQ5),agreement_p,4),VLOOKUP(AVERAGE(EN5:EQ5),agreement_w,4)) -> 50 | ES5: =IF(DP5<>"444","N/A",ER5) -> 50 | ET5: =VLOOKUP(DZ5,tabel_jpm,ED5+1,0) -> 8 | EU5: =VLOOKUP(EA5,tabel_jpm,EE5+1,0) -> 28 | EV5: =VLOOKUP(EB5,tabel_jpm,EF5+1,0) -> 12 | EW5: =VLOOKUP(EC5,tabel_jpm,EG5+1,0) -> 24 | EX5: =IF(B5="Pria",VLOOKUP(AVERAGE(ET5:EW5),agreement_p,4),VLOOKUP(AVERAGE(ET5:EW5),agreement_w,4)) -> 51 | EY5: =IF(DP5<>"444","N/A",EX5) -> 51
A6: =data!A6 -> Ayub Putra Utama | B6: =data!B6 -> Pria | C6: =data!C6 | D6: =data!D6 | E6: =data!E6 | F6: =data!F6 -> profiling | G6: =data!G6 -> 3 | H6: =data!H6 -> 4 | ... W6: =data!W6 -> 24 | Y6: =VLOOKUP(G6,tableD1,2,0) -> 11 | Z6: =VLOOKUP(H6,tableI1,2,0) -> 18 | AA6: =VLOOKUP(I6,table1S,2,0) -> 22 | AB6: =VLOOKUP(J6,table1C,2,0) -> 10 | AC6: =VLOOKUP(L6,table2D,2,0) -> 15 | AD6: =VLOOKUP(M6,table2I,2,0) -> 12 | AE6: =VLOOKUP(N6,table2S,2,0) -> 31 | AF6: =VLOOKUP(O6,table2C,2,0) -> 28 | AG6: =VLOOKUP(Q6,table3D,2,0) -> 14 | AH6: =VLOOKUP(R6,table3I,2,0) -> 14 | AI6: =VLOOKUP(S6,table3S,2,0) -> 26 | AJ6: =VLOOKUP(T6,table3C,2,0) -> 19 | AL6: =VALUE(Y6&AL$2) -> 111 | AM6: =VALUE(Z6&AM$2) -> 182 | AN6: =VALUE(AA6&AN$2) -> 223 | AO6: =VALUE(AB6&AO$2) -> 104 | AQ6: =LARGE($AL6:$AO6,AQ$2) -> 223 | AR6: =LARGE($AL6:$AO6,AR$2) -> 182 | AS6: =LARGE($AL6:$AO6,AS$2) -> 111 | AT6: =LARGE($AL6:$AO6,AT$2) -> 104 | AV6: =VLOOKUP(VALUE(RIGHT(AQ6,1)),misc!$A$2:$B$5,2,0) -> S | AW6: =VLOOKUP(VALUE(RIGHT(AR6,1)),misc!$A$2:$B$5,2,0) -> I | AX6: =VLOOKUP(VALUE(RIGHT(AS6,1)),misc!$A$2:$B$5,2,0) -> D | AY6: =VLOOKUP(VALUE(RIGHT(AT6,1)),misc!$A$2:$B$5,2,0) -> C | BA6: =IF(VALUE(AQ6)>=170,AV6,"") -> S | BB6: =IF(VALUE(AR6)>=170,AW6,"") -> I | BC6: =IF(VALUE(AS6)>=170,AX6,"") | BD6: =IF(VALUE(AT6)>=170,AY6,"") | BF6: =IF(VALUE(AQ6)<170,AV6,"") | BG6: =IF(VALUE(AR6)<170,AW6,"") | BH6: =IF(VALUE(AS6)<170,AX6,"") -> D | BI6: =IF(VALUE(AT6)<170,AY6,"") -> C | BJ6: =IF(AND(Y6<17,Z6<17,AA6<17,AB6<17),1,IF(AND(Y6>=17,Z6>=17,AA6>=17,AB6>=17),2,IF(AND(Y6>12,Y6<21,Z6>12,Z6<21,AA6>12,AA6<21,AB6>12,AB6<21),3,4))) -> 4 | BK6: =TRIM(BA6&BB6&BC6&BD6) -> SI | BN6: =VALUE(AC6&BN$2) -> 151 | BO6: =VALUE(AD6&BO$2) -> 122 | BP6: =VALUE(AE6&BP$2) -> 313 | BQ6: =VALUE(AF6&BQ$2) -> 284 | BS6: =LARGE($BN6:$BQ6,BS$2) -> 313 | BT6: =LARGE($BN6:$BQ6,BT$2) -> 284 | BU6: =LARGE($BN6:$BQ6,BU$2) -> 151 | BV6: =LARGE($BN6:$BQ6,BV$2) -> 122 | BX6: =VLOOKUP(VALUE(RIGHT(BS6,1)),misc!$A$2:$B$5,2,0) -> S | BY6: =VLOOKUP(VALUE(RIGHT(BT6,1)),misc!$A$2:$B$5,2,0) -> C | BZ6: =VLOOKUP(VALUE(RIGHT(BU6,1)),misc!$A$2:$B$5,2,0) -> D | CA6: =VLOOKUP(VALUE(RIGHT(BV6,1)),misc!$A$2:$B$5,2,0) -> I | CC6: =IF(VALUE(BS6)>=170,BX6,"") -> S | CD6: =IF(VALUE(BT6)>=170,BY6,"") -> C | CE6: =IF(VALUE(BU6)>=170,BZ6,"") | CF6: =IF(VALUE(BV6)>=170,CA6,"") | CH6: =IF(VALUE(BS6)<170,BX6,"") | CI6: =IF(VALUE(BT6)<170,BY6,"") | CJ6: =IF(VALUE(BU6)<170,BZ6,"") -> D | CK6: =IF(VALUE(BV6)<170,CA6,"") -> I | CL6: =IF(AND(AC6<17,AD6<17,AE6<17,AF6<17),1,IF(AND(AC6>=17,AD6>=17,AE6>=17,AF6>=17),2,IF(AND(AC6>12,AC6<21,AD6>12,AD6<21,AE6>12,AE6<21,AF6>12,AF6<21),3,4))) -> 4 | CM6: =TRIM(CC6&CD6&CE6&CF6) -> SC | CP6: =VALUE(AG6&CP$2) -> 141 | CQ6: =VALUE(AH6&CQ$2) -> 142 | CR6: =VALUE(AI6&CR$2) -> 263 | CS6: =VALUE(AJ6&CS$2) -> 194 | CU6: =LARGE($CP6:$CS6,CU$2) -> 263 | CV6: =LARGE($CP6:$CS6,CV$2) -> 194 | CW6: =LARGE($CP6:$CS6,CW$2) -> 142 | CX6: =LARGE($CP6:$CS6,CX$2) -> 141 | CZ6: =VLOOKUP(VALUE(RIGHT(CU6,1)),misc!$A$2:$B$5,2,0) -> S | DA6: =VLOOKUP(VALUE(RIGHT(CV6,1)),misc!$A$2:$B$5,2,0) -> C | DB6: =VLOOKUP(VALUE(RIGHT(CW6,1)),misc!$A$2:$B$5,2,0) -> I | DC6: =VLOOKUP(VALUE(RIGHT(CX6,1)),misc!$A$2:$B$5,2,0) -> D | DE6: =IF(VALUE(CU6)>=170,CZ6,"") -> S | DF6: =IF(VALUE(CV6)>=170,DA6,"") -> C | DG6: =IF(VALUE(CW6)>=170,DB6,"") | DH6: =IF(VALUE(CX6)>=170,DC6,"") | DJ6: =IF(VALUE(CU6)<170,CZ6,"") | DK6: =IF(VALUE(CV6)<170,DA6,"") | DL6: =IF(VALUE(CW6)<170,DB6,"") -> I | DM6: =IF(VALUE(CX6)<170,DC6,"") -> D | DN6: =IF(AND(AG6<17,AH6<17,AI6<17,AJ6<17),1,IF(AND(AG6>=17,AH6>=17,AI6>=17,AJ6>=17),2,IF(AND(AG6>12,AG6<21,AH6>12,AH6<21,AI6>12,AI6<21,AJ6>12,AJ6<21),3,4))) -> 4 | DO6: =TRIM(DE6&DF6&DG6&DH6) -> SC | DP6: =BJ6&CL6&DN6 -> 444 | DQ6: =A6&G6&H6&I6&J6&L6&M6&N6&O6 -> Ayub Putra Utama34827612 | DR6: =VLOOKUP(G6,tableD1,3,0) -> 3 | DS6: =VLOOKUP(H6,tableI1,3,0) -> 5 | DT6: =VLOOKUP(I6,table1S,3,0) -> 6 | DU6: =VLOOKUP(J6,table1C,3,0) -> 3 | DV6: =VLOOKUP(L6,table2D,3,0) -> 4 | DW6: =VLOOKUP(M6,table2I,3,0) -> 3 | DX6: =VLOOKUP(N6,table2S,3,0) -> 8 | DY6: =VLOOKUP(O6,table2C,3,0) -> 7 | DZ6: =VLOOKUP(Q6,table3D,3,0) -> 4 | EA6: =VLOOKUP(R6,table3I,3,0) -> 4 | EB6: =VLOOKUP(S6,table3S,3,0) -> 7 | EC6: =VLOOKUP(T6,table3C,3,0) -> 5 | ED6: {=VLOOKUP(INDEX(JD,data!$AA$1),key!$J$3:$L$27,3,0)} -> 6 | EE6: {=VLOOKUP(INDEX(JI,data!$AA$1),key!$J$3:$L$27,3,0)} -> 4 | EF6: {=VLOOKUP(INDEX(JS,data!$AA$1),key!$J$3:$L$27,3,0)} -> 4 | EG6: {=VLOOKUP(INDEX(JC,data!$AA$1),key!$J$3:$L$27,3,0)} -> 7 | EH6: =VLOOKUP(DR6,tabel_jpm,ED6+1,0) -> 16 | EI6: =VLOOKUP(DS6,tabel_jpm,EE6+1,0) -> 24 | EJ6: =VLOOKUP(DT6,tabel_jpm,EF6+1,0) -> 20 | EK6: =VLOOKUP(DU6,tabel_jpm,EG6+1,0) -> 12 | EL6: =IF(B6="Pria",VLOOKUP(AVERAGE(EH6:EK6),agreement_p,4),VLOOKUP(AVERAGE(EH6:EK6),agreement_w,4)) -> 57 | EM6: =IF(DP6<>"444","N/A",EL6) -> 57 | EN6: =VLOOKUP(DV6,tabel_jpm,ED6+1,0) -> 20 | EO6: =VLOOKUP(DW6,tabel_jpm,EE6+1,0) -> 24 | EP6: =VLOOKUP(DX6,tabel_jpm,EF6+1,0) -> 12 | EQ6: =VLOOKUP(DY6,tabel_jpm,EG6+1,0) -> 28 | ER6: =IF(B6="Pria",VLOOKUP(AVERAGE(EN6:EQ6),agreement_p,4),VLOOKUP(AVERAGE(EN6:EQ6),agreement_w,4)) -> 62 | ES6: =IF(DP6<>"444","N/A",ER6) -> 62 | ET6: =VLOOKUP(DZ6,tabel_jpm,ED6+1,0) -> 20 | EU6: =VLOOKUP(EA6,tabel_jpm,EE6+1,0) -> 28 | EV6: =VLOOKUP(EB6,tabel_jpm,EF6+1,0) -> 16 | EW6: =VLOOKUP(EC6,tabel_jpm,EG6+1,0) -> 20 | EX6: =IF(B6="Pria",VLOOKUP(AVERAGE(ET6:EW6),agreement_p,4),VLOOKUP(AVERAGE(ET6:EW6),agreement_w,4)) -> 62 | EY6: =IF(DP6<>"444","N/A",EX6) -> 62
A7: =data!A7 | B7: =data!B7 | C7: =data!C7 | D7: =data!D7 | E7: =data!E7 | F7: =data!F7 | G7: =data!G7 | H7: =data!H7 | ... W7: =data!W7 | Y7: =VLOOKUP(G7,tableD1,2,0) -> 4 | Z7: =VLOOKUP(H7,tableI1,2,0) -> 3 | AA7: =VLOOKUP(I7,table1S,2,0) -> 5 | AB7: =VLOOKUP(J7,table1C,2,0) -> 4 | AC7: =VLOOKUP(L7,table2D,2,0) -> 31 | AD7: =VLOOKUP(M7,table2I,2,0) -> 31 | AE7: =VLOOKUP(N7,table2S,2,0) -> 32 | AF7: =VLOOKUP(O7,table2C,2,0) -> 32 | AG7: =VLOOKUP(Q7,table3D,2,0) -> 16 | AH7: =VLOOKUP(R7,table3I,2,0) -> 18 | AI7: =VLOOKUP(S7,table3S,2,0) -> 19 | AJ7: =VLOOKUP(T7,table3C,2,0) -> 19 | AL7: =VALUE(Y7&AL$2) -> 41 | AM7: =VALUE(Z7&AM$2) -> 32 | AN7: =VALUE(AA7&AN$2) -> 53 | AO7: =VALUE(AB7&AO$2) -> 44 | AQ7: =LARGE($AL7:$AO7,AQ$2) -> 53 | AR7: =LARGE($AL7:$AO7,AR$2) -> 44 | AS7: =LARGE($AL7:$AO7,AS$2) -> 41 | AT7: =LARGE($AL7:$AO7,AT$2) -> 32 | AV7: =VLOOKUP(VALUE(RIGHT(AQ7,1)),misc!$A$2:$B$5,2,0) -> S | AW7: =VLOOKUP(VALUE(RIGHT(AR7,1)),misc!$A$2:$B$5,2,0) -> C | AX7: =VLOOKUP(VALUE(RIGHT(AS7,1)),misc!$A$2:$B$5,2,0) -> D | AY7: =VLOOKUP(VALUE(RIGHT(AT7,1)),misc!$A$2:$B$5,2,0) -> I | BA7: =IF(VALUE(AQ7)>=170,AV7,"") | BB7: =IF(VALUE(AR7)>=170,AW7,"") | BC7: =IF(VALUE(AS7)>=170,AX7,"") | BD7: =IF(VALUE(AT7)>=170,AY7,"") | BF7: =IF(VALUE(AQ7)<170,AV7,"") -> S | BG7: =IF(VALUE(AR7)<170,AW7,"") -> C | BH7: =IF(VALUE(AS7)<170,AX7,"") -> D | BI7: =IF(VALUE(AT7)<170,AY7,"") -> I | BJ7: =IF(AND(Y7<17,Z7<17,AA7<17,AB7<17),1,IF(AND(Y7>=17,Z7>=17,AA7>=17,AB7>=17),2,IF(AND(Y7>12,Y7<21,Z7>12,Z7<21,AA7>12,AA7<21,AB7>12,AB7<21),3,4))) -> 1 | BK7: =TRIM(BA7&BB7&BC7&BD7) | BN7: =VALUE(AC7&BN$2) -> 311 | BO7: =VALUE(AD7&BO$2) -> 312 | BP7: =VALUE(AE7&BP$2) -> 323 | BQ7: =VALUE(AF7&BQ$2) -> 324 | BS7: =LARGE($BN7:$BQ7,BS$2) -> 324 | BT7: =LARGE($BN7:$BQ7,BT$2) -> 323 | BU7: =LARGE($BN7:$BQ7,BU$2) -> 312 | BV7: =LARGE($BN7:$BQ7,BV$2) -> 311 | BX7: =VLOOKUP(VALUE(RIGHT(BS7,1)),misc!$A$2:$B$5,2,0) -> C | BY7: =VLOOKUP(VALUE(RIGHT(BT7,1)),misc!$A$2:$B$5,2,0) -> S | BZ7: =VLOOKUP(VALUE(RIGHT(BU7,1)),misc!$A$2:$B$5,2,0) -> I | CA7: =VLOOKUP(VALUE(RIGHT(BV7,1)),misc!$A$2:$B$5,2,0) -> D | CC7: =IF(VALUE(BS7)>=170,BX7,"") -> C | CD7: =IF(VALUE(BT7)>=170,BY7,"") -> S | CE7: =IF(VALUE(BU7)>=170,BZ7,"") -> I | CF7: =IF(VALUE(BV7)>=170,CA7,"") -> D | CH7: =IF(VALUE(BS7)<170,BX7,"") | CI7: =IF(VALUE(BT7)<170,BY7,"") | CJ7: =IF(VALUE(BU7)<170,BZ7,"") | CK7: =IF(VALUE(BV7)<170,CA7,"") | CL7: =IF(AND(AC7<17,AD7<17,AE7<17,AF7<17),1,IF(AND(AC7>=17,AD7>=17,AE7>=17,AF7>=17),2,IF(AND(AC7>12,AC7<21,AD7>12,AD7<21,AE7>12,AE7<21,AF7>12,AF7<21),3,4))) -> 2 | CM7: =TRIM(CC7&CD7&CE7&CF7) -> CSID | CP7: =VALUE(AG7&CP$2) -> 161 | CQ7: =VALUE(AH7&CQ$2) -> 182 | CR7: =VALUE(AI7&CR$2) -> 193 | CS7: =VALUE(AJ7&CS$2) -> 194 | CU7: =LARGE($CP7:$CS7,CU$2) -> 194 | CV7: =LARGE($CP7:$CS7,CV$2) -> 193 | CW7: =LARGE($CP7:$CS7,CW$2) -> 182 | CX7: =LARGE($CP7:$CS7,CX$2) -> 161 | CZ7: =VLOOKUP(VALUE(RIGHT(CU7,1)),misc!$A$2:$B$5,2,0) -> C | DA7: =VLOOKUP(VALUE(RIGHT(CV7,1)),misc!$A$2:$B$5,2,0) -> S | DB7: =VLOOKUP(VALUE(RIGHT(CW7,1)),misc!$A$2:$B$5,2,0) -> I | DC7: =VLOOKUP(VALUE(RIGHT(CX7,1)),misc!$A$2:$B$5,2,0) -> D | DE7: =IF(VALUE(CU7)>=170,CZ7,"") -> C | DF7: =IF(VALUE(CV7)>=170,DA7,"") -> S | DG7: =IF(VALUE(CW7)>=170,DB7,"") -> I | DH7: =IF(VALUE(CX7)>=170,DC7,"") | DJ7: =IF(VALUE(CU7)<170,CZ7,"") | DK7: =IF(VALUE(CV7)<170,DA7,"") | DL7: =IF(VALUE(CW7)<170,DB7,"") | DM7: =IF(VALUE(CX7)<170,DC7,"") -> D | DN7: =IF(AND(AG7<17,AH7<17,AI7<17,AJ7<17),1,IF(AND(AG7>=17,AH7>=17,AI7>=17,AJ7>=17),2,IF(AND(AG7>12,AG7<21,AH7>12,AH7<21,AI7>12,AI7<21,AJ7>12,AJ7<21),3,4))) -> 3 | DO7: =TRIM(DE7&DF7&DG7&DH7) -> CSI | DP7: =BJ7&CL7&DN7 -> 123 | DQ7: =A7&G7&H7&I7&J7&L7&M7&N7&O7 | DR7: =VLOOKUP(G7,tableD1,3,0) -> 1 | DS7: =VLOOKUP(H7,tableI1,3,0) -> 1 | DT7: =VLOOKUP(I7,table1S,3,0) -> 2 | DU7: =VLOOKUP(J7,table1C,3,0) -> 1 | DV7: =VLOOKUP(L7,table2D,3,0) -> 8 | DW7: =VLOOKUP(M7,table2I,3,0) -> 8 | DX7: =VLOOKUP(N7,table2S,3,0) -> 8 | DY7: =VLOOKUP(O7,table2C,3,0) -> 8 | DZ7: =VLOOKUP(Q7,table3D,3,0) -> 4 | EA7: =VLOOKUP(R7,table3I,3,0) -> 5 | EB7: =VLOOKUP(S7,table3S,3,0) -> 5 | EC7: =VLOOKUP(T7,table3C,3,0) -> 5 | ED7: {=VLOOKUP(INDEX(JD,data!$AA$1),key!$J$3:$L$27,3,0)} -> 6 | EE7: {=VLOOKUP(INDEX(JI,data!$AA$1),key!$J$3:$L$27,3,0)} -> 4 | EF7: {=VLOOKUP(INDEX(JS,data!$AA$1),key!$J$3:$L$27,3,0)} -> 4 | EG7: {=VLOOKUP(INDEX(JC,data!$AA$1),key!$J$3:$L$27,3,0)} -> 7 | EH7: =VLOOKUP(DR7,tabel_jpm,ED7+1,0) -> 8 | EI7: =VLOOKUP(DS7,tabel_jpm,EE7+1,0) -> 16 | EJ7: =VLOOKUP(DT7,tabel_jpm,EF7+1,0) -> 20 | EK7: =VLOOKUP(DU7,tabel_jpm,EG7+1,0) -> 4 | EL7: =IF(B7="Pria",VLOOKUP(AVERAGE(EH7:EK7),agreement_p,4),VLOOKUP(AVERAGE(EH7:EK7),agreement_w,4)) -> 32 | EM7: =IF(DP7<>"444","N/A",EL7) -> N/A | EN7: =VLOOKUP(DV7,tabel_jpm,ED7+1,0) -> 20 | EO7: =VLOOKUP(DW7,tabel_jpm,EE7+1,0) -> 12 | EP7: =VLOOKUP(DX7,tabel_jpm,EF7+1,0) -> 12 | EQ7: =VLOOKUP(DY7,tabel_jpm,EG7+1,0) -> 24 | ER7: =IF(B7="Pria",VLOOKUP(AVERAGE(EN7:EQ7),agreement_p,4),VLOOKUP(AVERAGE(EN7:EQ7),agreement_w,4)) -> 50 | ES7: =IF(DP7<>"444","N/A",ER7) -> N/A | ET7: =VLOOKUP(DZ7,tabel_jpm,ED7+1,0) -> 20 | EU7: =VLOOKUP(EA7,tabel_jpm,EE7+1,0) -> 24 | EV7: =VLOOKUP(EB7,tabel_jpm,EF7+1,0) -> 24 | EW7: =VLOOKUP(EC7,tabel_jpm,EG7+1,0) -> 20 | EX7: =IF(B7="Pria",VLOOKUP(AVERAGE(ET7:EW7),agreement_p,4),VLOOKUP(AVERAGE(ET7:EW7),agreement_w,4)) -> 68 | EY7: =IF(DP7<>"444","N/A",EX7) -> N/A
A8: =data!A8 | B8: =data!B8 | C8: =data!C8 | D8: =data!D8 | E8: =data!E8 | F8: =data!F8 | G8: =data!G8 | H8: =data!H8 | ... W8: =data!W8 | Y8: =VLOOKUP(G8,tableD1,2,0) -> 4 | Z8: =VLOOKUP(H8,tableI1,2,0) -> 3 | AA8: =VLOOKUP(I8,table1S,2,0) -> 5 | AB8: =VLOOKUP(J8,table1C,2,0) -> 4 | AC8: =VLOOKUP(L8,table2D,2,0) -> 31 | AD8: =VLOOKUP(M8,table2I,2,0) -> 31 | AE8: =VLOOKUP(N8,table2S,2,0) -> 32 | AF8: =VLOOKUP(O8,table2C,2,0) -> 32 | AG8: =VLOOKUP(Q8,table3D,2,0) -> 16 | AH8: =VLOOKUP(R8,table3I,2,0) -> 18 | AI8: =VLOOKUP(S8,table3S,2,0) -> 19 | AJ8: =VLOOKUP(T8,table3C,2,0) -> 19 | AL8: =VALUE(Y8&AL$2) -> 41 | AM8: =VALUE(Z8&AM$2) -> 32 | AN8: =VALUE(AA8&AN$2) -> 53 | AO8: =VALUE(AB8&AO$2) -> 44 | AQ8: =LARGE($AL8:$AO8,AQ$2) -> 53 | AR8: =LARGE($AL8:$AO8,AR$2) -> 44 | AS8: =LARGE($AL8:$AO8,AS$2) -> 41 | AT8: =LARGE($AL8:$AO8,AT$2) -> 32 | AV8: =VLOOKUP(VALUE(RIGHT(AQ8,1)),misc!$A$2:$B$5,2,0) -> S | AW8: =VLOOKUP(VALUE(RIGHT(AR8,1)),misc!$A$2:$B$5,2,0) -> C | AX8: =VLOOKUP(VALUE(RIGHT(AS8,1)),misc!$A$2:$B$5,2,0) -> D | AY8: =VLOOKUP(VALUE(RIGHT(AT8,1)),misc!$A$2:$B$5,2,0) -> I | BA8: =IF(VALUE(AQ8)>=170,AV8,"") | BB8: =IF(VALUE(AR8)>=170,AW8,"") | BC8: =IF(VALUE(AS8)>=170,AX8,"") | BD8: =IF(VALUE(AT8)>=170,AY8,"") | BF8: =IF(VALUE(AQ8)<170,AV8,"") -> S | BG8: =IF(VALUE(AR8)<170,AW8,"") -> C | BH8: =IF(VALUE(AS8)<170,AX8,"") -> D | BI8: =IF(VALUE(AT8)<170,AY8,"") -> I | BJ8: =IF(AND(Y8<17,Z8<17,AA8<17,AB8<17),1,IF(AND(Y8>=17,Z8>=17,AA8>=17,AB8>=17),2,IF(AND(Y8>12,Y8<21,Z8>12,Z8<21,AA8>12,AA8<21,AB8>12,AB8<21),3,4))) -> 1 | BK8: =TRIM(BA8&BB8&BC8&BD8) | BN8: =VALUE(AC8&BN$2) -> 311 | BO8: =VALUE(AD8&BO$2) -> 312 | BP8: =VALUE(AE8&BP$2) -> 323 | BQ8: =VALUE(AF8&BQ$2) -> 324 | BS8: =LARGE($BN8:$BQ8,BS$2) -> 324 | BT8: =LARGE($BN8:$BQ8,BT$2) -> 323 | BU8: =LARGE($BN8:$BQ8,BU$2) -> 312 | BV8: =LARGE($BN8:$BQ8,BV$2) -> 311 | BX8: =VLOOKUP(VALUE(RIGHT(BS8,1)),misc!$A$2:$B$5,2,0) -> C | BY8: =VLOOKUP(VALUE(RIGHT(BT8,1)),misc!$A$2:$B$5,2,0) -> S | BZ8: =VLOOKUP(VALUE(RIGHT(BU8,1)),misc!$A$2:$B$5,2,0) -> I | CA8: =VLOOKUP(VALUE(RIGHT(BV8,1)),misc!$A$2:$B$5,2,0) -> D | CC8: =IF(VALUE(BS8)>=170,BX8,"") -> C | CD8: =IF(VALUE(BT8)>=170,BY8,"") -> S | CE8: =IF(VALUE(BU8)>=170,BZ8,"") -> I | CF8: =IF(VALUE(BV8)>=170,CA8,"") -> D | CH8: =IF(VALUE(BS8)<170,BX8,"") | CI8: =IF(VALUE(BT8)<170,BY8,"") | CJ8: =IF(VALUE(BU8)<170,BZ8,"") | CK8: =IF(VALUE(BV8)<170,CA8,"") | CL8: =IF(AND(AC8<17,AD8<17,AE8<17,AF8<17),1,IF(AND(AC8>=17,AD8>=17,AE8>=17,AF8>=17),2,IF(AND(AC8>12,AC8<21,AD8>12,AD8<21,AE8>12,AE8<21,AF8>12,AF8<21),3,4))) -> 2 | CM8: =TRIM(CC8&CD8&CE8&CF8) -> CSID | CP8: =VALUE(AG8&CP$2) -> 161 | CQ8: =VALUE(AH8&CQ$2) -> 182 | CR8: =VALUE(AI8&CR$2) -> 193 | CS8: =VALUE(AJ8&CS$2) -> 194 | CU8: =LARGE($CP8:$CS8,CU$2) -> 194 | CV8: =LARGE($CP8:$CS8,CV$2) -> 193 | CW8: =LARGE($CP8:$CS8,CW$2) -> 182 | CX8: =LARGE($CP8:$CS8,CX$2) -> 161 | CZ8: =VLOOKUP(VALUE(RIGHT(CU8,1)),misc!$A$2:$B$5,2,0) -> C | DA8: =VLOOKUP(VALUE(RIGHT(CV8,1)),misc!$A$2:$B$5,2,0) -> S | DB8: =VLOOKUP(VALUE(RIGHT(CW8,1)),misc!$A$2:$B$5,2,0) -> I | DC8: =VLOOKUP(VALUE(RIGHT(CX8,1)),misc!$A$2:$B$5,2,0) -> D | DE8: =IF(VALUE(CU8)>=170,CZ8,"") -> C | DF8: =IF(VALUE(CV8)>=170,DA8,"") -> S | DG8: =IF(VALUE(CW8)>=170,DB8,"") -> I | DH8: =IF(VALUE(CX8)>=170,DC8,"") | DJ8: =IF(VALUE(CU8)<170,CZ8,"") | DK8: =IF(VALUE(CV8)<170,DA8,"") | DL8: =IF(VALUE(CW8)<170,DB8,"") | DM8: =IF(VALUE(CX8)<170,DC8,"") -> D | DN8: =IF(AND(AG8<17,AH8<17,AI8<17,AJ8<17),1,IF(AND(AG8>=17,AH8>=17,AI8>=17,AJ8>=17),2,IF(AND(AG8>12,AG8<21,AH8>12,AH8<21,AI8>12,AI8<21,AJ8>12,AJ8<21),3,4))) -> 3 | DO8: =TRIM(DE8&DF8&DG8&DH8) -> CSI | DP8: =BJ8&CL8&DN8 -> 123 | DQ8: =A8&G8&H8&I8&J8&L8&M8&N8&O8 | DR8: =VLOOKUP(G8,tableD1,3,0) -> 1 | DS8: =VLOOKUP(H8,tableI1,3,0) -> 1 | DT8: =VLOOKUP(I8,table1S,3,0) -> 2 | DU8: =VLOOKUP(J8,table1C,3,0) -> 1 | DV8: =VLOOKUP(L8,table2D,3,0) -> 8 | DW8: =VLOOKUP(M8,table2I,3,0) -> 8 | DX8: =VLOOKUP(N8,table2S,3,0) -> 8 | DY8: =VLOOKUP(O8,table2C,3,0) -> 8 | DZ8: =VLOOKUP(Q8,table3D,3,0) -> 4 | EA8: =VLOOKUP(R8,table3I,3,0) -> 5 | EB8: =VLOOKUP(S8,table3S,3,0) -> 5 | EC8: =VLOOKUP(T8,table3C,3,0) -> 5 | ED8: {=VLOOKUP(INDEX(JD,data!$AA$1),key!$J$3:$L$27,3,0)} -> 6 | EE8: {=VLOOKUP(INDEX(JI,data!$AA$1),key!$J$3:$L$27,3,0)} -> 4 | EF8: {=VLOOKUP(INDEX(JS,data!$AA$1),key!$J$3:$L$27,3,0)} -> 4 | EG8: {=VLOOKUP(INDEX(JC,data!$AA$1),key!$J$3:$L$27,3,0)} -> 7 | EH8: =VLOOKUP(DR8,tabel_jpm,ED8+1,0) -> 8 | EI8: =VLOOKUP(DS8,tabel_jpm,EE8+1,0) -> 16 | EJ8: =VLOOKUP(DT8,tabel_jpm,EF8+1,0) -> 20 | EK8: =VLOOKUP(DU8,tabel_jpm,EG8+1,0) -> 4 | EL8: =IF(B8="Pria",VLOOKUP(AVERAGE(EH8:EK8),agreement_p,4),VLOOKUP(AVERAGE(EH8:EK8),agreement_w,4)) -> 32 | EM8: =IF(DP8<>"444","N/A",EL8) -> N/A | EN8: =VLOOKUP(DV8,tabel_jpm,ED8+1,0) -> 20 | EO8: =VLOOKUP(DW8,tabel_jpm,EE8+1,0) -> 12 | EP8: =VLOOKUP(DX8,tabel_jpm,EF8+1,0) -> 12 | EQ8: =VLOOKUP(DY8,tabel_jpm,EG8+1,0) -> 24 | ER8: =IF(B8="Pria",VLOOKUP(AVERAGE(EN8:EQ8),agreement_p,4),VLOOKUP(AVERAGE(EN8:EQ8),agreement_w,4)) -> 50 | ES8: =IF(DP8<>"444","N/A",ER8) -> N/A | ET8: =VLOOKUP(DZ8,tabel_jpm,ED8+1,0) -> 20 | EU8: =VLOOKUP(EA8,tabel_jpm,EE8+1,0) -> 24 | EV8: =VLOOKUP(EB8,tabel_jpm,EF8+1,0) -> 24 | EW8: =VLOOKUP(EC8,tabel_jpm,EG8+1,0) -> 20 | EX8: =IF(B8="Pria",VLOOKUP(AVERAGE(ET8:EW8),agreement_p,4),VLOOKUP(AVERAGE(ET8:EW8),agreement_w,4)) -> 68 | EY8: =IF(DP8<>"444","N/A",EX8) -> N/A
A9: =data!A9 | B9: =data!B9 | C9: =data!C9 | D9: =data!D9 | E9: =data!E9 | F9: =data!F9 | G9: =data!G9 | H9: =data!H9 | ... W9: =data!W9 | Y9: =VLOOKUP(G9,tableD1,2,0) -> 4 | Z9: =VLOOKUP(H9,tableI1,2,0) -> 3 | AA9: =VLOOKUP(I9,table1S,2,0) -> 5 | AB9: =VLOOKUP(J9,table1C,2,0) -> 4 | AC9: =VLOOKUP(L9,table2D,2,0) -> 31 | AD9: =VLOOKUP(M9,table2I,2,0) -> 31 | AE9: =VLOOKUP(N9,table2S,2,0) -> 32 | AF9: =VLOOKUP(O9,table2C,2,0) -> 32 | AG9: =VLOOKUP(Q9,table3D,2,0) -> 16 | AH9: =VLOOKUP(R9,table3I,2,0) -> 18 | AI9: =VLOOKUP(S9,table3S,2,0) -> 19 | AJ9: =VLOOKUP(T9,table3C,2,0) -> 19 | AL9: =VALUE(Y9&AL$2) -> 41 | AM9: =VALUE(Z9&AM$2) -> 32 | AN9: =VALUE(AA9&AN$2) -> 53 | AO9: =VALUE(AB9&AO$2) -> 44 | AQ9: =LARGE($AL9:$AO9,AQ$2) -> 53 | AR9: =LARGE($AL9:$AO9,AR$2) -> 44 | AS9: =LARGE($AL9:$AO9,AS$2) -> 41 | AT9: =LARGE($AL9:$AO9,AT$2) -> 32 | AV9: =VLOOKUP(VALUE(RIGHT(AQ9,1)),misc!$A$2:$B$5,2,0) -> S | AW9: =VLOOKUP(VALUE(RIGHT(AR9,1)),misc!$A$2:$B$5,2,0) -> C | AX9: =VLOOKUP(VALUE(RIGHT(AS9,1)),misc!$A$2:$B$5,2,0) -> D | AY9: =VLOOKUP(VALUE(RIGHT(AT9,1)),misc!$A$2:$B$5,2,0) -> I | BA9: =IF(VALUE(AQ9)>=170,AV9,"") | BB9: =IF(VALUE(AR9)>=170,AW9,"") | BC9: =IF(VALUE(AS9)>=170,AX9,"") | BD9: =IF(VALUE(AT9)>=170,AY9,"") | BF9: =IF(VALUE(AQ9)<170,AV9,"") -> S | BG9: =IF(VALUE(AR9)<170,AW9,"") -> C | BH9: =IF(VALUE(AS9)<170,AX9,"") -> D | BI9: =IF(VALUE(AT9)<170,AY9,"") -> I | BJ9: =IF(AND(Y9<17,Z9<17,AA9<17,AB9<17),1,IF(AND(Y9>=17,Z9>=17,AA9>=17,AB9>=17),2,IF(AND(Y9>12,Y9<21,Z9>12,Z9<21,AA9>12,AA9<21,AB9>12,AB9<21),3,4))) -> 1 | BK9: =TRIM(BA9&BB9&BC9&BD9) | BN9: =VALUE(AC9&BN$2) -> 311 | BO9: =VALUE(AD9&BO$2) -> 312 | BP9: =VALUE(AE9&BP$2) -> 323 | BQ9: =VALUE(AF9&BQ$2) -> 324 | BS9: =LARGE($BN9:$BQ9,BS$2) -> 324 | BT9: =LARGE($BN9:$BQ9,BT$2) -> 323 | BU9: =LARGE($BN9:$BQ9,BU$2) -> 312 | BV9: =LARGE($BN9:$BQ9,BV$2) -> 311 | BX9: =VLOOKUP(VALUE(RIGHT(BS9,1)),misc!$A$2:$B$5,2,0) -> C | BY9: =VLOOKUP(VALUE(RIGHT(BT9,1)),misc!$A$2:$B$5,2,0) -> S | BZ9: =VLOOKUP(VALUE(RIGHT(BU9,1)),misc!$A$2:$B$5,2,0) -> I | CA9: =VLOOKUP(VALUE(RIGHT(BV9,1)),misc!$A$2:$B$5,2,0) -> D | CC9: =IF(VALUE(BS9)>=170,BX9,"") -> C | CD9: =IF(VALUE(BT9)>=170,BY9,"") -> S | CE9: =IF(VALUE(BU9)>=170,BZ9,"") -> I | CF9: =IF(VALUE(BV9)>=170,CA9,"") -> D | CH9: =IF(VALUE(BS9)<170,BX9,"") | CI9: =IF(VALUE(BT9)<170,BY9,"") | CJ9: =IF(VALUE(BU9)<170,BZ9,"") | CK9: =IF(VALUE(BV9)<170,CA9,"") | CL9: =IF(AND(AC9<17,AD9<17,AE9<17,AF9<17),1,IF(AND(AC9>=17,AD9>=17,AE9>=17,AF9>=17),2,IF(AND(AC9>12,AC9<21,AD9>12,AD9<21,AE9>12,AE9<21,AF9>12,AF9<21),3,4))) -> 2 | CM9: =TRIM(CC9&CD9&CE9&CF9) -> CSID | CP9: =VALUE(AG9&CP$2) -> 161 | CQ9: =VALUE(AH9&CQ$2) -> 182 | CR9: =VALUE(AI9&CR$2) -> 193 | CS9: =VALUE(AJ9&CS$2) -> 194 | CU9: =LARGE($CP9:$CS9,CU$2) -> 194 | CV9: =LARGE($CP9:$CS9,CV$2) -> 193 | CW9: =LARGE($CP9:$CS9,CW$2) -> 182 | CX9: =LARGE($CP9:$CS9,CX$2) -> 161 | CZ9: =VLOOKUP(VALUE(RIGHT(CU9,1)),misc!$A$2:$B$5,2,0) -> C | DA9: =VLOOKUP(VALUE(RIGHT(CV9,1)),misc!$A$2:$B$5,2,0) -> S | DB9: =VLOOKUP(VALUE(RIGHT(CW9,1)),misc!$A$2:$B$5,2,0) -> I | DC9: =VLOOKUP(VALUE(RIGHT(CX9,1)),misc!$A$2:$B$5,2,0) -> D | DE9: =IF(VALUE(CU9)>=170,CZ9,"") -> C | DF9: =IF(VALUE(CV9)>=170,DA9,"") -> S | DG9: =IF(VALUE(CW9)>=170,DB9,"") -> I | DH9: =IF(VALUE(CX9)>=170,DC9,"") | DJ9: =IF(VALUE(CU9)<170,CZ9,"") | DK9: =IF(VALUE(CV9)<170,DA9,"") | DL9: =IF(VALUE(CW9)<170,DB9,"") | DM9: =IF(VALUE(CX9)<170,DC9,"") -> D | DN9: =IF(AND(AG9<17,AH9<17,AI9<17,AJ9<17),1,IF(AND(AG9>=17,AH9>=17,AI9>=17,AJ9>=17),2,IF(AND(AG9>12,AG9<21,AH9>12,AH9<21,AI9>12,AI9<21,AJ9>12,AJ9<21),3,4))) -> 3 | DO9: =TRIM(DE9&DF9&DG9&DH9) -> CSI | DP9: =BJ9&CL9&DN9 -> 123 | DQ9: =A9&G9&H9&I9&J9&L9&M9&N9&O9 | DR9: =VLOOKUP(G9,tableD1,3,0) -> 1 | DS9: =VLOOKUP(H9,tableI1,3,0) -> 1 | DT9: =VLOOKUP(I9,table1S,3,0) -> 2 | DU9: =VLOOKUP(J9,table1C,3,0) -> 1 | DV9: =VLOOKUP(L9,table2D,3,0) -> 8 | DW9: =VLOOKUP(M9,table2I,3,0) -> 8 | DX9: =VLOOKUP(N9,table2S,3,0) -> 8 | DY9: =VLOOKUP(O9,table2C,3,0) -> 8 | DZ9: =VLOOKUP(Q9,table3D,3,0) -> 4 | EA9: =VLOOKUP(R9,table3I,3,0) -> 5 | EB9: =VLOOKUP(S9,table3S,3,0) -> 5 | EC9: =VLOOKUP(T9,table3C,3,0) -> 5 | ED9: {=VLOOKUP(INDEX(JD,data!$AA$1),key!$J$3:$L$27,3,0)} -> 6 | EE9: {=VLOOKUP(INDEX(JI,data!$AA$1),key!$J$3:$L$27,3,0)} -> 4 | EF9: {=VLOOKUP(INDEX(JS,data!$AA$1),key!$J$3:$L$27,3,0)} -> 4 | EG9: {=VLOOKUP(INDEX(JC,data!$AA$1),key!$J$3:$L$27,3,0)} -> 7 | EH9: =VLOOKUP(DR9,tabel_jpm,ED9+1,0) -> 8 | EI9: =VLOOKUP(DS9,tabel_jpm,EE9+1,0) -> 16 | EJ9: =VLOOKUP(DT9,tabel_jpm,EF9+1,0) -> 20 | EK9: =VLOOKUP(DU9,tabel_jpm,EG9+1,0) -> 4 | EL9: =IF(B9="Pria",VLOOKUP(AVERAGE(EH9:EK9),agreement_p,4),VLOOKUP(AVERAGE(EH9:EK9),agreement_w,4)) -> 32 | EM9: =IF(DP9<>"444","N/A",EL9) -> N/A | EN9: =VLOOKUP(DV9,tabel_jpm,ED9+1,0) -> 20 | EO9: =VLOOKUP(DW9,tabel_jpm,EE9+1,0) -> 12 | EP9: =VLOOKUP(DX9,tabel_jpm,EF9+1,0) -> 12 | EQ9: =VLOOKUP(DY9,tabel_jpm,EG9+1,0) -> 24 | ER9: =IF(B9="Pria",VLOOKUP(AVERAGE(EN9:EQ9),agreement_p,4),VLOOKUP(AVERAGE(EN9:EQ9),agreement_w,4)) -> 50 | ES9: =IF(DP9<>"444","N/A",ER9) -> N/A | ET9: =VLOOKUP(DZ9,tabel_jpm,ED9+1,0) -> 20 | EU9: =VLOOKUP(EA9,tabel_jpm,EE9+1,0) -> 24 | EV9: =VLOOKUP(EB9,tabel_jpm,EF9+1,0) -> 24 | EW9: =VLOOKUP(EC9,tabel_jpm,EG9+1,0) -> 20 | EX9: =IF(B9="Pria",VLOOKUP(AVERAGE(ET9:EW9),agreement_p,4),VLOOKUP(AVERAGE(ET9:EW9),agreement_w,4)) -> 68 | EY9: =IF(DP9<>"444","N/A",EX9) -> N/A
A10: =data!A10 | B10: =data!B10 | C10: =data!C10 | D10: =data!D10 | E10: =data!E10 | F10: =data!F10 | G10: =data!G10 | H10: =data!H10 | ... W10: =data!W10 | Y10: =VLOOKUP(G10,tableD1,2,0) -> 4 | Z10: =VLOOKUP(H10,tableI1,2,0) -> 3 | AA10: =VLOOKUP(I10,table1S,2,0) -> 5 | AB10: =VLOOKUP(J10,table1C,2,0) -> 4 | AC10: =VLOOKUP(L10,table2D,2,0) -> 31 | AD10: =VLOOKUP(M10,table2I,2,0) -> 31 | AE10: =VLOOKUP(N10,table2S,2,0) -> 32 | AF10: =VLOOKUP(O10,table2C,2,0) -> 32 | AG10: =VLOOKUP(Q10,table3D,2,0) -> 16 | AH10: =VLOOKUP(R10,table3I,2,0) -> 18 | AI10: =VLOOKUP(S10,table3S,2,0) -> 19 | AJ10: =VLOOKUP(T10,table3C,2,0) -> 19 | AL10: =VALUE(Y10&AL$2) -> 41 | AM10: =VALUE(Z10&AM$2) -> 32 | AN10: =VALUE(AA10&AN$2) -> 53 | AO10: =VALUE(AB10&AO$2) -> 44 | AQ10: =LARGE($AL10:$AO10,AQ$2) -> 53 | AR10: =LARGE($AL10:$AO10,AR$2) -> 44 | AS10: =LARGE($AL10:$AO10,AS$2) -> 41 | AT10: =LARGE($AL10:$AO10,AT$2) -> 32 | AV10: =VLOOKUP(VALUE(RIGHT(AQ10,1)),misc!$A$2:$B$5,2,0) -> S | AW10: =VLOOKUP(VALUE(RIGHT(AR10,1)),misc!$A$2:$B$5,2,0) -> C | AX10: =VLOOKUP(VALUE(RIGHT(AS10,1)),misc!$A$2:$B$5,2,0) -> D | AY10: =VLOOKUP(VALUE(RIGHT(AT10,1)),misc!$A$2:$B$5,2,0) -> I | BA10: =IF(VALUE(AQ10)>=170,AV10,"") | BB10: =IF(VALUE(AR10)>=170,AW10,"") | BC10: =IF(VALUE(AS10)>=170,AX10,"") | BD10: =IF(VALUE(AT10)>=170,AY10,"") | BF10: =IF(VALUE(AQ10)<170,AV10,"") -> S | BG10: =IF(VALUE(AR10)<170,AW10,"") -> C | BH10: =IF(VALUE(AS10)<170,AX10,"") -> D | BI10: =IF(VALUE(AT10)<170,AY10,"") -> I | BJ10: =IF(AND(Y10<17,Z10<17,AA10<17,AB10<17),1,IF(AND(Y10>=17,Z10>=17,AA10>=17,AB10>=17),2,IF(AND(Y10>12,Y10<21,Z10>12,Z10<21,AA10>12,AA10<21,AB10>12,AB10<21),3,4))) -> 1 | BK10: =TRIM(BA10&BB10&BC10&BD10) | BN10: =VALUE(AC10&BN$2) -> 311 | BO10: =VALUE(AD10&BO$2) -> 312 | BP10: =VALUE(AE10&BP$2) -> 323 | BQ10: =VALUE(AF10&BQ$2) -> 324 | BS10: =LARGE($BN10:$BQ10,BS$2) -> 324 | BT10: =LARGE($BN10:$BQ10,BT$2) -> 323 | BU10: =LARGE($BN10:$BQ10,BU$2) -> 312 | BV10: =LARGE($BN10:$BQ10,BV$2) -> 311 | BX10: =VLOOKUP(VALUE(RIGHT(BS10,1)),misc!$A$2:$B$5,2,0) -> C | BY10: =VLOOKUP(VALUE(RIGHT(BT10,1)),misc!$A$2:$B$5,2,0) -> S | BZ10: =VLOOKUP(VALUE(RIGHT(BU10,1)),misc!$A$2:$B$5,2,0) -> I | CA10: =VLOOKUP(VALUE(RIGHT(BV10,1)),misc!$A$2:$B$5,2,0) -> D | CC10: =IF(VALUE(BS10)>=170,BX10,"") -> C | CD10: =IF(VALUE(BT10)>=170,BY10,"") -> S | CE10: =IF(VALUE(BU10)>=170,BZ10,"") -> I | CF10: =IF(VALUE(BV10)>=170,CA10,"") -> D | CH10: =IF(VALUE(BS10)<170,BX10,"") | CI10: =IF(VALUE(BT10)<170,BY10,"") | CJ10: =IF(VALUE(BU10)<170,BZ10,"") | CK10: =IF(VALUE(BV10)<170,CA10,"") | CL10: =IF(AND(AC10<17,AD10<17,AE10<17,AF10<17),1,IF(AND(AC10>=17,AD10>=17,AE10>=17,AF10>=17),2,IF(AND(AC10>12,AC10<21,AD10>12,AD10<21,AE10>12,AE10<21,AF10>12,AF10<21),3,4))) -> 2 | CM10: =TRIM(CC10&CD10&CE10&CF10) -> CSID | CP10: =VALUE(AG10&CP$2) -> 161 | CQ10: =VALUE(AH10&CQ$2) -> 182 | CR10: =VALUE(AI10&CR$2) -> 193 | CS10: =VALUE(AJ10&CS$2) -> 194 | CU10: =LARGE($CP10:$CS10,CU$2) -> 194 | CV10: =LARGE($CP10:$CS10,CV$2) -> 193 | CW10: =LARGE($CP10:$CS10,CW$2) -> 182 | CX10: =LARGE($CP10:$CS10,CX$2) -> 161 | CZ10: =VLOOKUP(VALUE(RIGHT(CU10,1)),misc!$A$2:$B$5,2,0) -> C | DA10: =VLOOKUP(VALUE(RIGHT(CV10,1)),misc!$A$2:$B$5,2,0) -> S | DB10: =VLOOKUP(VALUE(RIGHT(CW10,1)),misc!$A$2:$B$5,2,0) -> I | DC10: =VLOOKUP(VALUE(RIGHT(CX10,1)),misc!$A$2:$B$5,2,0) -> D | DE10: =IF(VALUE(CU10)>=170,CZ10,"") -> C | DF10: =IF(VALUE(CV10)>=170,DA10,"") -> S | DG10: =IF(VALUE(CW10)>=170,DB10,"") -> I | DH10: =IF(VALUE(CX10)>=170,DC10,"") | DJ10: =IF(VALUE(CU10)<170,CZ10,"") | DK10: =IF(VALUE(CV10)<170,DA10,"") | DL10: =IF(VALUE(CW10)<170,DB10,"") | DM10: =IF(VALUE(CX10)<170,DC10,"") -> D | DN10: =IF(AND(AG10<17,AH10<17,AI10<17,AJ10<17),1,IF(AND(AG10>=17,AH10>=17,AI10>=17,AJ10>=17),2,IF(AND(AG10>12,AG10<21,AH10>12,AH10<21,AI10>12,AI10<21,AJ10>12,AJ10<21),3,4))) -> 3 | DO10: =TRIM(DE10&DF10&DG10&DH10) -> CSI | DP10: =BJ10&CL10&DN10 -> 123 | DQ10: =A10&G10&H10&I10&J10&L10&M10&N10&O10 | DR10: =VLOOKUP(G10,tableD1,3,0) -> 1 | DS10: =VLOOKUP(H10,tableI1,3,0) -> 1 | DT10: =VLOOKUP(I10,table1S,3,0) -> 2 | DU10: =VLOOKUP(J10,table1C,3,0) -> 1 | DV10: =VLOOKUP(L10,table2D,3,0) -> 8 | DW10: =VLOOKUP(M10,table2I,3,0) -> 8 | DX10: =VLOOKUP(N10,table2S,3,0) -> 8 | DY10: =VLOOKUP(O10,table2C,3,0) -> 8 | DZ10: =VLOOKUP(Q10,table3D,3,0) -> 4 | EA10: =VLOOKUP(R10,table3I,3,0) -> 5 | EB10: =VLOOKUP(S10,table3S,3,0) -> 5 | EC10: =VLOOKUP(T10,table3C,3,0) -> 5 | ED10: {=VLOOKUP(INDEX(JD,data!$AA$1),key!$J$3:$L$27,3,0)} -> 6 | EE10: {=VLOOKUP(INDEX(JI,data!$AA$1),key!$J$3:$L$27,3,0)} -> 4 | EF10: {=VLOOKUP(INDEX(JS,data!$AA$1),key!$J$3:$L$27,3,0)} -> 4 | EG10: {=VLOOKUP(INDEX(JC,data!$AA$1),key!$J$3:$L$27,3,0)} -> 7 | EH10: =VLOOKUP(DR10,tabel_jpm,ED10+1,0) -> 8 | EI10: =VLOOKUP(DS10,tabel_jpm,EE10+1,0) -> 16 | EJ10: =VLOOKUP(DT10,tabel_jpm,EF10+1,0) -> 20 | EK10: =VLOOKUP(DU10,tabel_jpm,EG10+1,0) -> 4 | EL10: =IF(B10="Pria",VLOOKUP(AVERAGE(EH10:EK10),agreement_p,4),VLOOKUP(AVERAGE(EH10:EK10),agreement_w,4)) -> 32 | EM10: =IF(DP10<>"444","N/A",EL10) -> N/A | EN10: =VLOOKUP(DV10,tabel_jpm,ED10+1,0) -> 20 | EO10: =VLOOKUP(DW10,tabel_jpm,EE10+1,0) -> 12 | EP10: =VLOOKUP(DX10,tabel_jpm,EF10+1,0) -> 12 | EQ10: =VLOOKUP(DY10,tabel_jpm,EG10+1,0) -> 24 | ER10: =IF(B10="Pria",VLOOKUP(AVERAGE(EN10:EQ10),agreement_p,4),VLOOKUP(AVERAGE(EN10:EQ10),agreement_w,4)) -> 50 | ES10: =IF(DP10<>"444","N/A",ER10) -> N/A | ET10: =VLOOKUP(DZ10,tabel_jpm,ED10+1,0) -> 20 | EU10: =VLOOKUP(EA10,tabel_jpm,EE10+1,0) -> 24 | EV10: =VLOOKUP(EB10,tabel_jpm,EF10+1,0) -> 24 | EW10: =VLOOKUP(EC10,tabel_jpm,EG10+1,0) -> 20 | EX10: =IF(B10="Pria",VLOOKUP(AVERAGE(ET10:EW10),agreement_p,4),VLOOKUP(AVERAGE(ET10:EW10),agreement_w,4)) -> 68 | EY10: =IF(DP10<>"444","N/A",EX10) -> N/A
A11: =data!A11 | B11: =data!B11 | C11: =data!C11 | D11: =data!D11 | E11: =data!E11 | F11: =data!F11 | G11: =data!G11 | H11: =data!H11 | ... W11: =data!W11 | Y11: =VLOOKUP(G11,tableD1,2,0) -> 4 | Z11: =VLOOKUP(H11,tableI1,2,0) -> 3 | AA11: =VLOOKUP(I11,table1S,2,0) -> 5 | AB11: =VLOOKUP(J11,table1C,2,0) -> 4 | AC11: =VLOOKUP(L11,table2D,2,0) -> 31 | AD11: =VLOOKUP(M11,table2I,2,0) -> 31 | AE11: =VLOOKUP(N11,table2S,2,0) -> 32 | AF11: =VLOOKUP(O11,table2C,2,0) -> 32 | AG11: =VLOOKUP(Q11,table3D,2,0) -> 16 | AH11: =VLOOKUP(R11,table3I,2,0) -> 18 | AI11: =VLOOKUP(S11,table3S,2,0) -> 19 | AJ11: =VLOOKUP(T11,table3C,2,0) -> 19 | AL11: =VALUE(Y11&AL$2) -> 41 | AM11: =VALUE(Z11&AM$2) -> 32 | AN11: =VALUE(AA11&AN$2) -> 53 | AO11: =VALUE(AB11&AO$2) -> 44 | AQ11: =LARGE($AL11:$AO11,AQ$2) -> 53 | AR11: =LARGE($AL11:$AO11,AR$2) -> 44 | AS11: =LARGE($AL11:$AO11,AS$2) -> 41 | AT11: =LARGE($AL11:$AO11,AT$2) -> 32 | AV11: =VLOOKUP(VALUE(RIGHT(AQ11,1)),misc!$A$2:$B$5,2,0) -> S | AW11: =VLOOKUP(VALUE(RIGHT(AR11,1)),misc!$A$2:$B$5,2,0) -> C | AX11: =VLOOKUP(VALUE(RIGHT(AS11,1)),misc!$A$2:$B$5,2,0) -> D | AY11: =VLOOKUP(VALUE(RIGHT(AT11,1)),misc!$A$2:$B$5,2,0) -> I | BA11: =IF(VALUE(AQ11)>=170,AV11,"") | BB11: =IF(VALUE(AR11)>=170,AW11,"") | BC11: =IF(VALUE(AS11)>=170,AX11,"") | BD11: =IF(VALUE(AT11)>=170,AY11,"") | BF11: =IF(VALUE(AQ11)<170,AV11,"") -> S | BG11: =IF(VALUE(AR11)<170,AW11,"") -> C | BH11: =IF(VALUE(AS11)<170,AX11,"") -> D | BI11: =IF(VALUE(AT11)<170,AY11,"") -> I | BJ11: =IF(AND(Y11<17,Z11<17,AA11<17,AB11<17),1,IF(AND(Y11>=17,Z11>=17,AA11>=17,AB11>=17),2,IF(AND(Y11>12,Y11<21,Z11>12,Z11<21,AA11>12,AA11<21,AB11>12,AB11<21),3,4))) -> 1 | BK11: =TRIM(BA11&BB11&BC11&BD11) | BN11: =VALUE(AC11&BN$2) -> 311 | BO11: =VALUE(AD11&BO$2) -> 312 | BP11: =VALUE(AE11&BP$2) -> 323 | BQ11: =VALUE(AF11&BQ$2) -> 324 | BS11: =LARGE($BN11:$BQ11,BS$2) -> 324 | BT11: =LARGE($BN11:$BQ11,BT$2) -> 323 | BU11: =LARGE($BN11:$BQ11,BU$2) -> 312 | BV11: =LARGE($BN11:$BQ11,BV$2) -> 311 | BX11: =VLOOKUP(VALUE(RIGHT(BS11,1)),misc!$A$2:$B$5,2,0) -> C | BY11: =VLOOKUP(VALUE(RIGHT(BT11,1)),misc!$A$2:$B$5,2,0) -> S | BZ11: =VLOOKUP(VALUE(RIGHT(BU11,1)),misc!$A$2:$B$5,2,0) -> I | CA11: =VLOOKUP(VALUE(RIGHT(BV11,1)),misc!$A$2:$B$5,2,0) -> D | CC11: =IF(VALUE(BS11)>=170,BX11,"") -> C | CD11: =IF(VALUE(BT11)>=170,BY11,"") -> S | CE11: =IF(VALUE(BU11)>=170,BZ11,"") -> I | CF11: =IF(VALUE(BV11)>=170,CA11,"") -> D | CH11: =IF(VALUE(BS11)<170,BX11,"") | CI11: =IF(VALUE(BT11)<170,BY11,"") | CJ11: =IF(VALUE(BU11)<170,BZ11,"") | CK11: =IF(VALUE(BV11)<170,CA11,"") | CL11: =IF(AND(AC11<17,AD11<17,AE11<17,AF11<17),1,IF(AND(AC11>=17,AD11>=17,AE11>=17,AF11>=17),2,IF(AND(AC11>12,AC11<21,AD11>12,AD11<21,AE11>12,AE11<21,AF11>12,AF11<21),3,4))) -> 2 | CM11: =TRIM(CC11&CD11&CE11&CF11) -> CSID | CP11: =VALUE(AG11&CP$2) -> 161 | CQ11: =VALUE(AH11&CQ$2) -> 182 | CR11: =VALUE(AI11&CR$2) -> 193 | CS11: =VALUE(AJ11&CS$2) -> 194 | CU11: =LARGE($CP11:$CS11,CU$2) -> 194 | CV11: =LARGE($CP11:$CS11,CV$2) -> 193 | CW11: =LARGE($CP11:$CS11,CW$2) -> 182 | CX11: =LARGE($CP11:$CS11,CX$2) -> 161 | CZ11: =VLOOKUP(VALUE(RIGHT(CU11,1)),misc!$A$2:$B$5,2,0) -> C | DA11: =VLOOKUP(VALUE(RIGHT(CV11,1)),misc!$A$2:$B$5,2,0) -> S | DB11: =VLOOKUP(VALUE(RIGHT(CW11,1)),misc!$A$2:$B$5,2,0) -> I | DC11: =VLOOKUP(VALUE(RIGHT(CX11,1)),misc!$A$2:$B$5,2,0) -> D | DE11: =IF(VALUE(CU11)>=170,CZ11,"") -> C | DF11: =IF(VALUE(CV11)>=170,DA11,"") -> S | DG11: =IF(VALUE(CW11)>=170,DB11,"") -> I | DH11: =IF(VALUE(CX11)>=170,DC11,"") | DJ11: =IF(VALUE(CU11)<170,CZ11,"") | DK11: =IF(VALUE(CV11)<170,DA11,"") | DL11: =IF(VALUE(CW11)<170,DB11,"") | DM11: =IF(VALUE(CX11)<170,DC11,"") -> D | DN11: =IF(AND(AG11<17,AH11<17,AI11<17,AJ11<17),1,IF(AND(AG11>=17,AH11>=17,AI11>=17,AJ11>=17),2,IF(AND(AG11>12,AG11<21,AH11>12,AH11<21,AI11>12,AI11<21,AJ11>12,AJ11<21),3,4))) -> 3 | DO11: =TRIM(DE11&DF11&DG11&DH11) -> CSI | DP11: =BJ11&CL11&DN11 -> 123 | DQ11: =A11&G11&H11&I11&J11&L11&M11&N11&O11 | DR11: =VLOOKUP(G11,tableD1,3,0) -> 1 | DS11: =VLOOKUP(H11,tableI1,3,0) -> 1 | DT11: =VLOOKUP(I11,table1S,3,0) -> 2 | DU11: =VLOOKUP(J11,table1C,3,0) -> 1 | DV11: =VLOOKUP(L11,table2D,3,0) -> 8 | DW11: =VLOOKUP(M11,table2I,3,0) -> 8 | DX11: =VLOOKUP(N11,table2S,3,0) -> 8 | DY11: =VLOOKUP(O11,table2C,3,0) -> 8 | DZ11: =VLOOKUP(Q11,table3D,3,0) -> 4 | EA11: =VLOOKUP(R11,table3I,3,0) -> 5 | EB11: =VLOOKUP(S11,table3S,3,0) -> 5 | EC11: =VLOOKUP(T11,table3C,3,0) -> 5 | ED11: {=VLOOKUP(INDEX(JD,data!$AA$1),key!$J$3:$L$27,3,0)} -> 6 | EE11: {=VLOOKUP(INDEX(JI,data!$AA$1),key!$J$3:$L$27,3,0)} -> 4 | EF11: {=VLOOKUP(INDEX(JS,data!$AA$1),key!$J$3:$L$27,3,0)} -> 4 | EG11: {=VLOOKUP(INDEX(JC,data!$AA$1),key!$J$3:$L$27,3,0)} -> 7 | EH11: =VLOOKUP(DR11,tabel_jpm,ED11+1,0) -> 8 | EI11: =VLOOKUP(DS11,tabel_jpm,EE11+1,0) -> 16 | EJ11: =VLOOKUP(DT11,tabel_jpm,EF11+1,0) -> 20 | EK11: =VLOOKUP(DU11,tabel_jpm,EG11+1,0) -> 4 | EL11: =IF(B11="Pria",VLOOKUP(AVERAGE(EH11:EK11),agreement_p,4),VLOOKUP(AVERAGE(EH11:EK11),agreement_w,4)) -> 32 | EM11: =IF(DP11<>"444","N/A",EL11) -> N/A | EN11: =VLOOKUP(DV11,tabel_jpm,ED11+1,0) -> 20 | EO11: =VLOOKUP(DW11,tabel_jpm,EE11+1,0) -> 12 | EP11: =VLOOKUP(DX11,tabel_jpm,EF11+1,0) -> 12 | EQ11: =VLOOKUP(DY11,tabel_jpm,EG11+1,0) -> 24 | ER11: =IF(B11="Pria",VLOOKUP(AVERAGE(EN11:EQ11),agreement_p,4),VLOOKUP(AVERAGE(EN11:EQ11),agreement_w,4)) -> 50 | ES11: =IF(DP11<>"444","N/A",ER11) -> N/A | ET11: =VLOOKUP(DZ11,tabel_jpm,ED11+1,0) -> 20 | EU11: =VLOOKUP(EA11,tabel_jpm,EE11+1,0) -> 24 | EV11: =VLOOKUP(EB11,tabel_jpm,EF11+1,0) -> 24 | EW11: =VLOOKUP(EC11,tabel_jpm,EG11+1,0) -> 20 | EX11: =IF(B11="Pria",VLOOKUP(AVERAGE(ET11:EW11),agreement_p,4),VLOOKUP(AVERAGE(ET11:EW11),agreement_w,4)) -> 68 | EY11: =IF(DP11<>"444","N/A",EX11) -> N/A
A12: =data!A12 | B12: =data!B12 | C12: =data!C12 | D12: =data!D12 | E12: =data!E12 | F12: =data!F12 | G12: =data!G12 | H12: =data!H12 | ... W12: =data!W12 | Y12: =VLOOKUP(G12,tableD1,2,0) -> 4 | Z12: =VLOOKUP(H12,tableI1,2,0) -> 3 | AA12: =VLOOKUP(I12,table1S,2,0) -> 5 | AB12: =VLOOKUP(J12,table1C,2,0) -> 4 | AC12: =VLOOKUP(L12,table2D,2,0) -> 31 | AD12: =VLOOKUP(M12,table2I,2,0) -> 31 | AE12: =VLOOKUP(N12,table2S,2,0) -> 32 | AF12: =VLOOKUP(O12,table2C,2,0) -> 32 | AG12: =VLOOKUP(Q12,table3D,2,0) -> 16 | AH12: =VLOOKUP(R12,table3I,2,0) -> 18 | AI12: =VLOOKUP(S12,table3S,2,0) -> 19 | AJ12: =VLOOKUP(T12,table3C,2,0) -> 19 | AL12: =VALUE(Y12&AL$2) -> 41 | AM12: =VALUE(Z12&AM$2) -> 32 | AN12: =VALUE(AA12&AN$2) -> 53 | AO12: =VALUE(AB12&AO$2) -> 44 | AQ12: =LARGE($AL12:$AO12,AQ$2) -> 53 | AR12: =LARGE($AL12:$AO12,AR$2) -> 44 | AS12: =LARGE($AL12:$AO12,AS$2) -> 41 | AT12: =LARGE($AL12:$AO12,AT$2) -> 32 | AV12: =VLOOKUP(VALUE(RIGHT(AQ12,1)),misc!$A$2:$B$5,2,0) -> S | AW12: =VLOOKUP(VALUE(RIGHT(AR12,1)),misc!$A$2:$B$5,2,0) -> C | AX12: =VLOOKUP(VALUE(RIGHT(AS12,1)),misc!$A$2:$B$5,2,0) -> D | AY12: =VLOOKUP(VALUE(RIGHT(AT12,1)),misc!$A$2:$B$5,2,0) -> I | BA12: =IF(VALUE(AQ12)>=170,AV12,"") | BB12: =IF(VALUE(AR12)>=170,AW12,"") | BC12: =IF(VALUE(AS12)>=170,AX12,"") | BD12: =IF(VALUE(AT12)>=170,AY12,"") | BF12: =IF(VALUE(AQ12)<170,AV12,"") -> S | BG12: =IF(VALUE(AR12)<170,AW12,"") -> C | BH12: =IF(VALUE(AS12)<170,AX12,"") -> D | BI12: =IF(VALUE(AT12)<170,AY12,"") -> I | BJ12: =IF(AND(Y12<17,Z12<17,AA12<17,AB12<17),1,IF(AND(Y12>=17,Z12>=17,AA12>=17,AB12>=17),2,IF(AND(Y12>12,Y12<21,Z12>12,Z12<21,AA12>12,AA12<21,AB12>12,AB12<21),3,4))) -> 1 | BK12: =TRIM(BA12&BB12&BC12&BD12) | BN12: =VALUE(AC12&BN$2) -> 311 | BO12: =VALUE(AD12&BO$2) -> 312 | BP12: =VALUE(AE12&BP$2) -> 323 | BQ12: =VALUE(AF12&BQ$2) -> 324 | BS12: =LARGE($BN12:$BQ12,BS$2) -> 324 | BT12: =LARGE($BN12:$BQ12,BT$2) -> 323 | BU12: =LARGE($BN12:$BQ12,BU$2) -> 312 | BV12: =LARGE($BN12:$BQ12,BV$2) -> 311 | BX12: =VLOOKUP(VALUE(RIGHT(BS12,1)),misc!$A$2:$B$5,2,0) -> C | BY12: =VLOOKUP(VALUE(RIGHT(BT12,1)),misc!$A$2:$B$5,2,0) -> S | BZ12: =VLOOKUP(VALUE(RIGHT(BU12,1)),misc!$A$2:$B$5,2,0) -> I | CA12: =VLOOKUP(VALUE(RIGHT(BV12,1)),misc!$A$2:$B$5,2,0) -> D | CC12: =IF(VALUE(BS12)>=170,BX12,"") -> C | CD12: =IF(VALUE(BT12)>=170,BY12,"") -> S | CE12: =IF(VALUE(BU12)>=170,BZ12,"") -> I | CF12: =IF(VALUE(BV12)>=170,CA12,"") -> D | CH12: =IF(VALUE(BS12)<170,BX12,"") | CI12: =IF(VALUE(BT12)<170,BY12,"") | CJ12: =IF(VALUE(BU12)<170,BZ12,"") | CK12: =IF(VALUE(BV12)<170,CA12,"") | CL12: =IF(AND(AC12<17,AD12<17,AE12<17,AF12<17),1,IF(AND(AC12>=17,AD12>=17,AE12>=17,AF12>=17),2,IF(AND(AC12>12,AC12<21,AD12>12,AD12<21,AE12>12,AE12<21,AF12>12,AF12<21),3,4))) -> 2 | CM12: =TRIM(CC12&CD12&CE12&CF12) -> CSID | CP12: =VALUE(AG12&CP$2) -> 161 | CQ12: =VALUE(AH12&CQ$2) -> 182 | CR12: =VALUE(AI12&CR$2) -> 193 | CS12: =VALUE(AJ12&CS$2) -> 194 | CU12: =LARGE($CP12:$CS12,CU$2) -> 194 | CV12: =LARGE($CP12:$CS12,CV$2) -> 193 | CW12: =LARGE($CP12:$CS12,CW$2) -> 182 | CX12: =LARGE($CP12:$CS12,CX$2) -> 161 | CZ12: =VLOOKUP(VALUE(RIGHT(CU12,1)),misc!$A$2:$B$5,2,0) -> C | DA12: =VLOOKUP(VALUE(RIGHT(CV12,1)),misc!$A$2:$B$5,2,0) -> S | DB12: =VLOOKUP(VALUE(RIGHT(CW12,1)),misc!$A$2:$B$5,2,0) -> I | DC12: =VLOOKUP(VALUE(RIGHT(CX12,1)),misc!$A$2:$B$5,2,0) -> D | DE12: =IF(VALUE(CU12)>=170,CZ12,"") -> C | DF12: =IF(VALUE(CV12)>=170,DA12,"") -> S | DG12: =IF(VALUE(CW12)>=170,DB12,"") -> I | DH12: =IF(VALUE(CX12)>=170,DC12,"") | DJ12: =IF(VALUE(CU12)<170,CZ12,"") | DK12: =IF(VALUE(CV12)<170,DA12,"") | DL12: =IF(VALUE(CW12)<170,DB12,"") | DM12: =IF(VALUE(CX12)<170,DC12,"") -> D | DN12: =IF(AND(AG12<17,AH12<17,AI12<17,AJ12<17),1,IF(AND(AG12>=17,AH12>=17,AI12>=17,AJ12>=17),2,IF(AND(AG12>12,AG12<21,AH12>12,AH12<21,AI12>12,AI12<21,AJ12>12,AJ12<21),3,4))) -> 3 | DO12: =TRIM(DE12&DF12&DG12&DH12) -> CSI | DP12: =BJ12&CL12&DN12 -> 123 | DQ12: =A12&G12&H12&I12&J12&L12&M12&N12&O12 | DR12: =VLOOKUP(G12,tableD1,3,0) -> 1 | DS12: =VLOOKUP(H12,tableI1,3,0) -> 1 | DT12: =VLOOKUP(I12,table1S,3,0) -> 2 | DU12: =VLOOKUP(J12,table1C,3,0) -> 1 | DV12: =VLOOKUP(L12,table2D,3,0) -> 8 | DW12: =VLOOKUP(M12,table2I,3,0) -> 8 | DX12: =VLOOKUP(N12,table2S,3,0) -> 8 | DY12: =VLOOKUP(O12,table2C,3,0) -> 8 | DZ12: =VLOOKUP(Q12,table3D,3,0) -> 4 | EA12: =VLOOKUP(R12,table3I,3,0) -> 5 | EB12: =VLOOKUP(S12,table3S,3,0) -> 5 | EC12: =VLOOKUP(T12,table3C,3,0) -> 5 | ED12: {=VLOOKUP(INDEX(JD,data!$AA$1),key!$J$3:$L$27,3,0)} -> 6 | EE12: {=VLOOKUP(INDEX(JI,data!$AA$1),key!$J$3:$L$27,3,0)} -> 4 | EF12: {=VLOOKUP(INDEX(JS,data!$AA$1),key!$J$3:$L$27,3,0)} -> 4 | EG12: {=VLOOKUP(INDEX(JC,data!$AA$1),key!$J$3:$L$27,3,0)} -> 7 | EH12: =VLOOKUP(DR12,tabel_jpm,ED12+1,0) -> 8 | EI12: =VLOOKUP(DS12,tabel_jpm,EE12+1,0) -> 16 | EJ12: =VLOOKUP(DT12,tabel_jpm,EF12+1,0) -> 20 | EK12: =VLOOKUP(DU12,tabel_jpm,EG12+1,0) -> 4 | EL12: =IF(B12="Pria",VLOOKUP(AVERAGE(EH12:EK12),agreement_p,4),VLOOKUP(AVERAGE(EH12:EK12),agreement_w,4)) -> 32 | EM12: =IF(DP12<>"444","N/A",EL12) -> N/A | EN12: =VLOOKUP(DV12,tabel_jpm,ED12+1,0) -> 20 | EO12: =VLOOKUP(DW12,tabel_jpm,EE12+1,0) -> 12 | EP12: =VLOOKUP(DX12,tabel_jpm,EF12+1,0) -> 12 | EQ12: =VLOOKUP(DY12,tabel_jpm,EG12+1,0) -> 24 | ER12: =IF(B12="Pria",VLOOKUP(AVERAGE(EN12:EQ12),agreement_p,4),VLOOKUP(AVERAGE(EN12:EQ12),agreement_w,4)) -> 50 | ES12: =IF(DP12<>"444","N/A",ER12) -> N/A | ET12: =VLOOKUP(DZ12,tabel_jpm,ED12+1,0) -> 20 | EU12: =VLOOKUP(EA12,tabel_jpm,EE12+1,0) -> 24 | EV12: =VLOOKUP(EB12,tabel_jpm,EF12+1,0) -> 24 | EW12: =VLOOKUP(EC12,tabel_jpm,EG12+1,0) -> 20 | EX12: =IF(B12="Pria",VLOOKUP(AVERAGE(ET12:EW12),agreement_p,4),VLOOKUP(AVERAGE(ET12:EW12),agreement_w,4)) -> 68 | EY12: =IF(DP12<>"444","N/A",EX12) -> N/A
A13: =data!A13 | B13: =data!B13 | C13: =data!C13 | D13: =data!D13 | E13: =data!E13 | F13: =data!F13 | G13: =data!G13 | H13: =data!H13 | ... W13: =data!W13 | Y13: =VLOOKUP(G13,tableD1,2,0) -> 4 | Z13: =VLOOKUP(H13,tableI1,2,0) -> 3 | AA13: =VLOOKUP(I13,table1S,2,0) -> 5 | AB13: =VLOOKUP(J13,table1C,2,0) -> 4 | AC13: =VLOOKUP(L13,table2D,2,0) -> 31 | AD13: =VLOOKUP(M13,table2I,2,0) -> 31 | AE13: =VLOOKUP(N13,table2S,2,0) -> 32 | AF13: =VLOOKUP(O13,table2C,2,0) -> 32 | AG13: =VLOOKUP(Q13,table3D,2,0) -> 16 | AH13: =VLOOKUP(R13,table3I,2,0) -> 18 | AI13: =VLOOKUP(S13,table3S,2,0) -> 19 | AJ13: =VLOOKUP(T13,table3C,2,0) -> 19 | AL13: =VALUE(Y13&AL$2) -> 41 | AM13: =VALUE(Z13&AM$2) -> 32 | AN13: =VALUE(AA13&AN$2) -> 53 | AO13: =VALUE(AB13&AO$2) -> 44 | AQ13: =LARGE($AL13:$AO13,AQ$2) -> 53 | AR13: =LARGE($AL13:$AO13,AR$2) -> 44 | AS13: =LARGE($AL13:$AO13,AS$2) -> 41 | AT13: =LARGE($AL13:$AO13,AT$2) -> 32 | AV13: =VLOOKUP(VALUE(RIGHT(AQ13,1)),misc!$A$2:$B$5,2,0) -> S | AW13: =VLOOKUP(VALUE(RIGHT(AR13,1)),misc!$A$2:$B$5,2,0) -> C | AX13: =VLOOKUP(VALUE(RIGHT(AS13,1)),misc!$A$2:$B$5,2,0) -> D | AY13: =VLOOKUP(VALUE(RIGHT(AT13,1)),misc!$A$2:$B$5,2,0) -> I | BA13: =IF(VALUE(AQ13)>=170,AV13,"") | BB13: =IF(VALUE(AR13)>=170,AW13,"") | BC13: =IF(VALUE(AS13)>=170,AX13,"") | BD13: =IF(VALUE(AT13)>=170,AY13,"") | BF13: =IF(VALUE(AQ13)<170,AV13,"") -> S | BG13: =IF(VALUE(AR13)<170,AW13,"") -> C | BH13: =IF(VALUE(AS13)<170,AX13,"") -> D | BI13: =IF(VALUE(AT13)<170,AY13,"") -> I | BJ13: =IF(AND(Y13<17,Z13<17,AA13<17,AB13<17),1,IF(AND(Y13>=17,Z13>=17,AA13>=17,AB13>=17),2,IF(AND(Y13>12,Y13<21,Z13>12,Z13<21,AA13>12,AA13<21,AB13>12,AB13<21),3,4))) -> 1 | BK13: =TRIM(BA13&BB13&BC13&BD13) | BN13: =VALUE(AC13&BN$2) -> 311 | BO13: =VALUE(AD13&BO$2) -> 312 | BP13: =VALUE(AE13&BP$2) -> 323 | BQ13: =VALUE(AF13&BQ$2) -> 324 | BS13: =LARGE($BN13:$BQ13,BS$2) -> 324 | BT13: =LARGE($BN13:$BQ13,BT$2) -> 323 | BU13: =LARGE($BN13:$BQ13,BU$2) -> 312 | BV13: =LARGE($BN13:$BQ13,BV$2) -> 311 | BX13: =VLOOKUP(VALUE(RIGHT(BS13,1)),misc!$A$2:$B$5,2,0) -> C | BY13: =VLOOKUP(VALUE(RIGHT(BT13,1)),misc!$A$2:$B$5,2,0) -> S | BZ13: =VLOOKUP(VALUE(RIGHT(BU13,1)),misc!$A$2:$B$5,2,0) -> I | CA13: =VLOOKUP(VALUE(RIGHT(BV13,1)),misc!$A$2:$B$5,2,0) -> D | CC13: =IF(VALUE(BS13)>=170,BX13,"") -> C | CD13: =IF(VALUE(BT13)>=170,BY13,"") -> S | CE13: =IF(VALUE(BU13)>=170,BZ13,"") -> I | CF13: =IF(VALUE(BV13)>=170,CA13,"") -> D | CH13: =IF(VALUE(BS13)<170,BX13,"") | CI13: =IF(VALUE(BT13)<170,BY13,"") | CJ13: =IF(VALUE(BU13)<170,BZ13,"") | CK13: =IF(VALUE(BV13)<170,CA13,"") | CL13: =IF(AND(AC13<17,AD13<17,AE13<17,AF13<17),1,IF(AND(AC13>=17,AD13>=17,AE13>=17,AF13>=17),2,IF(AND(AC13>12,AC13<21,AD13>12,AD13<21,AE13>12,AE13<21,AF13>12,AF13<21),3,4))) -> 2 | CM13: =TRIM(CC13&CD13&CE13&CF13) -> CSID | CP13: =VALUE(AG13&CP$2) -> 161 | CQ13: =VALUE(AH13&CQ$2) -> 182 | CR13: =VALUE(AI13&CR$2) -> 193 | CS13: =VALUE(AJ13&CS$2) -> 194 | CU13: =LARGE($CP13:$CS13,CU$2) -> 194 | CV13: =LARGE($CP13:$CS13,CV$2) -> 193 | CW13: =LARGE($CP13:$CS13,CW$2) -> 182 | CX13: =LARGE($CP13:$CS13,CX$2) -> 161 | CZ13: =VLOOKUP(VALUE(RIGHT(CU13,1)),misc!$A$2:$B$5,2,0) -> C | DA13: =VLOOKUP(VALUE(RIGHT(CV13,1)),misc!$A$2:$B$5,2,0) -> S | DB13: =VLOOKUP(VALUE(RIGHT(CW13,1)),misc!$A$2:$B$5,2,0) -> I | DC13: =VLOOKUP(VALUE(RIGHT(CX13,1)),misc!$A$2:$B$5,2,0) -> D | DE13: =IF(VALUE(CU13)>=170,CZ13,"") -> C | DF13: =IF(VALUE(CV13)>=170,DA13,"") -> S | DG13: =IF(VALUE(CW13)>=170,DB13,"") -> I | DH13: =IF(VALUE(CX13)>=170,DC13,"") | DJ13: =IF(VALUE(CU13)<170,CZ13,"") | DK13: =IF(VALUE(CV13)<170,DA13,"") | DL13: =IF(VALUE(CW13)<170,DB13,"") | DM13: =IF(VALUE(CX13)<170,DC13,"") -> D | DN13: =IF(AND(AG13<17,AH13<17,AI13<17,AJ13<17),1,IF(AND(AG13>=17,AH13>=17,AI13>=17,AJ13>=17),2,IF(AND(AG13>12,AG13<21,AH13>12,AH13<21,AI13>12,AI13<21,AJ13>12,AJ13<21),3,4))) -> 3 | DO13: =TRIM(DE13&DF13&DG13&DH13) -> CSI | DP13: =BJ13&CL13&DN13 -> 123 | DQ13: =A13&G13&H13&I13&J13&L13&M13&N13&O13 | DR13: =VLOOKUP(G13,tableD1,3,0) -> 1 | DS13: =VLOOKUP(H13,tableI1,3,0) -> 1 | DT13: =VLOOKUP(I13,table1S,3,0) -> 2 | DU13: =VLOOKUP(J13,table1C,3,0) -> 1 | DV13: =VLOOKUP(L13,table2D,3,0) -> 8 | DW13: =VLOOKUP(M13,table2I,3,0) -> 8 | DX13: =VLOOKUP(N13,table2S,3,0) -> 8 | DY13: =VLOOKUP(O13,table2C,3,0) -> 8 | DZ13: =VLOOKUP(Q13,table3D,3,0) -> 4 | EA13: =VLOOKUP(R13,table3I,3,0) -> 5 | EB13: =VLOOKUP(S13,table3S,3,0) -> 5 | EC13: =VLOOKUP(T13,table3C,3,0) -> 5 | ED13: {=VLOOKUP(INDEX(JD,data!$AA$1),key!$J$3:$L$27,3,0)} -> 6 | EE13: {=VLOOKUP(INDEX(JI,data!$AA$1),key!$J$3:$L$27,3,0)} -> 4 | EF13: {=VLOOKUP(INDEX(JS,data!$AA$1),key!$J$3:$L$27,3,0)} -> 4 | EG13: {=VLOOKUP(INDEX(JC,data!$AA$1),key!$J$3:$L$27,3,0)} -> 7 | EH13: =VLOOKUP(DR13,tabel_jpm,ED13+1,0) -> 8 | EI13: =VLOOKUP(DS13,tabel_jpm,EE13+1,0) -> 16 | EJ13: =VLOOKUP(DT13,tabel_jpm,EF13+1,0) -> 20 | EK13: =VLOOKUP(DU13,tabel_jpm,EG13+1,0) -> 4 | EL13: =IF(B13="Pria",VLOOKUP(AVERAGE(EH13:EK13),agreement_p,4),VLOOKUP(AVERAGE(EH13:EK13),agreement_w,4)) -> 32 | EM13: =IF(DP13<>"444","N/A",EL13) -> N/A | EN13: =VLOOKUP(DV13,tabel_jpm,ED13+1,0) -> 20 | EO13: =VLOOKUP(DW13,tabel_jpm,EE13+1,0) -> 12 | EP13: =VLOOKUP(DX13,tabel_jpm,EF13+1,0) -> 12 | EQ13: =VLOOKUP(DY13,tabel_jpm,EG13+1,0) -> 24 | ER13: =IF(B13="Pria",VLOOKUP(AVERAGE(EN13:EQ13),agreement_p,4),VLOOKUP(AVERAGE(EN13:EQ13),agreement_w,4)) -> 50 | ES13: =IF(DP13<>"444","N/A",ER13) -> N/A | ET13: =VLOOKUP(DZ13,tabel_jpm,ED13+1,0) -> 20 | EU13: =VLOOKUP(EA13,tabel_jpm,EE13+1,0) -> 24 | EV13: =VLOOKUP(EB13,tabel_jpm,EF13+1,0) -> 24 | EW13: =VLOOKUP(EC13,tabel_jpm,EG13+1,0) -> 20 | EX13: =IF(B13="Pria",VLOOKUP(AVERAGE(ET13:EW13),agreement_p,4),VLOOKUP(AVERAGE(ET13:EW13),agreement_w,4)) -> 68 | EY13: =IF(DP13<>"444","N/A",EX13) -> N/A
A14: =data!A14 | B14: =data!B14 | C14: =data!C14 | D14: =data!D14 | E14: =data!E14 | F14: =data!F14 | G14: =data!G14 | H14: =data!H14 | ... W14: =data!W14 | Y14: =VLOOKUP(G14,tableD1,2,0) -> 4 | Z14: =VLOOKUP(H14,tableI1,2,0) -> 3 | AA14: =VLOOKUP(I14,table1S,2,0) -> 5 | AB14: =VLOOKUP(J14,table1C,2,0) -> 4 | AC14: =VLOOKUP(L14,table2D,2,0) -> 31 | AD14: =VLOOKUP(M14,table2I,2,0) -> 31 | AE14: =VLOOKUP(N14,table2S,2,0) -> 32 | AF14: =VLOOKUP(O14,table2C,2,0) -> 32 | AG14: =VLOOKUP(Q14,table3D,2,0) -> 16 | AH14: =VLOOKUP(R14,table3I,2,0) -> 18 | AI14: =VLOOKUP(S14,table3S,2,0) -> 19 | AJ14: =VLOOKUP(T14,table3C,2,0) -> 19 | AL14: =VALUE(Y14&AL$2) -> 41 | AM14: =VALUE(Z14&AM$2) -> 32 | AN14: =VALUE(AA14&AN$2) -> 53 | AO14: =VALUE(AB14&AO$2) -> 44 | AQ14: =LARGE($AL14:$AO14,AQ$2) -> 53 | AR14: =LARGE($AL14:$AO14,AR$2) -> 44 | AS14: =LARGE($AL14:$AO14,AS$2) -> 41 | AT14: =LARGE($AL14:$AO14,AT$2) -> 32 | AV14: =VLOOKUP(VALUE(RIGHT(AQ14,1)),misc!$A$2:$B$5,2,0) -> S | AW14: =VLOOKUP(VALUE(RIGHT(AR14,1)),misc!$A$2:$B$5,2,0) -> C | AX14: =VLOOKUP(VALUE(RIGHT(AS14,1)),misc!$A$2:$B$5,2,0) -> D | AY14: =VLOOKUP(VALUE(RIGHT(AT14,1)),misc!$A$2:$B$5,2,0) -> I | BA14: =IF(VALUE(AQ14)>=170,AV14,"") | BB14: =IF(VALUE(AR14)>=170,AW14,"") | BC14: =IF(VALUE(AS14)>=170,AX14,"") | BD14: =IF(VALUE(AT14)>=170,AY14,"") | BF14: =IF(VALUE(AQ14)<170,AV14,"") -> S | BG14: =IF(VALUE(AR14)<170,AW14,"") -> C | BH14: =IF(VALUE(AS14)<170,AX14,"") -> D | BI14: =IF(VALUE(AT14)<170,AY14,"") -> I | BJ14: =IF(AND(Y14<17,Z14<17,AA14<17,AB14<17),1,IF(AND(Y14>=17,Z14>=17,AA14>=17,AB14>=17),2,IF(AND(Y14>12,Y14<21,Z14>12,Z14<21,AA14>12,AA14<21,AB14>12,AB14<21),3,4))) -> 1 | BK14: =TRIM(BA14&BB14&BC14&BD14) | BN14: =VALUE(AC14&BN$2) -> 311 | BO14: =VALUE(AD14&BO$2) -> 312 | BP14: =VALUE(AE14&BP$2) -> 323 | BQ14: =VALUE(AF14&BQ$2) -> 324 | BS14: =LARGE($BN14:$BQ14,BS$2) -> 324 | BT14: =LARGE($BN14:$BQ14,BT$2) -> 323 | BU14: =LARGE($BN14:$BQ14,BU$2) -> 312 | BV14: =LARGE($BN14:$BQ14,BV$2) -> 311 | BX14: =VLOOKUP(VALUE(RIGHT(BS14,1)),misc!$A$2:$B$5,2,0) -> C | BY14: =VLOOKUP(VALUE(RIGHT(BT14,1)),misc!$A$2:$B$5,2,0) -> S | BZ14: =VLOOKUP(VALUE(RIGHT(BU14,1)),misc!$A$2:$B$5,2,0) -> I | CA14: =VLOOKUP(VALUE(RIGHT(BV14,1)),misc!$A$2:$B$5,2,0) -> D | CC14: =IF(VALUE(BS14)>=170,BX14,"") -> C | CD14: =IF(VALUE(BT14)>=170,BY14,"") -> S | CE14: =IF(VALUE(BU14)>=170,BZ14,"") -> I | CF14: =IF(VALUE(BV14)>=170,CA14,"") -> D | CH14: =IF(VALUE(BS14)<170,BX14,"") | CI14: =IF(VALUE(BT14)<170,BY14,"") | CJ14: =IF(VALUE(BU14)<170,BZ14,"") | CK14: =IF(VALUE(BV14)<170,CA14,"") | CL14: =IF(AND(AC14<17,AD14<17,AE14<17,AF14<17),1,IF(AND(AC14>=17,AD14>=17,AE14>=17,AF14>=17),2,IF(AND(AC14>12,AC14<21,AD14>12,AD14<21,AE14>12,AE14<21,AF14>12,AF14<21),3,4))) -> 2 | CM14: =TRIM(CC14&CD14&CE14&CF14) -> CSID | CP14: =VALUE(AG14&CP$2) -> 161 | CQ14: =VALUE(AH14&CQ$2) -> 182 | CR14: =VALUE(AI14&CR$2) -> 193 | CS14: =VALUE(AJ14&CS$2) -> 194 | CU14: =LARGE($CP14:$CS14,CU$2) -> 194 | CV14: =LARGE($CP14:$CS14,CV$2) -> 193 | CW14: =LARGE($CP14:$CS14,CW$2) -> 182 | CX14: =LARGE($CP14:$CS14,CX$2) -> 161 | CZ14: =VLOOKUP(VALUE(RIGHT(CU14,1)),misc!$A$2:$B$5,2,0) -> C | DA14: =VLOOKUP(VALUE(RIGHT(CV14,1)),misc!$A$2:$B$5,2,0) -> S | DB14: =VLOOKUP(VALUE(RIGHT(CW14,1)),misc!$A$2:$B$5,2,0) -> I | DC14: =VLOOKUP(VALUE(RIGHT(CX14,1)),misc!$A$2:$B$5,2,0) -> D | DE14: =IF(VALUE(CU14)>=170,CZ14,"") -> C | DF14: =IF(VALUE(CV14)>=170,DA14,"") -> S | DG14: =IF(VALUE(CW14)>=170,DB14,"") -> I | DH14: =IF(VALUE(CX14)>=170,DC14,"") | DJ14: =IF(VALUE(CU14)<170,CZ14,"") | DK14: =IF(VALUE(CV14)<170,DA14,"") | DL14: =IF(VALUE(CW14)<170,DB14,"") | DM14: =IF(VALUE(CX14)<170,DC14,"") -> D | DN14: =IF(AND(AG14<17,AH14<17,AI14<17,AJ14<17),1,IF(AND(AG14>=17,AH14>=17,AI14>=17,AJ14>=17),2,IF(AND(AG14>12,AG14<21,AH14>12,AH14<21,AI14>12,AI14<21,AJ14>12,AJ14<21),3,4))) -> 3 | DO14: =TRIM(DE14&DF14&DG14&DH14) -> CSI | DP14: =BJ14&CL14&DN14 -> 123 | DQ14: =A14&G14&H14&I14&J14&L14&M14&N14&O14 | DR14: =VLOOKUP(G14,tableD1,3,0) -> 1 | DS14: =VLOOKUP(H14,tableI1,3,0) -> 1 | DT14: =VLOOKUP(I14,table1S,3,0) -> 2 | DU14: =VLOOKUP(J14,table1C,3,0) -> 1 | DV14: =VLOOKUP(L14,table2D,3,0) -> 8 | DW14: =VLOOKUP(M14,table2I,3,0) -> 8 | DX14: =VLOOKUP(N14,table2S,3,0) -> 8 | DY14: =VLOOKUP(O14,table2C,3,0) -> 8 | DZ14: =VLOOKUP(Q14,table3D,3,0) -> 4 | EA14: =VLOOKUP(R14,table3I,3,0) -> 5 | EB14: =VLOOKUP(S14,table3S,3,0) -> 5 | EC14: =VLOOKUP(T14,table3C,3,0) -> 5 | ED14: {=VLOOKUP(INDEX(JD,data!$AA$1),key!$J$3:$L$27,3,0)} -> 6 | EE14: {=VLOOKUP(INDEX(JI,data!$AA$1),key!$J$3:$L$27,3,0)} -> 4 | EF14: {=VLOOKUP(INDEX(JS,data!$AA$1),key!$J$3:$L$27,3,0)} -> 4 | EG14: {=VLOOKUP(INDEX(JC,data!$AA$1),key!$J$3:$L$27,3,0)} -> 7 | EH14: =VLOOKUP(DR14,tabel_jpm,ED14+1,0) -> 8 | EI14: =VLOOKUP(DS14,tabel_jpm,EE14+1,0) -> 16 | EJ14: =VLOOKUP(DT14,tabel_jpm,EF14+1,0) -> 20 | EK14: =VLOOKUP(DU14,tabel_jpm,EG14+1,0) -> 4 | EL14: =IF(B14="Pria",VLOOKUP(AVERAGE(EH14:EK14),agreement_p,4),VLOOKUP(AVERAGE(EH14:EK14),agreement_w,4)) -> 32 | EM14: =IF(DP14<>"444","N/A",EL14) -> N/A | EN14: =VLOOKUP(DV14,tabel_jpm,ED14+1,0) -> 20 | EO14: =VLOOKUP(DW14,tabel_jpm,EE14+1,0) -> 12 | EP14: =VLOOKUP(DX14,tabel_jpm,EF14+1,0) -> 12 | EQ14: =VLOOKUP(DY14,tabel_jpm,EG14+1,0) -> 24 | ER14: =IF(B14="Pria",VLOOKUP(AVERAGE(EN14:EQ14),agreement_p,4),VLOOKUP(AVERAGE(EN14:EQ14),agreement_w,4)) -> 50 | ES14: =IF(DP14<>"444","N/A",ER14) -> N/A | ET14: =VLOOKUP(DZ14,tabel_jpm,ED14+1,0) -> 20 | EU14: =VLOOKUP(EA14,tabel_jpm,EE14+1,0) -> 24 | EV14: =VLOOKUP(EB14,tabel_jpm,EF14+1,0) -> 24 | EW14: =VLOOKUP(EC14,tabel_jpm,EG14+1,0) -> 20 | EX14: =IF(B14="Pria",VLOOKUP(AVERAGE(ET14:EW14),agreement_p,4),VLOOKUP(AVERAGE(ET14:EW14),agreement_w,4)) -> 68 | EY14: =IF(DP14<>"444","N/A",EX14) -> N/A
... A38: =data!A38 | B38: =data!B38 | C38: =data!C38 | D38: =data!D38 | E38: =data!E38 | F38: =data!F38 | G38: =data!G38 | H38: =data!H38 | ... W38: =data!W38 | Y38: =VLOOKUP(G38,tableD1,2,0) -> 4 | Z38: =VLOOKUP(H38,tableI1,2,0) -> 3 | AA38: =VLOOKUP(I38,table1S,2,0) -> 5 | AB38: =VLOOKUP(J38,table1C,2,0) -> 4 | AC38: =VLOOKUP(L38,table2D,2,0) -> 31 | AD38: =VLOOKUP(M38,table2I,2,0) -> 31 | AE38: =VLOOKUP(N38,table2S,2,0) -> 32 | AF38: =VLOOKUP(O38,table2C,2,0) -> 32 | AG38: =VLOOKUP(Q38,table3D,2,0) -> 16 | AH38: =VLOOKUP(R38,table3I,2,0) -> 18 | AI38: =VLOOKUP(S38,table3S,2,0) -> 19 | AJ38: =VLOOKUP(T38,table3C,2,0) -> 19 | AL38: =VALUE(Y38&AL$2) -> 41 | AM38: =VALUE(Z38&AM$2) -> 32 | AN38: =VALUE(AA38&AN$2) -> 53 | AO38: =VALUE(AB38&AO$2) -> 44 | AQ38: =LARGE($AL38:$AO38,AQ$2) -> 53 | AR38: =LARGE($AL38:$AO38,AR$2) -> 44 | AS38: =LARGE($AL38:$AO38,AS$2) -> 41 | AT38: =LARGE($AL38:$AO38,AT$2) -> 32 | AV38: =VLOOKUP(VALUE(RIGHT(AQ38,1)),misc!$A$2:$B$5,2,0) -> S | AW38: =VLOOKUP(VALUE(RIGHT(AR38,1)),misc!$A$2:$B$5,2,0) -> C | AX38: =VLOOKUP(VALUE(RIGHT(AS38,1)),misc!$A$2:$B$5,2,0) -> D | AY38: =VLOOKUP(VALUE(RIGHT(AT38,1)),misc!$A$2:$B$5,2,0) -> I | BA38: =IF(VALUE(AQ38)>=170,AV38,"") | BB38: =IF(VALUE(AR38)>=170,AW38,"") | BC38: =IF(VALUE(AS38)>=170,AX38,"") | BD38: =IF(VALUE(AT38)>=170,AY38,"") | BF38: =IF(VALUE(AQ38)<170,AV38,"") -> S | BG38: =IF(VALUE(AR38)<170,AW38,"") -> C | BH38: =IF(VALUE(AS38)<170,AX38,"") -> D | BI38: =IF(VALUE(AT38)<170,AY38,"") -> I | BJ38: =IF(AND(Y38<17,Z38<17,AA38<17,AB38<17),1,IF(AND(Y38>=17,Z38>=17,AA38>=17,AB38>=17),2,IF(AND(Y38>12,Y38<21,Z38>12,Z38<21,AA38>12,AA38<21,AB38>12,AB38<21),3,4))) -> 1 | BK38: =TRIM(BA38&BB38&BC38&BD38) | BN38: =VALUE(AC38&BN$2) -> 311 | BO38: =VALUE(AD38&BO$2) -> 312 | BP38: =VALUE(AE38&BP$2) -> 323 | BQ38: =VALUE(AF38&BQ$2) -> 324 | BS38: =LARGE($BN38:$BQ38,BS$2) -> 324 | BT38: =LARGE($BN38:$BQ38,BT$2) -> 323 | BU38: =LARGE($BN38:$BQ38,BU$2) -> 312 | BV38: =LARGE($BN38:$BQ38,BV$2) -> 311 | BX38: =VLOOKUP(VALUE(RIGHT(BS38,1)),misc!$A$2:$B$5,2,0) -> C | BY38: =VLOOKUP(VALUE(RIGHT(BT38,1)),misc!$A$2:$B$5,2,0) -> S | BZ38: =VLOOKUP(VALUE(RIGHT(BU38,1)),misc!$A$2:$B$5,2,0) -> I | CA38: =VLOOKUP(VALUE(RIGHT(BV38,1)),misc!$A$2:$B$5,2,0) -> D | CC38: =IF(VALUE(BS38)>=170,BX38,"") -> C | CD38: =IF(VALUE(BT38)>=170,BY38,"") -> S | CE38: =IF(VALUE(BU38)>=170,BZ38,"") -> I | CF38: =IF(VALUE(BV38)>=170,CA38,"") -> D | CH38: =IF(VALUE(BS38)<170,BX38,"") | CI38: =IF(VALUE(BT38)<170,BY38,"") | CJ38: =IF(VALUE(BU38)<170,BZ38,"") | CK38: =IF(VALUE(BV38)<170,CA38,"") | CL38: =IF(AND(AC38<17,AD38<17,AE38<17,AF38<17),1,IF(AND(AC38>=17,AD38>=17,AE38>=17,AF38>=17),2,IF(AND(AC38>12,AC38<21,AD38>12,AD38<21,AE38>12,AE38<21,AF38>12,AF38<21),3,4))) -> 2 | CM38: =TRIM(CC38&CD38&CE38&CF38) -> CSID | CP38: =VALUE(AG38&CP$2) -> 161 | CQ38: =VALUE(AH38&CQ$2) -> 182 | CR38: =VALUE(AI38&CR$2) -> 193 | CS38: =VALUE(AJ38&CS$2) -> 194 | CU38: =LARGE($CP38:$CS38,CU$2) -> 194 | CV38: =LARGE($CP38:$CS38,CV$2) -> 193 | CW38: =LARGE($CP38:$CS38,CW$2) -> 182 | CX38: =LARGE($CP38:$CS38,CX$2) -> 161 | CZ38: =VLOOKUP(VALUE(RIGHT(CU38,1)),misc!$A$2:$B$5,2,0) -> C | DA38: =VLOOKUP(VALUE(RIGHT(CV38,1)),misc!$A$2:$B$5,2,0) -> S | DB38: =VLOOKUP(VALUE(RIGHT(CW38,1)),misc!$A$2:$B$5,2,0) -> I | DC38: =VLOOKUP(VALUE(RIGHT(CX38,1)),misc!$A$2:$B$5,2,0) -> D | DE38: =IF(VALUE(CU38)>=170,CZ38,"") -> C | DF38: =IF(VALUE(CV38)>=170,DA38,"") -> S | DG38: =IF(VALUE(CW38)>=170,DB38,"") -> I | DH38: =IF(VALUE(CX38)>=170,DC38,"") | DJ38: =IF(VALUE(CU38)<170,CZ38,"") | DK38: =IF(VALUE(CV38)<170,DA38,"") | DL38: =IF(VALUE(CW38)<170,DB38,"") | DM38: =IF(VALUE(CX38)<170,DC38,"") -> D | DN38: =IF(AND(AG38<17,AH38<17,AI38<17,AJ38<17),1,IF(AND(AG38>=17,AH38>=17,AI38>=17,AJ38>=17),2,IF(AND(AG38>12,AG38<21,AH38>12,AH38<21,AI38>12,AI38<21,AJ38>12,AJ38<21),3,4))) -> 3 | DO38: =TRIM(DE38&DF38&DG38&DH38) -> CSI | DP38: =BJ38&CL38&DN38 -> 123 | DQ38: =A38&G38&H38&I38&J38&L38&M38&N38&O38 | DR38: =VLOOKUP(G38,tableD1,3,0) -> 1 | DS38: =VLOOKUP(H38,tableI1,3,0) -> 1 | DT38: =VLOOKUP(I38,table1S,3,0) -> 2 | DU38: =VLOOKUP(J38,table1C,3,0) -> 1 | DV38: =VLOOKUP(L38,table2D,3,0) -> 8 | DW38: =VLOOKUP(M38,table2I,3,0) -> 8 | DX38: =VLOOKUP(N38,table2S,3,0) -> 8 | DY38: =VLOOKUP(O38,table2C,3,0) -> 8 | DZ38: =VLOOKUP(Q38,table3D,3,0) -> 4 | EA38: =VLOOKUP(R38,table3I,3,0) -> 5 | EB38: =VLOOKUP(S38,table3S,3,0) -> 5 | EC38: =VLOOKUP(T38,table3C,3,0) -> 5 | ED38: {=VLOOKUP(INDEX(JD,data!$AA$1),key!$J$3:$L$27,3,0)} -> 6 | EE38: {=VLOOKUP(INDEX(JI,data!$AA$1),key!$J$3:$L$27,3,0)} -> 4 | EF38: {=VLOOKUP(INDEX(JS,data!$AA$1),key!$J$3:$L$27,3,0)} -> 4 | EG38: {=VLOOKUP(INDEX(JC,data!$AA$1),key!$J$3:$L$27,3,0)} -> 7 | EH38: =VLOOKUP(DR38,tabel_jpm,ED38+1,0) -> 8 | EI38: =VLOOKUP(DS38,tabel_jpm,EE38+1,0) -> 16 | EJ38: =VLOOKUP(DT38,tabel_jpm,EF38+1,0) -> 20 | EK38: =VLOOKUP(DU38,tabel_jpm,EG38+1,0) -> 4 | EL38: =IF(B38="Pria",VLOOKUP(AVERAGE(EH38:EK38),agreement_p,4),VLOOKUP(AVERAGE(EH38:EK38),agreement_w,4)) -> 32 | EM38: =IF(DP38<>"444","N/A",EL38) -> N/A | EN38: =VLOOKUP(DV38,tabel_jpm,ED38+1,0) -> 20 | EO38: =VLOOKUP(DW38,tabel_jpm,EE38+1,0) -> 12 | EP38: =VLOOKUP(DX38,tabel_jpm,EF38+1,0) -> 12 | EQ38: =VLOOKUP(DY38,tabel_jpm,EG38+1,0) -> 24 | ER38: =IF(B38="Pria",VLOOKUP(AVERAGE(EN38:EQ38),agreement_p,4),VLOOKUP(AVERAGE(EN38:EQ38),agreement_w,4)) -> 50 | ES38: =IF(DP38<>"444","N/A",ER38) -> N/A | ET38: =VLOOKUP(DZ38,tabel_jpm,ED38+1,0) -> 20 | EU38: =VLOOKUP(EA38,tabel_jpm,EE38+1,0) -> 24 | EV38: =VLOOKUP(EB38,tabel_jpm,EF38+1,0) -> 24 | EW38: =VLOOKUP(EC38,tabel_jpm,EG38+1,0) -> 20 | EX38: =IF(B38="Pria",VLOOKUP(AVERAGE(ET38:EW38),agreement_p,4),VLOOKUP(AVERAGE(ET38:EW38),agreement_w,4)) -> 68 | EY38: =IF(DP38<>"444","N/A",EX38) -> N/A
A39: =data!#REF! -> #ERROR! | B39: =data!B39 | C39: =data!C39 | D39: =data!D39 | E39: =data!E39 | F39: =data!F39 | G39: =data!#REF! -> #ERROR! | H39: =data!#REF! -> #ERROR! | I39: =data!#REF! -> #ERROR! | J39: =data!#REF! -> #ERROR! | K39: =data!#REF! -> #ERROR! | L39: =data!#REF! -> #ERROR! | M39: =data!#REF! -> #ERROR! | N39: =data!#REF! -> #ERROR! | ... T39: =data!#REF! -> #ERROR! | U39: =data!U39 | V39: =data!V39 | W39: =data!W39 | Y39: =VLOOKUP(G39,tableD1,2,0) -> #ERROR! | Z39: =VLOOKUP(H39,tableI1,2,0) -> #ERROR! | AA39: =VLOOKUP(I39,table1S,2,0) -> #ERROR! | AB39: =VLOOKUP(J39,table1C,2,0) -> #ERROR! | AC39: =VLOOKUP(L39,table2D,2,0) -> #ERROR! | AD39: =VLOOKUP(M39,table2I,2,0) -> #ERROR! | AE39: =VLOOKUP(N39,table2S,2,0) -> #ERROR! | AF39: =VLOOKUP(O39,table2C,2,0) -> #ERROR! | AG39: =VLOOKUP(Q39,table3D,2,0) -> #ERROR! | AH39: =VLOOKUP(R39,table3I,2,0) -> #ERROR! | AI39: =VLOOKUP(S39,table3S,2,0) -> #ERROR! | AJ39: =VLOOKUP(T39,table3C,2,0) -> #ERROR! | AL39: =VALUE(Y39&AL$2) -> #ERROR! | AM39: =VALUE(Z39&AM$2) -> #ERROR! | AN39: =VALUE(AA39&AN$2) -> #ERROR! | AO39: =VALUE(AB39&AO$2) -> #ERROR! | AQ39: =LARGE($AL39:$AO39,AQ$2) -> #ERROR! | AR39: =LARGE($AL39:$AO39,AR$2) -> #ERROR! | AS39: =LARGE($AL39:$AO39,AS$2) -> #ERROR! | AT39: =LARGE($AL39:$AO39,AT$2) -> #ERROR! | AV39: =VLOOKUP(VALUE(RIGHT(AQ39,1)),misc!$A$2:$B$5,2,0) -> #ERROR! | AW39: =VLOOKUP(VALUE(RIGHT(AR39,1)),misc!$A$2:$B$5,2,0) -> #ERROR! | AX39: =VLOOKUP(VALUE(RIGHT(AS39,1)),misc!$A$2:$B$5,2,0) -> #ERROR! | AY39: =VLOOKUP(VALUE(RIGHT(AT39,1)),misc!$A$2:$B$5,2,0) -> #ERROR! | BA39: =IF(VALUE(AQ39)>=170,AV39,"") -> #ERROR! | BB39: =IF(VALUE(AR39)>=170,AW39,"") -> #ERROR! | BC39: =IF(VALUE(AS39)>=170,AX39,"") -> #ERROR! | BD39: =IF(VALUE(AT39)>=170,AY39,"") -> #ERROR! | BF39: =IF(VALUE(AQ39)<170,AV39,"") -> #ERROR! | BG39: =IF(VALUE(AR39)<170,AW39,"") -> #ERROR! | BH39: =IF(VALUE(AS39)<170,AX39,"") -> #ERROR! | BI39: =IF(VALUE(AT39)<170,AY39,"") -> #ERROR! | BJ39: =IF(AND(Y39<17,Z39<17,AA39<17,AB39<17),1,IF(AND(Y39>=17,Z39>=17,AA39>=17,AB39>=17),2,IF(AND(Y39>12,Y39<21,Z39>12,Z39<21,AA39>12,AA39<21,AB39>12,AB39<21),3,4))) -> #ERROR! | BK39: =TRIM(BA39&BB39&BC39&BD39) -> #ERROR! | BN39: =VALUE(AC39&BN$2) -> #ERROR! | BO39: =VALUE(AD39&BO$2) -> #ERROR! | BP39: =VALUE(AE39&BP$2) -> #ERROR! | BQ39: =VALUE(AF39&BQ$2) -> #ERROR! | BS39: =LARGE($BN39:$BQ39,BS$2) -> #ERROR! | BT39: =LARGE($BN39:$BQ39,BT$2) -> #ERROR! | BU39: =LARGE($BN39:$BQ39,BU$2) -> #ERROR! | BV39: =LARGE($BN39:$BQ39,BV$2) -> #ERROR! | BX39: =VLOOKUP(VALUE(RIGHT(BS39,1)),misc!$A$2:$B$5,2,0) -> #ERROR! | BY39: =VLOOKUP(VALUE(RIGHT(BT39,1)),misc!$A$2:$B$5,2,0) -> #ERROR! | BZ39: =VLOOKUP(VALUE(RIGHT(BU39,1)),misc!$A$2:$B$5,2,0) -> #ERROR! | CA39: =VLOOKUP(VALUE(RIGHT(BV39,1)),misc!$A$2:$B$5,2,0) -> #ERROR! | CC39: =IF(VALUE(BS39)>=170,BX39,"") -> #ERROR! | CD39: =IF(VALUE(BT39)>=170,BY39,"") -> #ERROR! | CE39: =IF(VALUE(BU39)>=170,BZ39,"") -> #ERROR! | CF39: =IF(VALUE(BV39)>=170,CA39,"") -> #ERROR! | CH39: =IF(VALUE(BS39)<170,BX39,"") -> #ERROR! | CI39: =IF(VALUE(BT39)<170,BY39,"") -> #ERROR! | CJ39: =IF(VALUE(BU39)<170,BZ39,"") -> #ERROR! | CK39: =IF(VALUE(BV39)<170,CA39,"") -> #ERROR! | CL39: =IF(AND(AC39<17,AD39<17,AE39<17,AF39<17),1,IF(AND(AC39>=17,AD39>=17,AE39>=17,AF39>=17),2,IF(AND(AC39>12,AC39<21,AD39>12,AD39<21,AE39>12,AE39<21,AF39>12,AF39<21),3,4))) -> #ERROR! | CM39: =TRIM(CC39&CD39&CE39&CF39) -> #ERROR! | CP39: =VALUE(AG39&CP$2) -> #ERROR! | CQ39: =VALUE(AH39&CQ$2) -> #ERROR! | CR39: =VALUE(AI39&CR$2) -> #ERROR! | CS39: =VALUE(AJ39&CS$2) -> #ERROR! | CU39: =LARGE($CP39:$CS39,CU$2) -> #ERROR! | CV39: =LARGE($CP39:$CS39,CV$2) -> #ERROR! | CW39: =LARGE($CP39:$CS39,CW$2) -> #ERROR! | CX39: =LARGE($CP39:$CS39,CX$2) -> #ERROR! | CZ39: =VLOOKUP(VALUE(RIGHT(CU39,1)),misc!$A$2:$B$5,2,0) -> #ERROR! | DA39: =VLOOKUP(VALUE(RIGHT(CV39,1)),misc!$A$2:$B$5,2,0) -> #ERROR! | DB39: =VLOOKUP(VALUE(RIGHT(CW39,1)),misc!$A$2:$B$5,2,0) -> #ERROR! | DC39: =VLOOKUP(VALUE(RIGHT(CX39,1)),misc!$A$2:$B$5,2,0) -> #ERROR! | DE39: =IF(VALUE(CU39)>=170,CZ39,"") -> #ERROR! | DF39: =IF(VALUE(CV39)>=170,DA39,"") -> #ERROR! | DG39: =IF(VALUE(CW39)>=170,DB39,"") -> #ERROR! | DH39: =IF(VALUE(CX39)>=170,DC39,"") -> #ERROR! | DJ39: =IF(VALUE(CU39)<170,CZ39,"") -> #ERROR! | DK39: =IF(VALUE(CV39)<170,DA39,"") -> #ERROR! | DL39: =IF(VALUE(CW39)<170,DB39,"") -> #ERROR! | DM39: =IF(VALUE(CX39)<170,DC39,"") -> #ERROR! | DN39: =IF(AND(AG39<17,AH39<17,AI39<17,AJ39<17),1,IF(AND(AG39>=17,AH39>=17,AI39>=17,AJ39>=17),2,IF(AND(AG39>12,AG39<21,AH39>12,AH39<21,AI39>12,AI39<21,AJ39>12,AJ39<21),3,4))) -> #ERROR! | DO39: =TRIM(DE39&DF39&DG39&DH39) -> #ERROR! | DP39: =BJ39&CL39&DN39 -> #ERROR! | DQ39: =A39&G39&H39&I39&J39&L39&M39&N39&O39 -> #ERROR! | DR39: =VLOOKUP(G39,tableD1,3,0) -> #ERROR! | DS39: =VLOOKUP(H39,tableI1,3,0) -> #ERROR! | DT39: =VLOOKUP(I39,table1S,3,0) -> #ERROR! | DU39: =VLOOKUP(J39,table1C,3,0) -> #ERROR! | DV39: =VLOOKUP(L39,table2D,3,0) -> #ERROR! | DW39: =VLOOKUP(M39,table2I,3,0) -> #ERROR! | DX39: =VLOOKUP(N39,table2S,3,0) -> #ERROR! | DY39: =VLOOKUP(O39,table2C,3,0) -> #ERROR! | DZ39: =VLOOKUP(Q39,table3D,3,0) -> #ERROR! | EA39: =VLOOKUP(R39,table3I,3,0) -> #ERROR! | EB39: =VLOOKUP(S39,table3S,3,0) -> #ERROR! | EC39: =VLOOKUP(T39,table3C,3,0) -> #ERROR! | ED39: {=VLOOKUP(INDEX(JD,data!$AA$1),key!$J$3:$L$27,3,0)} -> 6 | EE39: {=VLOOKUP(INDEX(JI,data!$AA$1),key!$J$3:$L$27,3,0)} -> 4 | EF39: {=VLOOKUP(INDEX(JS,data!$AA$1),key!$J$3:$L$27,3,0)} -> 4 | EG39: {=VLOOKUP(INDEX(JC,data!$AA$1),key!$J$3:$L$27,3,0)} -> 7 | EH39: =VLOOKUP(DR39,tabel_jpm,ED39+1,0) -> #ERROR! | EI39: =VLOOKUP(DS39,tabel_jpm,EE39+1,0) -> #ERROR! | EJ39: =VLOOKUP(DT39,tabel_jpm,EF39+1,0) -> #ERROR! | EK39: =VLOOKUP(DU39,tabel_jpm,EG39+1,0) -> #ERROR! | EL39: =IF(B39="Pria",VLOOKUP(AVERAGE(EH39:EK39),agreement_p,4),VLOOKUP(AVERAGE(EH39:EK39),agreement_w,4)) -> #ERROR! | EM39: =IF(DP39<>"444","N/A",EL39) -> #ERROR! | EN39: =VLOOKUP(DV39,tabel_jpm,ED39+1,0) -> #ERROR! | EO39: =VLOOKUP(DW39,tabel_jpm,EE39+1,0) -> #ERROR! | EP39: =VLOOKUP(DX39,tabel_jpm,EF39+1,0) -> #ERROR! | EQ39: =VLOOKUP(DY39,tabel_jpm,EG39+1,0) -> #ERROR! | ER39: =IF(B39="Pria",VLOOKUP(AVERAGE(EN39:EQ39),agreement_p,4),VLOOKUP(AVERAGE(EN39:EQ39),agreement_w,4)) -> #ERROR! | ES39: =IF(DP39<>"444","N/A",ER39) -> #ERROR! | ET39: =VLOOKUP(DZ39,tabel_jpm,ED39+1,0) -> #ERROR! | EU39: =VLOOKUP(EA39,tabel_jpm,EE39+1,0) -> #ERROR! | EV39: =VLOOKUP(EB39,tabel_jpm,EF39+1,0) -> #ERROR! | EW39: =VLOOKUP(EC39,tabel_jpm,EG39+1,0) -> #ERROR! | EX39: =IF(B39="Pria",VLOOKUP(AVERAGE(ET39:EW39),agreement_p,4),VLOOKUP(AVERAGE(ET39:EW39),agreement_w,4)) -> #ERROR! | EY39: =IF(DP39<>"444","N/A",EX39) -> #ERROR!
A40: =data!A40 | B40: =data!B40 | C40: =data!C40 | D40: =data!D40 | E40: =data!E40 | F40: =data!F40 | G40: =data!G40 | H40: =data!H40 | ... W40: =data!W40 | Y40: =VLOOKUP(G40,tableD1,2,0) -> 4 | Z40: =VLOOKUP(H40,tableI1,2,0) -> 3 | AA40: =VLOOKUP(I40,table1S,2,0) -> 5 | AB40: =VLOOKUP(J40,table1C,2,0) -> 4 | AC40: =VLOOKUP(L40,table2D,2,0) -> 31 | AD40: =VLOOKUP(M40,table2I,2,0) -> 31 | AE40: =VLOOKUP(N40,table2S,2,0) -> 32 | AF40: =VLOOKUP(O40,table2C,2,0) -> 32 | AG40: =VLOOKUP(Q40,table3D,2,0) -> 16 | AH40: =VLOOKUP(R40,table3I,2,0) -> 18 | AI40: =VLOOKUP(S40,table3S,2,0) -> 19 | AJ40: =VLOOKUP(T40,table3C,2,0) -> 19 | AL40: =VALUE(Y40&AL$2) -> 41 | AM40: =VALUE(Z40&AM$2) -> 32 | AN40: =VALUE(AA40&AN$2) -> 53 | AO40: =VALUE(AB40&AO$2) -> 44 | AQ40: =LARGE($AL40:$AO40,AQ$2) -> 53 | AR40: =LARGE($AL40:$AO40,AR$2) -> 44 | AS40: =LARGE($AL40:$AO40,AS$2) -> 41 | AT40: =LARGE($AL40:$AO40,AT$2) -> 32 | AV40: =VLOOKUP(VALUE(RIGHT(AQ40,1)),misc!$A$2:$B$5,2,0) -> S | AW40: =VLOOKUP(VALUE(RIGHT(AR40,1)),misc!$A$2:$B$5,2,0) -> C | AX40: =VLOOKUP(VALUE(RIGHT(AS40,1)),misc!$A$2:$B$5,2,0) -> D | AY40: =VLOOKUP(VALUE(RIGHT(AT40,1)),misc!$A$2:$B$5,2,0) -> I | BA40: =IF(VALUE(AQ40)>=170,AV40,"") | BB40: =IF(VALUE(AR40)>=170,AW40,"") | BC40: =IF(VALUE(AS40)>=170,AX40,"") | BD40: =IF(VALUE(AT40)>=170,AY40,"") | BF40: =IF(VALUE(AQ40)<170,AV40,"") -> S | BG40: =IF(VALUE(AR40)<170,AW40,"") -> C | BH40: =IF(VALUE(AS40)<170,AX40,"") -> D | BI40: =IF(VALUE(AT40)<170,AY40,"") -> I | BJ40: =IF(AND(Y40<17,Z40<17,AA40<17,AB40<17),1,IF(AND(Y40>=17,Z40>=17,AA40>=17,AB40>=17),2,IF(AND(Y40>12,Y40<21,Z40>12,Z40<21,AA40>12,AA40<21,AB40>12,AB40<21),3,4))) -> 1 | BK40: =TRIM(BA40&BB40&BC40&BD40) | BN40: =VALUE(AC40&BN$2) -> 311 | BO40: =VALUE(AD40&BO$2) -> 312 | BP40: =VALUE(AE40&BP$2) -> 323 | BQ40: =VALUE(AF40&BQ$2) -> 324 | BS40: =LARGE($BN40:$BQ40,BS$2) -> 324 | BT40: =LARGE($BN40:$BQ40,BT$2) -> 323 | BU40: =LARGE($BN40:$BQ40,BU$2) -> 312 | BV40: =LARGE($BN40:$BQ40,BV$2) -> 311 | BX40: =VLOOKUP(VALUE(RIGHT(BS40,1)),misc!$A$2:$B$5,2,0) -> C | BY40: =VLOOKUP(VALUE(RIGHT(BT40,1)),misc!$A$2:$B$5,2,0) -> S | BZ40: =VLOOKUP(VALUE(RIGHT(BU40,1)),misc!$A$2:$B$5,2,0) -> I | CA40: =VLOOKUP(VALUE(RIGHT(BV40,1)),misc!$A$2:$B$5,2,0) -> D | CC40: =IF(VALUE(BS40)>=170,BX40,"") -> C | CD40: =IF(VALUE(BT40)>=170,BY40,"") -> S | CE40: =IF(VALUE(BU40)>=170,BZ40,"") -> I | CF40: =IF(VALUE(BV40)>=170,CA40,"") -> D | CH40: =IF(VALUE(BS40)<170,BX40,"") | CI40: =IF(VALUE(BT40)<170,BY40,"") | CJ40: =IF(VALUE(BU40)<170,BZ40,"") | CK40: =IF(VALUE(BV40)<170,CA40,"") | CL40: =IF(AND(AC40<17,AD40<17,AE40<17,AF40<17),1,IF(AND(AC40>=17,AD40>=17,AE40>=17,AF40>=17),2,IF(AND(AC40>12,AC40<21,AD40>12,AD40<21,AE40>12,AE40<21,AF40>12,AF40<21),3,4))) -> 2 | CM40: =TRIM(CC40&CD40&CE40&CF40) -> CSID | CP40: =VALUE(AG40&CP$2) -> 161 | CQ40: =VALUE(AH40&CQ$2) -> 182 | CR40: =VALUE(AI40&CR$2) -> 193 | CS40: =VALUE(AJ40&CS$2) -> 194 | CU40: =LARGE($CP40:$CS40,CU$2) -> 194 | CV40: =LARGE($CP40:$CS40,CV$2) -> 193 | CW40: =LARGE($CP40:$CS40,CW$2) -> 182 | CX40: =LARGE($CP40:$CS40,CX$2) -> 161 | CZ40: =VLOOKUP(VALUE(RIGHT(CU40,1)),misc!$A$2:$B$5,2,0) -> C | DA40: =VLOOKUP(VALUE(RIGHT(CV40,1)),misc!$A$2:$B$5,2,0) -> S | DB40: =VLOOKUP(VALUE(RIGHT(CW40,1)),misc!$A$2:$B$5,2,0) -> I | DC40: =VLOOKUP(VALUE(RIGHT(CX40,1)),misc!$A$2:$B$5,2,0) -> D | DE40: =IF(VALUE(CU40)>=170,CZ40,"") -> C | DF40: =IF(VALUE(CV40)>=170,DA40,"") -> S | DG40: =IF(VALUE(CW40)>=170,DB40,"") -> I | DH40: =IF(VALUE(CX40)>=170,DC40,"") | DJ40: =IF(VALUE(CU40)<170,CZ40,"") | DK40: =IF(VALUE(CV40)<170,DA40,"") | DL40: =IF(VALUE(CW40)<170,DB40,"") | DM40: =IF(VALUE(CX40)<170,DC40,"") -> D | DN40: =IF(AND(AG40<17,AH40<17,AI40<17,AJ40<17),1,IF(AND(AG40>=17,AH40>=17,AI40>=17,AJ40>=17),2,IF(AND(AG40>12,AG40<21,AH40>12,AH40<21,AI40>12,AI40<21,AJ40>12,AJ40<21),3,4))) -> 3 | DO40: =TRIM(DE40&DF40&DG40&DH40) -> CSI | DP40: =BJ40&CL40&DN40 -> 123 | DQ40: =A40&G40&H40&I40&J40&L40&M40&N40&O40 | DR40: =VLOOKUP(G40,tableD1,3,0) -> 1 | DS40: =VLOOKUP(H40,tableI1,3,0) -> 1 | DT40: =VLOOKUP(I40,table1S,3,0) -> 2 | DU40: =VLOOKUP(J40,table1C,3,0) -> 1 | DV40: =VLOOKUP(L40,table2D,3,0) -> 8 | DW40: =VLOOKUP(M40,table2I,3,0) -> 8 | DX40: =VLOOKUP(N40,table2S,3,0) -> 8 | DY40: =VLOOKUP(O40,table2C,3,0) -> 8 | DZ40: =VLOOKUP(Q40,table3D,3,0) -> 4 | EA40: =VLOOKUP(R40,table3I,3,0) -> 5 | EB40: =VLOOKUP(S40,table3S,3,0) -> 5 | EC40: =VLOOKUP(T40,table3C,3,0) -> 5 | ED40: {=VLOOKUP(INDEX(JD,data!$AA$1),key!$J$3:$L$27,3,0)} -> 6 | EE40: {=VLOOKUP(INDEX(JI,data!$AA$1),key!$J$3:$L$27,3,0)} -> 4 | EF40: {=VLOOKUP(INDEX(JS,data!$AA$1),key!$J$3:$L$27,3,0)} -> 4 | EG40: {=VLOOKUP(INDEX(JC,data!$AA$1),key!$J$3:$L$27,3,0)} -> 7 | EH40: =VLOOKUP(DR40,tabel_jpm,ED40+1,0) -> 8 | EI40: =VLOOKUP(DS40,tabel_jpm,EE40+1,0) -> 16 | EJ40: =VLOOKUP(DT40,tabel_jpm,EF40+1,0) -> 20 | EK40: =VLOOKUP(DU40,tabel_jpm,EG40+1,0) -> 4 | EL40: =IF(B40="Pria",VLOOKUP(AVERAGE(EH40:EK40),agreement_p,4),VLOOKUP(AVERAGE(EH40:EK40),agreement_w,4)) -> 32 | EM40: =IF(DP40<>"444","N/A",EL40) -> N/A | EN40: =VLOOKUP(DV40,tabel_jpm,ED40+1,0) -> 20 | EO40: =VLOOKUP(DW40,tabel_jpm,EE40+1,0) -> 12 | EP40: =VLOOKUP(DX40,tabel_jpm,EF40+1,0) -> 12 | EQ40: =VLOOKUP(DY40,tabel_jpm,EG40+1,0) -> 24 | ER40: =IF(B40="Pria",VLOOKUP(AVERAGE(EN40:EQ40),agreement_p,4),VLOOKUP(AVERAGE(EN40:EQ40),agreement_w,4)) -> 50 | ES40: =IF(DP40<>"444","N/A",ER40) -> N/A | ET40: =VLOOKUP(DZ40,tabel_jpm,ED40+1,0) -> 20 | EU40: =VLOOKUP(EA40,tabel_jpm,EE40+1,0) -> 24 | EV40: =VLOOKUP(EB40,tabel_jpm,EF40+1,0) -> 24 | EW40: =VLOOKUP(EC40,tabel_jpm,EG40+1,0) -> 20 | EX40: =IF(B40="Pria",VLOOKUP(AVERAGE(ET40:EW40),agreement_p,4),VLOOKUP(AVERAGE(ET40:EW40),agreement_w,4)) -> 68 | EY40: =IF(DP40<>"444","N/A",EX40) -> N/A
A41: =data!A41 | B41: =data!B41 | C41: =data!C41 | D41: =data!D41 | E41: =data!E41 | F41: =data!F41 | G41: =data!G41 | H41: =data!H41 | ... W41: =data!W41 | Y41: =VLOOKUP(G41,tableD1,2,0) -> 4 | Z41: =VLOOKUP(H41,tableI1,2,0) -> 3 | AA41: =VLOOKUP(I41,table1S,2,0) -> 5 | AB41: =VLOOKUP(J41,table1C,2,0) -> 4 | AC41: =VLOOKUP(L41,table2D,2,0) -> 31 | AD41: =VLOOKUP(M41,table2I,2,0) -> 31 | AE41: =VLOOKUP(N41,table2S,2,0) -> 32 | AF41: =VLOOKUP(O41,table2C,2,0) -> 32 | AG41: =VLOOKUP(Q41,table3D,2,0) -> 16 | AH41: =VLOOKUP(R41,table3I,2,0) -> 18 | AI41: =VLOOKUP(S41,table3S,2,0) -> 19 | AJ41: =VLOOKUP(T41,table3C,2,0) -> 19 | AL41: =VALUE(Y41&AL$2) -> 41 | AM41: =VALUE(Z41&AM$2) -> 32 | AN41: =VALUE(AA41&AN$2) -> 53 | AO41: =VALUE(AB41&AO$2) -> 44 | AQ41: =LARGE($AL41:$AO41,AQ$2) -> 53 | AR41: =LARGE($AL41:$AO41,AR$2) -> 44 | AS41: =LARGE($AL41:$AO41,AS$2) -> 41 | AT41: =LARGE($AL41:$AO41,AT$2) -> 32 | AV41: =VLOOKUP(VALUE(RIGHT(AQ41,1)),misc!$A$2:$B$5,2,0) -> S | AW41: =VLOOKUP(VALUE(RIGHT(AR41,1)),misc!$A$2:$B$5,2,0) -> C | AX41: =VLOOKUP(VALUE(RIGHT(AS41,1)),misc!$A$2:$B$5,2,0) -> D | AY41: =VLOOKUP(VALUE(RIGHT(AT41,1)),misc!$A$2:$B$5,2,0) -> I | BA41: =IF(VALUE(AQ41)>=170,AV41,"") | BB41: =IF(VALUE(AR41)>=170,AW41,"") | BC41: =IF(VALUE(AS41)>=170,AX41,"") | BD41: =IF(VALUE(AT41)>=170,AY41,"") | BF41: =IF(VALUE(AQ41)<170,AV41,"") -> S | BG41: =IF(VALUE(AR41)<170,AW41,"") -> C | BH41: =IF(VALUE(AS41)<170,AX41,"") -> D | BI41: =IF(VALUE(AT41)<170,AY41,"") -> I | BJ41: =IF(AND(Y41<17,Z41<17,AA41<17,AB41<17),1,IF(AND(Y41>=17,Z41>=17,AA41>=17,AB41>=17),2,IF(AND(Y41>12,Y41<21,Z41>12,Z41<21,AA41>12,AA41<21,AB41>12,AB41<21),3,4))) -> 1 | BK41: =TRIM(BA41&BB41&BC41&BD41) | BN41: =VALUE(AC41&BN$2) -> 311 | BO41: =VALUE(AD41&BO$2) -> 312 | BP41: =VALUE(AE41&BP$2) -> 323 | BQ41: =VALUE(AF41&BQ$2) -> 324 | BS41: =LARGE($BN41:$BQ41,BS$2) -> 324 | BT41: =LARGE($BN41:$BQ41,BT$2) -> 323 | BU41: =LARGE($BN41:$BQ41,BU$2) -> 312 | BV41: =LARGE($BN41:$BQ41,BV$2) -> 311 | BX41: =VLOOKUP(VALUE(RIGHT(BS41,1)),misc!$A$2:$B$5,2,0) -> C | BY41: =VLOOKUP(VALUE(RIGHT(BT41,1)),misc!$A$2:$B$5,2,0) -> S | BZ41: =VLOOKUP(VALUE(RIGHT(BU41,1)),misc!$A$2:$B$5,2,0) -> I | CA41: =VLOOKUP(VALUE(RIGHT(BV41,1)),misc!$A$2:$B$5,2,0) -> D | CC41: =IF(VALUE(BS41)>=170,BX41,"") -> C | CD41: =IF(VALUE(BT41)>=170,BY41,"") -> S | CE41: =IF(VALUE(BU41)>=170,BZ41,"") -> I | CF41: =IF(VALUE(BV41)>=170,CA41,"") -> D | CH41: =IF(VALUE(BS41)<170,BX41,"") | CI41: =IF(VALUE(BT41)<170,BY41,"") | CJ41: =IF(VALUE(BU41)<170,BZ41,"") | CK41: =IF(VALUE(BV41)<170,CA41,"") | CL41: =IF(AND(AC41<17,AD41<17,AE41<17,AF41<17),1,IF(AND(AC41>=17,AD41>=17,AE41>=17,AF41>=17),2,IF(AND(AC41>12,AC41<21,AD41>12,AD41<21,AE41>12,AE41<21,AF41>12,AF41<21),3,4))) -> 2 | CM41: =TRIM(CC41&CD41&CE41&CF41) -> CSID | CP41: =VALUE(AG41&CP$2) -> 161 | CQ41: =VALUE(AH41&CQ$2) -> 182 | CR41: =VALUE(AI41&CR$2) -> 193 | CS41: =VALUE(AJ41&CS$2) -> 194 | CU41: =LARGE($CP41:$CS41,CU$2) -> 194 | CV41: =LARGE($CP41:$CS41,CV$2) -> 193 | CW41: =LARGE($CP41:$CS41,CW$2) -> 182 | CX41: =LARGE($CP41:$CS41,CX$2) -> 161 | CZ41: =VLOOKUP(VALUE(RIGHT(CU41,1)),misc!$A$2:$B$5,2,0) -> C | DA41: =VLOOKUP(VALUE(RIGHT(CV41,1)),misc!$A$2:$B$5,2,0) -> S | DB41: =VLOOKUP(VALUE(RIGHT(CW41,1)),misc!$A$2:$B$5,2,0) -> I | DC41: =VLOOKUP(VALUE(RIGHT(CX41,1)),misc!$A$2:$B$5,2,0) -> D | DE41: =IF(VALUE(CU41)>=170,CZ41,"") -> C | DF41: =IF(VALUE(CV41)>=170,DA41,"") -> S | DG41: =IF(VALUE(CW41)>=170,DB41,"") -> I | DH41: =IF(VALUE(CX41)>=170,DC41,"") | DJ41: =IF(VALUE(CU41)<170,CZ41,"") | DK41: =IF(VALUE(CV41)<170,DA41,"") | DL41: =IF(VALUE(CW41)<170,DB41,"") | DM41: =IF(VALUE(CX41)<170,DC41,"") -> D | DN41: =IF(AND(AG41<17,AH41<17,AI41<17,AJ41<17),1,IF(AND(AG41>=17,AH41>=17,AI41>=17,AJ41>=17),2,IF(AND(AG41>12,AG41<21,AH41>12,AH41<21,AI41>12,AI41<21,AJ41>12,AJ41<21),3,4))) -> 3 | DO41: =TRIM(DE41&DF41&DG41&DH41) -> CSI | DP41: =BJ41&CL41&DN41 -> 123 | DQ41: =A41&G41&H41&I41&J41&L41&M41&N41&O41 | DR41: =VLOOKUP(G41,tableD1,3,0) -> 1 | DS41: =VLOOKUP(H41,tableI1,3,0) -> 1 | DT41: =VLOOKUP(I41,table1S,3,0) -> 2 | DU41: =VLOOKUP(J41,table1C,3,0) -> 1 | DV41: =VLOOKUP(L41,table2D,3,0) -> 8 | DW41: =VLOOKUP(M41,table2I,3,0) -> 8 | DX41: =VLOOKUP(N41,table2S,3,0) -> 8 | DY41: =VLOOKUP(O41,table2C,3,0) -> 8 | DZ41: =VLOOKUP(Q41,table3D,3,0) -> 4 | EA41: =VLOOKUP(R41,table3I,3,0) -> 5 | EB41: =VLOOKUP(S41,table3S,3,0) -> 5 | EC41: =VLOOKUP(T41,table3C,3,0) -> 5 | ED41: {=VLOOKUP(INDEX(JD,data!$AA$1),key!$J$3:$L$27,3,0)} -> 6 | EE41: {=VLOOKUP(INDEX(JI,data!$AA$1),key!$J$3:$L$27,3,0)} -> 4 | EF41: {=VLOOKUP(INDEX(JS,data!$AA$1),key!$J$3:$L$27,3,0)} -> 4 | EG41: {=VLOOKUP(INDEX(JC,data!$AA$1),key!$J$3:$L$27,3,0)} -> 7 | EH41: =VLOOKUP(DR41,tabel_jpm,ED41+1,0) -> 8 | EI41: =VLOOKUP(DS41,tabel_jpm,EE41+1,0) -> 16 | EJ41: =VLOOKUP(DT41,tabel_jpm,EF41+1,0) -> 20 | EK41: =VLOOKUP(DU41,tabel_jpm,EG41+1,0) -> 4 | EL41: =IF(B41="Pria",VLOOKUP(AVERAGE(EH41:EK41),agreement_p,4),VLOOKUP(AVERAGE(EH41:EK41),agreement_w,4)) -> 32 | EM41: =IF(DP41<>"444","N/A",EL41) -> N/A | EN41: =VLOOKUP(DV41,tabel_jpm,ED41+1,0) -> 20 | EO41: =VLOOKUP(DW41,tabel_jpm,EE41+1,0) -> 12 | EP41: =VLOOKUP(DX41,tabel_jpm,EF41+1,0) -> 12 | EQ41: =VLOOKUP(DY41,tabel_jpm,EG41+1,0) -> 24 | ER41: =IF(B41="Pria",VLOOKUP(AVERAGE(EN41:EQ41),agreement_p,4),VLOOKUP(AVERAGE(EN41:EQ41),agreement_w,4)) -> 50 | ES41: =IF(DP41<>"444","N/A",ER41) -> N/A | ET41: =VLOOKUP(DZ41,tabel_jpm,ED41+1,0) -> 20 | EU41: =VLOOKUP(EA41,tabel_jpm,EE41+1,0) -> 24 | EV41: =VLOOKUP(EB41,tabel_jpm,EF41+1,0) -> 24 | EW41: =VLOOKUP(EC41,tabel_jpm,EG41+1,0) -> 20 | EX41: =IF(B41="Pria",VLOOKUP(AVERAGE(ET41:EW41),agreement_p,4),VLOOKUP(AVERAGE(ET41:EW41),agreement_w,4)) -> 68 | EY41: =IF(DP41<>"444","N/A",EX41) -> N/A
A42: =data!A42 | B42: =data!B42 | C42: =data!C42 | D42: =data!D42 | E42: =data!E42 | F42: =data!F42 | G42: =data!G42 | H42: =data!H42 | ... W42: =data!W42 | Y42: =VLOOKUP(G42,tableD1,2,0) -> 4 | Z42: =VLOOKUP(H42,tableI1,2,0) -> 3 | AA42: =VLOOKUP(I42,table1S,2,0) -> 5 | AB42: =VLOOKUP(J42,table1C,2,0) -> 4 | AC42: =VLOOKUP(L42,table2D,2,0) -> 31 | AD42: =VLOOKUP(M42,table2I,2,0) -> 31 | AE42: =VLOOKUP(N42,table2S,2,0) -> 32 | AF42: =VLOOKUP(O42,table2C,2,0) -> 32 | AG42: =VLOOKUP(Q42,table3D,2,0) -> 16 | AH42: =VLOOKUP(R42,table3I,2,0) -> 18 | AI42: =VLOOKUP(S42,table3S,2,0) -> 19 | AJ42: =VLOOKUP(T42,table3C,2,0) -> 19 | AL42: =VALUE(Y42&AL$2) -> 41 | AM42: =VALUE(Z42&AM$2) -> 32 | AN42: =VALUE(AA42&AN$2) -> 53 | AO42: =VALUE(AB42&AO$2) -> 44 | AQ42: =LARGE($AL42:$AO42,AQ$2) -> 53 | AR42: =LARGE($AL42:$AO42,AR$2) -> 44 | AS42: =LARGE($AL42:$AO42,AS$2) -> 41 | AT42: =LARGE($AL42:$AO42,AT$2) -> 32 | AV42: =VLOOKUP(VALUE(RIGHT(AQ42,1)),misc!$A$2:$B$5,2,0) -> S | AW42: =VLOOKUP(VALUE(RIGHT(AR42,1)),misc!$A$2:$B$5,2,0) -> C | AX42: =VLOOKUP(VALUE(RIGHT(AS42,1)),misc!$A$2:$B$5,2,0) -> D | AY42: =VLOOKUP(VALUE(RIGHT(AT42,1)),misc!$A$2:$B$5,2,0) -> I | BA42: =IF(VALUE(AQ42)>=170,AV42,"") | BB42: =IF(VALUE(AR42)>=170,AW42,"") | BC42: =IF(VALUE(AS42)>=170,AX42,"") | BD42: =IF(VALUE(AT42)>=170,AY42,"") | BF42: =IF(VALUE(AQ42)<170,AV42,"") -> S | BG42: =IF(VALUE(AR42)<170,AW42,"") -> C | BH42: =IF(VALUE(AS42)<170,AX42,"") -> D | BI42: =IF(VALUE(AT42)<170,AY42,"") -> I | BJ42: =IF(AND(Y42<17,Z42<17,AA42<17,AB42<17),1,IF(AND(Y42>=17,Z42>=17,AA42>=17,AB42>=17),2,IF(AND(Y42>12,Y42<21,Z42>12,Z42<21,AA42>12,AA42<21,AB42>12,AB42<21),3,4))) -> 1 | BK42: =TRIM(BA42&BB42&BC42&BD42) | BN42: =VALUE(AC42&BN$2) -> 311 | BO42: =VALUE(AD42&BO$2) -> 312 | BP42: =VALUE(AE42&BP$2) -> 323 | BQ42: =VALUE(AF42&BQ$2) -> 324 | BS42: =LARGE($BN42:$BQ42,BS$2) -> 324 | BT42: =LARGE($BN42:$BQ42,BT$2) -> 323 | BU42: =LARGE($BN42:$BQ42,BU$2) -> 312 | BV42: =LARGE($BN42:$BQ42,BV$2) -> 311 | BX42: =VLOOKUP(VALUE(RIGHT(BS42,1)),misc!$A$2:$B$5,2,0) -> C | BY42: =VLOOKUP(VALUE(RIGHT(BT42,1)),misc!$A$2:$B$5,2,0) -> S | BZ42: =VLOOKUP(VALUE(RIGHT(BU42,1)),misc!$A$2:$B$5,2,0) -> I | CA42: =VLOOKUP(VALUE(RIGHT(BV42,1)),misc!$A$2:$B$5,2,0) -> D | CC42: =IF(VALUE(BS42)>=170,BX42,"") -> C | CD42: =IF(VALUE(BT42)>=170,BY42,"") -> S | CE42: =IF(VALUE(BU42)>=170,BZ42,"") -> I | CF42: =IF(VALUE(BV42)>=170,CA42,"") -> D | CH42: =IF(VALUE(BS42)<170,BX42,"") | CI42: =IF(VALUE(BT42)<170,BY42,"") | CJ42: =IF(VALUE(BU42)<170,BZ42,"") | CK42: =IF(VALUE(BV42)<170,CA42,"") | CL42: =IF(AND(AC42<17,AD42<17,AE42<17,AF42<17),1,IF(AND(AC42>=17,AD42>=17,AE42>=17,AF42>=17),2,IF(AND(AC42>12,AC42<21,AD42>12,AD42<21,AE42>12,AE42<21,AF42>12,AF42<21),3,4))) -> 2 | CM42: =TRIM(CC42&CD42&CE42&CF42) -> CSID | CP42: =VALUE(AG42&CP$2) -> 161 | CQ42: =VALUE(AH42&CQ$2) -> 182 | CR42: =VALUE(AI42&CR$2) -> 193 | CS42: =VALUE(AJ42&CS$2) -> 194 | CU42: =LARGE($CP42:$CS42,CU$2) -> 194 | CV42: =LARGE($CP42:$CS42,CV$2) -> 193 | CW42: =LARGE($CP42:$CS42,CW$2) -> 182 | CX42: =LARGE($CP42:$CS42,CX$2) -> 161 | CZ42: =VLOOKUP(VALUE(RIGHT(CU42,1)),misc!$A$2:$B$5,2,0) -> C | DA42: =VLOOKUP(VALUE(RIGHT(CV42,1)),misc!$A$2:$B$5,2,0) -> S | DB42: =VLOOKUP(VALUE(RIGHT(CW42,1)),misc!$A$2:$B$5,2,0) -> I | DC42: =VLOOKUP(VALUE(RIGHT(CX42,1)),misc!$A$2:$B$5,2,0) -> D | DE42: =IF(VALUE(CU42)>=170,CZ42,"") -> C | DF42: =IF(VALUE(CV42)>=170,DA42,"") -> S | DG42: =IF(VALUE(CW42)>=170,DB42,"") -> I | DH42: =IF(VALUE(CX42)>=170,DC42,"") | DJ42: =IF(VALUE(CU42)<170,CZ42,"") | DK42: =IF(VALUE(CV42)<170,DA42,"") | DL42: =IF(VALUE(CW42)<170,DB42,"") | DM42: =IF(VALUE(CX42)<170,DC42,"") -> D | DN42: =IF(AND(AG42<17,AH42<17,AI42<17,AJ42<17),1,IF(AND(AG42>=17,AH42>=17,AI42>=17,AJ42>=17),2,IF(AND(AG42>12,AG42<21,AH42>12,AH42<21,AI42>12,AI42<21,AJ42>12,AJ42<21),3,4))) -> 3 | DO42: =TRIM(DE42&DF42&DG42&DH42) -> CSI | DP42: =BJ42&CL42&DN42 -> 123 | DQ42: =A42&G42&H42&I42&J42&L42&M42&N42&O42 | DR42: =VLOOKUP(G42,tableD1,3,0) -> 1 | DS42: =VLOOKUP(H42,tableI1,3,0) -> 1 | DT42: =VLOOKUP(I42,table1S,3,0) -> 2 | DU42: =VLOOKUP(J42,table1C,3,0) -> 1 | DV42: =VLOOKUP(L42,table2D,3,0) -> 8 | DW42: =VLOOKUP(M42,table2I,3,0) -> 8 | DX42: =VLOOKUP(N42,table2S,3,0) -> 8 | DY42: =VLOOKUP(O42,table2C,3,0) -> 8 | DZ42: =VLOOKUP(Q42,table3D,3,0) -> 4 | EA42: =VLOOKUP(R42,table3I,3,0) -> 5 | EB42: =VLOOKUP(S42,table3S,3,0) -> 5 | EC42: =VLOOKUP(T42,table3C,3,0) -> 5 | ED42: {=VLOOKUP(INDEX(JD,data!$AA$1),key!$J$3:$L$27,3,0)} -> 6 | EE42: {=VLOOKUP(INDEX(JI,data!$AA$1),key!$J$3:$L$27,3,0)} -> 4 | EF42: {=VLOOKUP(INDEX(JS,data!$AA$1),key!$J$3:$L$27,3,0)} -> 4 | EG42: {=VLOOKUP(INDEX(JC,data!$AA$1),key!$J$3:$L$27,3,0)} -> 7 | EH42: =VLOOKUP(DR42,tabel_jpm,ED42+1,0) -> 8 | EI42: =VLOOKUP(DS42,tabel_jpm,EE42+1,0) -> 16 | EJ42: =VLOOKUP(DT42,tabel_jpm,EF42+1,0) -> 20 | EK42: =VLOOKUP(DU42,tabel_jpm,EG42+1,0) -> 4 | EL42: =IF(B42="Pria",VLOOKUP(AVERAGE(EH42:EK42),agreement_p,4),VLOOKUP(AVERAGE(EH42:EK42),agreement_w,4)) -> 32 | EM42: =IF(DP42<>"444","N/A",EL42) -> N/A | EN42: =VLOOKUP(DV42,tabel_jpm,ED42+1,0) -> 20 | EO42: =VLOOKUP(DW42,tabel_jpm,EE42+1,0) -> 12 | EP42: =VLOOKUP(DX42,tabel_jpm,EF42+1,0) -> 12 | EQ42: =VLOOKUP(DY42,tabel_jpm,EG42+1,0) -> 24 | ER42: =IF(B42="Pria",VLOOKUP(AVERAGE(EN42:EQ42),agreement_p,4),VLOOKUP(AVERAGE(EN42:EQ42),agreement_w,4)) -> 50 | ES42: =IF(DP42<>"444","N/A",ER42) -> N/A | ET42: =VLOOKUP(DZ42,tabel_jpm,ED42+1,0) -> 20 | EU42: =VLOOKUP(EA42,tabel_jpm,EE42+1,0) -> 24 | EV42: =VLOOKUP(EB42,tabel_jpm,EF42+1,0) -> 24 | EW42: =VLOOKUP(EC42,tabel_jpm,EG42+1,0) -> 20 | EX42: =IF(B42="Pria",VLOOKUP(AVERAGE(ET42:EW42),agreement_p,4),VLOOKUP(AVERAGE(ET42:EW42),agreement_w,4)) -> 68 | EY42: =IF(DP42<>"444","N/A",EX42) -> N/A
A43: =data!A43 | B43: =data!B43 | C43: =data!C43 | D43: =data!D43 | E43: =data!E43 | F43: =data!F43 | G43: =data!G43 | H43: =data!H43 | ... W43: =data!W43 | Y43: =VLOOKUP(G43,tableD1,2,0) -> 4 | Z43: =VLOOKUP(H43,tableI1,2,0) -> 3 | AA43: =VLOOKUP(I43,table1S,2,0) -> 5 | AB43: =VLOOKUP(J43,table1C,2,0) -> 4 | AC43: =VLOOKUP(L43,table2D,2,0) -> 31 | AD43: =VLOOKUP(M43,table2I,2,0) -> 31 | AE43: =VLOOKUP(N43,table2S,2,0) -> 32 | AF43: =VLOOKUP(O43,table2C,2,0) -> 32 | AG43: =VLOOKUP(Q43,table3D,2,0) -> 16 | AH43: =VLOOKUP(R43,table3I,2,0) -> 18 | AI43: =VLOOKUP(S43,table3S,2,0) -> 19 | AJ43: =VLOOKUP(T43,table3C,2,0) -> 19 | AL43: =VALUE(Y43&AL$2) -> 41 | AM43: =VALUE(Z43&AM$2) -> 32 | AN43: =VALUE(AA43&AN$2) -> 53 | AO43: =VALUE(AB43&AO$2) -> 44 | AQ43: =LARGE($AL43:$AO43,AQ$2) -> 53 | AR43: =LARGE($AL43:$AO43,AR$2) -> 44 | AS43: =LARGE($AL43:$AO43,AS$2) -> 41 | AT43: =LARGE($AL43:$AO43,AT$2) -> 32 | AV43: =VLOOKUP(VALUE(RIGHT(AQ43,1)),misc!$A$2:$B$5,2,0) -> S | AW43: =VLOOKUP(VALUE(RIGHT(AR43,1)),misc!$A$2:$B$5,2,0) -> C | AX43: =VLOOKUP(VALUE(RIGHT(AS43,1)),misc!$A$2:$B$5,2,0) -> D | AY43: =VLOOKUP(VALUE(RIGHT(AT43,1)),misc!$A$2:$B$5,2,0) -> I | BA43: =IF(VALUE(AQ43)>=170,AV43,"") | BB43: =IF(VALUE(AR43)>=170,AW43,"") | BC43: =IF(VALUE(AS43)>=170,AX43,"") | BD43: =IF(VALUE(AT43)>=170,AY43,"") | BF43: =IF(VALUE(AQ43)<170,AV43,"") -> S | BG43: =IF(VALUE(AR43)<170,AW43,"") -> C | BH43: =IF(VALUE(AS43)<170,AX43,"") -> D | BI43: =IF(VALUE(AT43)<170,AY43,"") -> I | BJ43: =IF(AND(Y43<17,Z43<17,AA43<17,AB43<17),1,IF(AND(Y43>=17,Z43>=17,AA43>=17,AB43>=17),2,IF(AND(Y43>12,Y43<21,Z43>12,Z43<21,AA43>12,AA43<21,AB43>12,AB43<21),3,4))) -> 1 | BK43: =TRIM(BA43&BB43&BC43&BD43) | BN43: =VALUE(AC43&BN$2) -> 311 | BO43: =VALUE(AD43&BO$2) -> 312 | BP43: =VALUE(AE43&BP$2) -> 323 | BQ43: =VALUE(AF43&BQ$2) -> 324 | BS43: =LARGE($BN43:$BQ43,BS$2) -> 324 | BT43: =LARGE($BN43:$BQ43,BT$2) -> 323 | BU43: =LARGE($BN43:$BQ43,BU$2) -> 312 | BV43: =LARGE($BN43:$BQ43,BV$2) -> 311 | BX43: =VLOOKUP(VALUE(RIGHT(BS43,1)),misc!$A$2:$B$5,2,0) -> C | BY43: =VLOOKUP(VALUE(RIGHT(BT43,1)),misc!$A$2:$B$5,2,0) -> S | BZ43: =VLOOKUP(VALUE(RIGHT(BU43,1)),misc!$A$2:$B$5,2,0) -> I | CA43: =VLOOKUP(VALUE(RIGHT(BV43,1)),misc!$A$2:$B$5,2,0) -> D | CC43: =IF(VALUE(BS43)>=170,BX43,"") -> C | CD43: =IF(VALUE(BT43)>=170,BY43,"") -> S | CE43: =IF(VALUE(BU43)>=170,BZ43,"") -> I | CF43: =IF(VALUE(BV43)>=170,CA43,"") -> D | CH43: =IF(VALUE(BS43)<170,BX43,"") | CI43: =IF(VALUE(BT43)<170,BY43,"") | CJ43: =IF(VALUE(BU43)<170,BZ43,"") | CK43: =IF(VALUE(BV43)<170,CA43,"") | CL43: =IF(AND(AC43<17,AD43<17,AE43<17,AF43<17),1,IF(AND(AC43>=17,AD43>=17,AE43>=17,AF43>=17),2,IF(AND(AC43>12,AC43<21,AD43>12,AD43<21,AE43>12,AE43<21,AF43>12,AF43<21),3,4))) -> 2 | CM43: =TRIM(CC43&CD43&CE43&CF43) -> CSID | CP43: =VALUE(AG43&CP$2) -> 161 | CQ43: =VALUE(AH43&CQ$2) -> 182 | CR43: =VALUE(AI43&CR$2) -> 193 | CS43: =VALUE(AJ43&CS$2) -> 194 | CU43: =LARGE($CP43:$CS43,CU$2) -> 194 | CV43: =LARGE($CP43:$CS43,CV$2) -> 193 | CW43: =LARGE($CP43:$CS43,CW$2) -> 182 | CX43: =LARGE($CP43:$CS43,CX$2) -> 161 | CZ43: =VLOOKUP(VALUE(RIGHT(CU43,1)),misc!$A$2:$B$5,2,0) -> C | DA43: =VLOOKUP(VALUE(RIGHT(CV43,1)),misc!$A$2:$B$5,2,0) -> S | DB43: =VLOOKUP(VALUE(RIGHT(CW43,1)),misc!$A$2:$B$5,2,0) -> I | DC43: =VLOOKUP(VALUE(RIGHT(CX43,1)),misc!$A$2:$B$5,2,0) -> D | DE43: =IF(VALUE(CU43)>=170,CZ43,"") -> C | DF43: =IF(VALUE(CV43)>=170,DA43,"") -> S | DG43: =IF(VALUE(CW43)>=170,DB43,"") -> I | DH43: =IF(VALUE(CX43)>=170,DC43,"") | DJ43: =IF(VALUE(CU43)<170,CZ43,"") | DK43: =IF(VALUE(CV43)<170,DA43,"") | DL43: =IF(VALUE(CW43)<170,DB43,"") | DM43: =IF(VALUE(CX43)<170,DC43,"") -> D | DN43: =IF(AND(AG43<17,AH43<17,AI43<17,AJ43<17),1,IF(AND(AG43>=17,AH43>=17,AI43>=17,AJ43>=17),2,IF(AND(AG43>12,AG43<21,AH43>12,AH43<21,AI43>12,AI43<21,AJ43>12,AJ43<21),3,4))) -> 3 | DO43: =TRIM(DE43&DF43&DG43&DH43) -> CSI | DP43: =BJ43&CL43&DN43 -> 123 | DQ43: =A43&G43&H43&I43&J43&L43&M43&N43&O43 | DR43: =VLOOKUP(G43,tableD1,3,0) -> 1 | DS43: =VLOOKUP(H43,tableI1,3,0) -> 1 | DT43: =VLOOKUP(I43,table1S,3,0) -> 2 | DU43: =VLOOKUP(J43,table1C,3,0) -> 1 | DV43: =VLOOKUP(L43,table2D,3,0) -> 8 | DW43: =VLOOKUP(M43,table2I,3,0) -> 8 | DX43: =VLOOKUP(N43,table2S,3,0) -> 8 | DY43: =VLOOKUP(O43,table2C,3,0) -> 8 | DZ43: =VLOOKUP(Q43,table3D,3,0) -> 4 | EA43: =VLOOKUP(R43,table3I,3,0) -> 5 | EB43: =VLOOKUP(S43,table3S,3,0) -> 5 | EC43: =VLOOKUP(T43,table3C,3,0) -> 5 | ED43: {=VLOOKUP(INDEX(JD,data!$AA$1),key!$J$3:$L$27,3,0)} -> 6 | EE43: {=VLOOKUP(INDEX(JI,data!$AA$1),key!$J$3:$L$27,3,0)} -> 4 | EF43: {=VLOOKUP(INDEX(JS,data!$AA$1),key!$J$3:$L$27,3,0)} -> 4 | EG43: {=VLOOKUP(INDEX(JC,data!$AA$1),key!$J$3:$L$27,3,0)} -> 7 | EH43: =VLOOKUP(DR43,tabel_jpm,ED43+1,0) -> 8 | EI43: =VLOOKUP(DS43,tabel_jpm,EE43+1,0) -> 16 | EJ43: =VLOOKUP(DT43,tabel_jpm,EF43+1,0) -> 20 | EK43: =VLOOKUP(DU43,tabel_jpm,EG43+1,0) -> 4 | EL43: =IF(B43="Pria",VLOOKUP(AVERAGE(EH43:EK43),agreement_p,4),VLOOKUP(AVERAGE(EH43:EK43),agreement_w,4)) -> 32 | EM43: =IF(DP43<>"444","N/A",EL43) -> N/A | EN43: =VLOOKUP(DV43,tabel_jpm,ED43+1,0) -> 20 | EO43: =VLOOKUP(DW43,tabel_jpm,EE43+1,0) -> 12 | EP43: =VLOOKUP(DX43,tabel_jpm,EF43+1,0) -> 12 | EQ43: =VLOOKUP(DY43,tabel_jpm,EG43+1,0) -> 24 | ER43: =IF(B43="Pria",VLOOKUP(AVERAGE(EN43:EQ43),agreement_p,4),VLOOKUP(AVERAGE(EN43:EQ43),agreement_w,4)) -> 50 | ES43: =IF(DP43<>"444","N/A",ER43) -> N/A | ET43: =VLOOKUP(DZ43,tabel_jpm,ED43+1,0) -> 20 | EU43: =VLOOKUP(EA43,tabel_jpm,EE43+1,0) -> 24 | EV43: =VLOOKUP(EB43,tabel_jpm,EF43+1,0) -> 24 | EW43: =VLOOKUP(EC43,tabel_jpm,EG43+1,0) -> 20 | EX43: =IF(B43="Pria",VLOOKUP(AVERAGE(ET43:EW43),agreement_p,4),VLOOKUP(AVERAGE(ET43:EW43),agreement_w,4)) -> 68 | EY43: =IF(DP43<>"444","N/A",EX43) -> N/A
A44: =data!A44 | B44: =data!B44 | C44: =data!C44 | D44: =data!D44 | E44: =data!E44 | F44: =data!F44 | G44: =data!G44 | H44: =data!H44 | ... W44: =data!W44 | Y44: =VLOOKUP(G44,tableD1,2,0) -> 4 | Z44: =VLOOKUP(H44,tableI1,2,0) -> 3 | AA44: =VLOOKUP(I44,table1S,2,0) -> 5 | AB44: =VLOOKUP(J44,table1C,2,0) -> 4 | AC44: =VLOOKUP(L44,table2D,2,0) -> 31 | AD44: =VLOOKUP(M44,table2I,2,0) -> 31 | AE44: =VLOOKUP(N44,table2S,2,0) -> 32 | AF44: =VLOOKUP(O44,table2C,2,0) -> 32 | AG44: =VLOOKUP(Q44,table3D,2,0) -> 16 | AH44: =VLOOKUP(R44,table3I,2,0) -> 18 | AI44: =VLOOKUP(S44,table3S,2,0) -> 19 | AJ44: =VLOOKUP(T44,table3C,2,0) -> 19 | AL44: =VALUE(Y44&AL$2) -> 41 | AM44: =VALUE(Z44&AM$2) -> 32 | AN44: =VALUE(AA44&AN$2) -> 53 | AO44: =VALUE(AB44&AO$2) -> 44 | AQ44: =LARGE($AL44:$AO44,AQ$2) -> 53 | AR44: =LARGE($AL44:$AO44,AR$2) -> 44 | AS44: =LARGE($AL44:$AO44,AS$2) -> 41 | AT44: =LARGE($AL44:$AO44,AT$2) -> 32 | AV44: =VLOOKUP(VALUE(RIGHT(AQ44,1)),misc!$A$2:$B$5,2,0) -> S | AW44: =VLOOKUP(VALUE(RIGHT(AR44,1)),misc!$A$2:$B$5,2,0) -> C | AX44: =VLOOKUP(VALUE(RIGHT(AS44,1)),misc!$A$2:$B$5,2,0) -> D | AY44: =VLOOKUP(VALUE(RIGHT(AT44,1)),misc!$A$2:$B$5,2,0) -> I | BA44: =IF(VALUE(AQ44)>=170,AV44,"") | BB44: =IF(VALUE(AR44)>=170,AW44,"") | BC44: =IF(VALUE(AS44)>=170,AX44,"") | BD44: =IF(VALUE(AT44)>=170,AY44,"") | BF44: =IF(VALUE(AQ44)<170,AV44,"") -> S | BG44: =IF(VALUE(AR44)<170,AW44,"") -> C | BH44: =IF(VALUE(AS44)<170,AX44,"") -> D | BI44: =IF(VALUE(AT44)<170,AY44,"") -> I | BJ44: =IF(AND(Y44<17,Z44<17,AA44<17,AB44<17),1,IF(AND(Y44>=17,Z44>=17,AA44>=17,AB44>=17),2,IF(AND(Y44>12,Y44<21,Z44>12,Z44<21,AA44>12,AA44<21,AB44>12,AB44<21),3,4))) -> 1 | BK44: =TRIM(BA44&BB44&BC44&BD44) | BN44: =VALUE(AC44&BN$2) -> 311 | BO44: =VALUE(AD44&BO$2) -> 312 | BP44: =VALUE(AE44&BP$2) -> 323 | BQ44: =VALUE(AF44&BQ$2) -> 324 | BS44: =LARGE($BN44:$BQ44,BS$2) -> 324 | BT44: =LARGE($BN44:$BQ44,BT$2) -> 323 | BU44: =LARGE($BN44:$BQ44,BU$2) -> 312 | BV44: =LARGE($BN44:$BQ44,BV$2) -> 311 | BX44: =VLOOKUP(VALUE(RIGHT(BS44,1)),misc!$A$2:$B$5,2,0) -> C | BY44: =VLOOKUP(VALUE(RIGHT(BT44,1)),misc!$A$2:$B$5,2,0) -> S | BZ44: =VLOOKUP(VALUE(RIGHT(BU44,1)),misc!$A$2:$B$5,2,0) -> I | CA44: =VLOOKUP(VALUE(RIGHT(BV44,1)),misc!$A$2:$B$5,2,0) -> D | CC44: =IF(VALUE(BS44)>=170,BX44,"") -> C | CD44: =IF(VALUE(BT44)>=170,BY44,"") -> S | CE44: =IF(VALUE(BU44)>=170,BZ44,"") -> I | CF44: =IF(VALUE(BV44)>=170,CA44,"") -> D | CH44: =IF(VALUE(BS44)<170,BX44,"") | CI44: =IF(VALUE(BT44)<170,BY44,"") | CJ44: =IF(VALUE(BU44)<170,BZ44,"") | CK44: =IF(VALUE(BV44)<170,CA44,"") | CL44: =IF(AND(AC44<17,AD44<17,AE44<17,AF44<17),1,IF(AND(AC44>=17,AD44>=17,AE44>=17,AF44>=17),2,IF(AND(AC44>12,AC44<21,AD44>12,AD44<21,AE44>12,AE44<21,AF44>12,AF44<21),3,4))) -> 2 | CM44: =TRIM(CC44&CD44&CE44&CF44) -> CSID | CP44: =VALUE(AG44&CP$2) -> 161 | CQ44: =VALUE(AH44&CQ$2) -> 182 | CR44: =VALUE(AI44&CR$2) -> 193 | CS44: =VALUE(AJ44&CS$2) -> 194 | CU44: =LARGE($CP44:$CS44,CU$2) -> 194 | CV44: =LARGE($CP44:$CS44,CV$2) -> 193 | CW44: =LARGE($CP44:$CS44,CW$2) -> 182 | CX44: =LARGE($CP44:$CS44,CX$2) -> 161 | CZ44: =VLOOKUP(VALUE(RIGHT(CU44,1)),misc!$A$2:$B$5,2,0) -> C | DA44: =VLOOKUP(VALUE(RIGHT(CV44,1)),misc!$A$2:$B$5,2,0) -> S | DB44: =VLOOKUP(VALUE(RIGHT(CW44,1)),misc!$A$2:$B$5,2,0) -> I | DC44: =VLOOKUP(VALUE(RIGHT(CX44,1)),misc!$A$2:$B$5,2,0) -> D | DE44: =IF(VALUE(CU44)>=170,CZ44,"") -> C | DF44: =IF(VALUE(CV44)>=170,DA44,"") -> S | DG44: =IF(VALUE(CW44)>=170,DB44,"") -> I | DH44: =IF(VALUE(CX44)>=170,DC44,"") | DJ44: =IF(VALUE(CU44)<170,CZ44,"") | DK44: =IF(VALUE(CV44)<170,DA44,"") | DL44: =IF(VALUE(CW44)<170,DB44,"") | DM44: =IF(VALUE(CX44)<170,DC44,"") -> D | DN44: =IF(AND(AG44<17,AH44<17,AI44<17,AJ44<17),1,IF(AND(AG44>=17,AH44>=17,AI44>=17,AJ44>=17),2,IF(AND(AG44>12,AG44<21,AH44>12,AH44<21,AI44>12,AI44<21,AJ44>12,AJ44<21),3,4))) -> 3 | DO44: =TRIM(DE44&DF44&DG44&DH44) -> CSI | DP44: =BJ44&CL44&DN44 -> 123 | DQ44: =A44&G44&H44&I44&J44&L44&M44&N44&O44 | DR44: =VLOOKUP(G44,tableD1,3,0) -> 1 | DS44: =VLOOKUP(H44,tableI1,3,0) -> 1 | DT44: =VLOOKUP(I44,table1S,3,0) -> 2 | DU44: =VLOOKUP(J44,table1C,3,0) -> 1 | DV44: =VLOOKUP(L44,table2D,3,0) -> 8 | DW44: =VLOOKUP(M44,table2I,3,0) -> 8 | DX44: =VLOOKUP(N44,table2S,3,0) -> 8 | DY44: =VLOOKUP(O44,table2C,3,0) -> 8 | DZ44: =VLOOKUP(Q44,table3D,3,0) -> 4 | EA44: =VLOOKUP(R44,table3I,3,0) -> 5 | EB44: =VLOOKUP(S44,table3S,3,0) -> 5 | EC44: =VLOOKUP(T44,table3C,3,0) -> 5 | ED44: {=VLOOKUP(INDEX(JD,data!$AA$1),key!$J$3:$L$27,3,0)} -> 6 | EE44: {=VLOOKUP(INDEX(JI,data!$AA$1),key!$J$3:$L$27,3,0)} -> 4 | EF44: {=VLOOKUP(INDEX(JS,data!$AA$1),key!$J$3:$L$27,3,0)} -> 4 | EG44: {=VLOOKUP(INDEX(JC,data!$AA$1),key!$J$3:$L$27,3,0)} -> 7 | EH44: =VLOOKUP(DR44,tabel_jpm,ED44+1,0) -> 8 | EI44: =VLOOKUP(DS44,tabel_jpm,EE44+1,0) -> 16 | EJ44: =VLOOKUP(DT44,tabel_jpm,EF44+1,0) -> 20 | EK44: =VLOOKUP(DU44,tabel_jpm,EG44+1,0) -> 4 | EL44: =IF(B44="Pria",VLOOKUP(AVERAGE(EH44:EK44),agreement_p,4),VLOOKUP(AVERAGE(EH44:EK44),agreement_w,4)) -> 32 | EM44: =IF(DP44<>"444","N/A",EL44) -> N/A | EN44: =VLOOKUP(DV44,tabel_jpm,ED44+1,0) -> 20 | EO44: =VLOOKUP(DW44,tabel_jpm,EE44+1,0) -> 12 | EP44: =VLOOKUP(DX44,tabel_jpm,EF44+1,0) -> 12 | EQ44: =VLOOKUP(DY44,tabel_jpm,EG44+1,0) -> 24 | ER44: =IF(B44="Pria",VLOOKUP(AVERAGE(EN44:EQ44),agreement_p,4),VLOOKUP(AVERAGE(EN44:EQ44),agreement_w,4)) -> 50 | ES44: =IF(DP44<>"444","N/A",ER44) -> N/A | ET44: =VLOOKUP(DZ44,tabel_jpm,ED44+1,0) -> 20 | EU44: =VLOOKUP(EA44,tabel_jpm,EE44+1,0) -> 24 | EV44: =VLOOKUP(EB44,tabel_jpm,EF44+1,0) -> 24 | EW44: =VLOOKUP(EC44,tabel_jpm,EG44+1,0) -> 20 | EX44: =IF(B44="Pria",VLOOKUP(AVERAGE(ET44:EW44),agreement_p,4),VLOOKUP(AVERAGE(ET44:EW44),agreement_w,4)) -> 68 | EY44: =IF(DP44<>"444","N/A",EX44) -> N/A
A45: =data!A45 | B45: =data!B45 | C45: =data!C45 | D45: =data!D45 | E45: =data!E45 | F45: =data!F45 -> profiling | G45: =data!G45 | H45: =data!H45 | ... W45: =data!W45 -> 0 | Y45: =VLOOKUP(G45,tableD1,2,0) -> 4 | Z45: =VLOOKUP(H45,tableI1,2,0) -> 3 | AA45: =VLOOKUP(I45,table1S,2,0) -> 5 | AB45: =VLOOKUP(J45,table1C,2,0) -> 4 | AC45: =VLOOKUP(L45,table2D,2,0) -> 31 | AD45: =VLOOKUP(M45,table2I,2,0) -> 31 | AE45: =VLOOKUP(N45,table2S,2,0) -> 32 | AF45: =VLOOKUP(O45,table2C,2,0) -> 32 | AG45: =VLOOKUP(Q45,table3D,2,0) -> 16 | AH45: =VLOOKUP(R45,table3I,2,0) -> 18 | AI45: =VLOOKUP(S45,table3S,2,0) -> 19 | AJ45: =VLOOKUP(T45,table3C,2,0) -> 19 | AL45: =VALUE(Y45&AL$2) -> 41 | AM45: =VALUE(Z45&AM$2) -> 32 | AN45: =VALUE(AA45&AN$2) -> 53 | AO45: =VALUE(AB45&AO$2) -> 44 | AQ45: =LARGE($AL45:$AO45,AQ$2) -> 53 | AR45: =LARGE($AL45:$AO45,AR$2) -> 44 | AS45: =LARGE($AL45:$AO45,AS$2) -> 41 | AT45: =LARGE($AL45:$AO45,AT$2) -> 32 | AV45: =VLOOKUP(VALUE(RIGHT(AQ45,1)),misc!$A$2:$B$5,2,0) -> S | AW45: =VLOOKUP(VALUE(RIGHT(AR45,1)),misc!$A$2:$B$5,2,0) -> C | AX45: =VLOOKUP(VALUE(RIGHT(AS45,1)),misc!$A$2:$B$5,2,0) -> D | AY45: =VLOOKUP(VALUE(RIGHT(AT45,1)),misc!$A$2:$B$5,2,0) -> I | BA45: =IF(VALUE(AQ45)>=170,AV45,"") | BB45: =IF(VALUE(AR45)>=170,AW45,"") | BC45: =IF(VALUE(AS45)>=170,AX45,"") | BD45: =IF(VALUE(AT45)>=170,AY45,"") | BF45: =IF(VALUE(AQ45)<170,AV45,"") -> S | BG45: =IF(VALUE(AR45)<170,AW45,"") -> C | BH45: =IF(VALUE(AS45)<170,AX45,"") -> D | BI45: =IF(VALUE(AT45)<170,AY45,"") -> I | BJ45: =IF(AND(Y45<17,Z45<17,AA45<17,AB45<17),1,IF(AND(Y45>=17,Z45>=17,AA45>=17,AB45>=17),2,IF(AND(Y45>12,Y45<21,Z45>12,Z45<21,AA45>12,AA45<21,AB45>12,AB45<21),3,4))) -> 1 | BK45: =TRIM(BA45&BB45&BC45&BD45) | BN45: =VALUE(AC45&BN$2) -> 311 | BO45: =VALUE(AD45&BO$2) -> 312 | BP45: =VALUE(AE45&BP$2) -> 323 | BQ45: =VALUE(AF45&BQ$2) -> 324 | BS45: =LARGE($BN45:$BQ45,BS$2) -> 324 | BT45: =LARGE($BN45:$BQ45,BT$2) -> 323 | BU45: =LARGE($BN45:$BQ45,BU$2) -> 312 | BV45: =LARGE($BN45:$BQ45,BV$2) -> 311 | BX45: =VLOOKUP(VALUE(RIGHT(BS45,1)),misc!$A$2:$B$5,2,0) -> C | BY45: =VLOOKUP(VALUE(RIGHT(BT45,1)),misc!$A$2:$B$5,2,0) -> S | BZ45: =VLOOKUP(VALUE(RIGHT(BU45,1)),misc!$A$2:$B$5,2,0) -> I | CA45: =VLOOKUP(VALUE(RIGHT(BV45,1)),misc!$A$2:$B$5,2,0) -> D | CC45: =IF(VALUE(BS45)>=170,BX45,"") -> C | CD45: =IF(VALUE(BT45)>=170,BY45,"") -> S | CE45: =IF(VALUE(BU45)>=170,BZ45,"") -> I | CF45: =IF(VALUE(BV45)>=170,CA45,"") -> D | CH45: =IF(VALUE(BS45)<170,BX45,"") | CI45: =IF(VALUE(BT45)<170,BY45,"") | CJ45: =IF(VALUE(BU45)<170,BZ45,"") | CK45: =IF(VALUE(BV45)<170,CA45,"") | CL45: =IF(AND(AC45<17,AD45<17,AE45<17,AF45<17),1,IF(AND(AC45>=17,AD45>=17,AE45>=17,AF45>=17),2,IF(AND(AC45>12,AC45<21,AD45>12,AD45<21,AE45>12,AE45<21,AF45>12,AF45<21),3,4))) -> 2 | CM45: =TRIM(CC45&CD45&CE45&CF45) -> CSID | CP45: =VALUE(AG45&CP$2) -> 161 | CQ45: =VALUE(AH45&CQ$2) -> 182 | CR45: =VALUE(AI45&CR$2) -> 193 | CS45: =VALUE(AJ45&CS$2) -> 194 | CU45: =LARGE($CP45:$CS45,CU$2) -> 194 | CV45: =LARGE($CP45:$CS45,CV$2) -> 193 | CW45: =LARGE($CP45:$CS45,CW$2) -> 182 | CX45: =LARGE($CP45:$CS45,CX$2) -> 161 | CZ45: =VLOOKUP(VALUE(RIGHT(CU45,1)),misc!$A$2:$B$5,2,0) -> C | DA45: =VLOOKUP(VALUE(RIGHT(CV45,1)),misc!$A$2:$B$5,2,0) -> S | DB45: =VLOOKUP(VALUE(RIGHT(CW45,1)),misc!$A$2:$B$5,2,0) -> I | DC45: =VLOOKUP(VALUE(RIGHT(CX45,1)),misc!$A$2:$B$5,2,0) -> D | DE45: =IF(VALUE(CU45)>=170,CZ45,"") -> C | DF45: =IF(VALUE(CV45)>=170,DA45,"") -> S | DG45: =IF(VALUE(CW45)>=170,DB45,"") -> I | DH45: =IF(VALUE(CX45)>=170,DC45,"") | DJ45: =IF(VALUE(CU45)<170,CZ45,"") | DK45: =IF(VALUE(CV45)<170,DA45,"") | DL45: =IF(VALUE(CW45)<170,DB45,"") | DM45: =IF(VALUE(CX45)<170,DC45,"") -> D | DN45: =IF(AND(AG45<17,AH45<17,AI45<17,AJ45<17),1,IF(AND(AG45>=17,AH45>=17,AI45>=17,AJ45>=17),2,IF(AND(AG45>12,AG45<21,AH45>12,AH45<21,AI45>12,AI45<21,AJ45>12,AJ45<21),3,4))) -> 3 | DO45: =TRIM(DE45&DF45&DG45&DH45) -> CSI | DP45: =BJ45&CL45&DN45 -> 123 | DQ45: =A45&G45&H45&I45&J45&L45&M45&N45&O45 | DR45: =VLOOKUP(G45,tableD1,3,0) -> 1 | DS45: =VLOOKUP(H45,tableI1,3,0) -> 1 | DT45: =VLOOKUP(I45,table1S,3,0) -> 2 | DU45: =VLOOKUP(J45,table1C,3,0) -> 1 | DV45: =VLOOKUP(L45,table2D,3,0) -> 8 | DW45: =VLOOKUP(M45,table2I,3,0) -> 8 | DX45: =VLOOKUP(N45,table2S,3,0) -> 8 | DY45: =VLOOKUP(O45,table2C,3,0) -> 8 | DZ45: =VLOOKUP(Q45,table3D,3,0) -> 4 | EA45: =VLOOKUP(R45,table3I,3,0) -> 5 | EB45: =VLOOKUP(S45,table3S,3,0) -> 5 | EC45: =VLOOKUP(T45,table3C,3,0) -> 5 | ED45: {=VLOOKUP(INDEX(JD,data!$AA$1),key!$J$3:$L$27,3,0)} -> 6 | EE45: {=VLOOKUP(INDEX(JI,data!$AA$1),key!$J$3:$L$27,3,0)} -> 4 | EF45: {=VLOOKUP(INDEX(JS,data!$AA$1),key!$J$3:$L$27,3,0)} -> 4 | EG45: {=VLOOKUP(INDEX(JC,data!$AA$1),key!$J$3:$L$27,3,0)} -> 7 | EH45: =VLOOKUP(DR45,tabel_jpm,ED45+1,0) -> 8 | EI45: =VLOOKUP(DS45,tabel_jpm,EE45+1,0) -> 16 | EJ45: =VLOOKUP(DT45,tabel_jpm,EF45+1,0) -> 20 | EK45: =VLOOKUP(DU45,tabel_jpm,EG45+1,0) -> 4 | EL45: =IF(B45="Pria",VLOOKUP(AVERAGE(EH45:EK45),agreement_p,4),VLOOKUP(AVERAGE(EH45:EK45),agreement_w,4)) -> 32 | EM45: =IF(DP45<>"444","N/A",EL45) -> N/A | EN45: =VLOOKUP(DV45,tabel_jpm,ED45+1,0) -> 20 | EO45: =VLOOKUP(DW45,tabel_jpm,EE45+1,0) -> 12 | EP45: =VLOOKUP(DX45,tabel_jpm,EF45+1,0) -> 12 | EQ45: =VLOOKUP(DY45,tabel_jpm,EG45+1,0) -> 24 | ER45: =IF(B45="Pria",VLOOKUP(AVERAGE(EN45:EQ45),agreement_p,4),VLOOKUP(AVERAGE(EN45:EQ45),agreement_w,4)) -> 50 | ES45: =IF(DP45<>"444","N/A",ER45) -> N/A | ET45: =VLOOKUP(DZ45,tabel_jpm,ED45+1,0) -> 20 | EU45: =VLOOKUP(EA45,tabel_jpm,EE45+1,0) -> 24 | EV45: =VLOOKUP(EB45,tabel_jpm,EF45+1,0) -> 24 | EW45: =VLOOKUP(EC45,tabel_jpm,EG45+1,0) -> 20 | EX45: =IF(B45="Pria",VLOOKUP(AVERAGE(ET45:EW45),agreement_p,4),VLOOKUP(AVERAGE(ET45:EW45),agreement_w,4)) -> 68 | EY45: =IF(DP45<>"444","N/A",EX45) -> N/A
A46: =data!A46 | B46: =data!B46 | C46: =data!C46 | D46: =data!D46 | E46: =data!E46 | F46: =data!F46 -> profiling | G46: =data!G46 | H46: =data!H46 | ... W46: =data!W46 -> 0 | Y46: =VLOOKUP(G46,tableD1,2,0) -> 4 | Z46: =VLOOKUP(H46,tableI1,2,0) -> 3 | AA46: =VLOOKUP(I46,table1S,2,0) -> 5 | AB46: =VLOOKUP(J46,table1C,2,0) -> 4 | AC46: =VLOOKUP(L46,table2D,2,0) -> 31 | AD46: =VLOOKUP(M46,table2I,2,0) -> 31 | AE46: =VLOOKUP(N46,table2S,2,0) -> 32 | AF46: =VLOOKUP(O46,table2C,2,0) -> 32 | AG46: =VLOOKUP(Q46,table3D,2,0) -> 16 | AH46: =VLOOKUP(R46,table3I,2,0) -> 18 | AI46: =VLOOKUP(S46,table3S,2,0) -> 19 | AJ46: =VLOOKUP(T46,table3C,2,0) -> 19 | AL46: =VALUE(Y46&AL$2) -> 41 | AM46: =VALUE(Z46&AM$2) -> 32 | AN46: =VALUE(AA46&AN$2) -> 53 | AO46: =VALUE(AB46&AO$2) -> 44 | AQ46: =LARGE($AL46:$AO46,AQ$2) -> 53 | AR46: =LARGE($AL46:$AO46,AR$2) -> 44 | AS46: =LARGE($AL46:$AO46,AS$2) -> 41 | AT46: =LARGE($AL46:$AO46,AT$2) -> 32 | AV46: =VLOOKUP(VALUE(RIGHT(AQ46,1)),misc!$A$2:$B$5,2,0) -> S | AW46: =VLOOKUP(VALUE(RIGHT(AR46,1)),misc!$A$2:$B$5,2,0) -> C | AX46: =VLOOKUP(VALUE(RIGHT(AS46,1)),misc!$A$2:$B$5,2,0) -> D | AY46: =VLOOKUP(VALUE(RIGHT(AT46,1)),misc!$A$2:$B$5,2,0) -> I | BA46: =IF(VALUE(AQ46)>=170,AV46,"") | BB46: =IF(VALUE(AR46)>=170,AW46,"") | BC46: =IF(VALUE(AS46)>=170,AX46,"") | BD46: =IF(VALUE(AT46)>=170,AY46,"") | BF46: =IF(VALUE(AQ46)<170,AV46,"") -> S | BG46: =IF(VALUE(AR46)<170,AW46,"") -> C | BH46: =IF(VALUE(AS46)<170,AX46,"") -> D | BI46: =IF(VALUE(AT46)<170,AY46,"") -> I | BJ46: =IF(AND(Y46<17,Z46<17,AA46<17,AB46<17),1,IF(AND(Y46>=17,Z46>=17,AA46>=17,AB46>=17),2,IF(AND(Y46>12,Y46<21,Z46>12,Z46<21,AA46>12,AA46<21,AB46>12,AB46<21),3,4))) -> 1 | BK46: =TRIM(BA46&BB46&BC46&BD46) | BN46: =VALUE(AC46&BN$2) -> 311 | BO46: =VALUE(AD46&BO$2) -> 312 | BP46: =VALUE(AE46&BP$2) -> 323 | BQ46: =VALUE(AF46&BQ$2) -> 324 | BS46: =LARGE($BN46:$BQ46,BS$2) -> 324 | BT46: =LARGE($BN46:$BQ46,BT$2) -> 323 | BU46: =LARGE($BN46:$BQ46,BU$2) -> 312 | BV46: =LARGE($BN46:$BQ46,BV$2) -> 311 | BX46: =VLOOKUP(VALUE(RIGHT(BS46,1)),misc!$A$2:$B$5,2,0) -> C | BY46: =VLOOKUP(VALUE(RIGHT(BT46,1)),misc!$A$2:$B$5,2,0) -> S | BZ46: =VLOOKUP(VALUE(RIGHT(BU46,1)),misc!$A$2:$B$5,2,0) -> I | CA46: =VLOOKUP(VALUE(RIGHT(BV46,1)),misc!$A$2:$B$5,2,0) -> D | CC46: =IF(VALUE(BS46)>=170,BX46,"") -> C | CD46: =IF(VALUE(BT46)>=170,BY46,"") -> S | CE46: =IF(VALUE(BU46)>=170,BZ46,"") -> I | CF46: =IF(VALUE(BV46)>=170,CA46,"") -> D | CH46: =IF(VALUE(BS46)<170,BX46,"") | CI46: =IF(VALUE(BT46)<170,BY46,"") | CJ46: =IF(VALUE(BU46)<170,BZ46,"") | CK46: =IF(VALUE(BV46)<170,CA46,"") | CL46: =IF(AND(AC46<17,AD46<17,AE46<17,AF46<17),1,IF(AND(AC46>=17,AD46>=17,AE46>=17,AF46>=17),2,IF(AND(AC46>12,AC46<21,AD46>12,AD46<21,AE46>12,AE46<21,AF46>12,AF46<21),3,4))) -> 2 | CM46: =TRIM(CC46&CD46&CE46&CF46) -> CSID | CP46: =VALUE(AG46&CP$2) -> 161 | CQ46: =VALUE(AH46&CQ$2) -> 182 | CR46: =VALUE(AI46&CR$2) -> 193 | CS46: =VALUE(AJ46&CS$2) -> 194 | CU46: =LARGE($CP46:$CS46,CU$2) -> 194 | CV46: =LARGE($CP46:$CS46,CV$2) -> 193 | CW46: =LARGE($CP46:$CS46,CW$2) -> 182 | CX46: =LARGE($CP46:$CS46,CX$2) -> 161 | CZ46: =VLOOKUP(VALUE(RIGHT(CU46,1)),misc!$A$2:$B$5,2,0) -> C | DA46: =VLOOKUP(VALUE(RIGHT(CV46,1)),misc!$A$2:$B$5,2,0) -> S | DB46: =VLOOKUP(VALUE(RIGHT(CW46,1)),misc!$A$2:$B$5,2,0) -> I | DC46: =VLOOKUP(VALUE(RIGHT(CX46,1)),misc!$A$2:$B$5,2,0) -> D | DE46: =IF(VALUE(CU46)>=170,CZ46,"") -> C | DF46: =IF(VALUE(CV46)>=170,DA46,"") -> S | DG46: =IF(VALUE(CW46)>=170,DB46,"") -> I | DH46: =IF(VALUE(CX46)>=170,DC46,"") | DJ46: =IF(VALUE(CU46)<170,CZ46,"") | DK46: =IF(VALUE(CV46)<170,DA46,"") | DL46: =IF(VALUE(CW46)<170,DB46,"") | DM46: =IF(VALUE(CX46)<170,DC46,"") -> D | DN46: =IF(AND(AG46<17,AH46<17,AI46<17,AJ46<17),1,IF(AND(AG46>=17,AH46>=17,AI46>=17,AJ46>=17),2,IF(AND(AG46>12,AG46<21,AH46>12,AH46<21,AI46>12,AI46<21,AJ46>12,AJ46<21),3,4))) -> 3 | DO46: =TRIM(DE46&DF46&DG46&DH46) -> CSI | DP46: =BJ46&CL46&DN46 -> 123 | DQ46: =A46&G46&H46&I46&J46&L46&M46&N46&O46 | DR46: =VLOOKUP(G46,tableD1,3,0) -> 1 | DS46: =VLOOKUP(H46,tableI1,3,0) -> 1 | DT46: =VLOOKUP(I46,table1S,3,0) -> 2 | DU46: =VLOOKUP(J46,table1C,3,0) -> 1 | DV46: =VLOOKUP(L46,table2D,3,0) -> 8 | DW46: =VLOOKUP(M46,table2I,3,0) -> 8 | DX46: =VLOOKUP(N46,table2S,3,0) -> 8 | DY46: =VLOOKUP(O46,table2C,3,0) -> 8 | DZ46: =VLOOKUP(Q46,table3D,3,0) -> 4 | EA46: =VLOOKUP(R46,table3I,3,0) -> 5 | EB46: =VLOOKUP(S46,table3S,3,0) -> 5 | EC46: =VLOOKUP(T46,table3C,3,0) -> 5 | ED46: {=VLOOKUP(INDEX(JD,data!$AA$1),key!$J$3:$L$27,3,0)} -> 6 | EE46: {=VLOOKUP(INDEX(JI,data!$AA$1),key!$J$3:$L$27,3,0)} -> 4 | EF46: {=VLOOKUP(INDEX(JS,data!$AA$1),key!$J$3:$L$27,3,0)} -> 4 | EG46: {=VLOOKUP(INDEX(JC,data!$AA$1),key!$J$3:$L$27,3,0)} -> 7 | EH46: =VLOOKUP(DR46,tabel_jpm,ED46+1,0) -> 8 | EI46: =VLOOKUP(DS46,tabel_jpm,EE46+1,0) -> 16 | EJ46: =VLOOKUP(DT46,tabel_jpm,EF46+1,0) -> 20 | EK46: =VLOOKUP(DU46,tabel_jpm,EG46+1,0) -> 4 | EL46: =IF(B46="Pria",VLOOKUP(AVERAGE(EH46:EK46),agreement_p,4),VLOOKUP(AVERAGE(EH46:EK46),agreement_w,4)) -> 32 | EM46: =IF(DP46<>"444","N/A",EL46) -> N/A | EN46: =VLOOKUP(DV46,tabel_jpm,ED46+1,0) -> 20 | EO46: =VLOOKUP(DW46,tabel_jpm,EE46+1,0) -> 12 | EP46: =VLOOKUP(DX46,tabel_jpm,EF46+1,0) -> 12 | EQ46: =VLOOKUP(DY46,tabel_jpm,EG46+1,0) -> 24 | ER46: =IF(B46="Pria",VLOOKUP(AVERAGE(EN46:EQ46),agreement_p,4),VLOOKUP(AVERAGE(EN46:EQ46),agreement_w,4)) -> 50 | ES46: =IF(DP46<>"444","N/A",ER46) -> N/A | ET46: =VLOOKUP(DZ46,tabel_jpm,ED46+1,0) -> 20 | EU46: =VLOOKUP(EA46,tabel_jpm,EE46+1,0) -> 24 | EV46: =VLOOKUP(EB46,tabel_jpm,EF46+1,0) -> 24 | EW46: =VLOOKUP(EC46,tabel_jpm,EG46+1,0) -> 20 | EX46: =IF(B46="Pria",VLOOKUP(AVERAGE(ET46:EW46),agreement_p,4),VLOOKUP(AVERAGE(ET46:EW46),agreement_w,4)) -> 68 | EY46: =IF(DP46<>"444","N/A",EX46) -> N/A
A47: =data!A47 | B47: =data!B47 | C47: =data!C47 | D47: =data!D47 | E47: =data!E47 | F47: =data!F47 -> profiling | G47: =data!G47 | H47: =data!H47 | ... W47: =data!W47 -> 0 | Y47: =VLOOKUP(G47,tableD1,2,0) -> 4 | Z47: =VLOOKUP(H47,tableI1,2,0) -> 3 | AA47: =VLOOKUP(I47,table1S,2,0) -> 5 | AB47: =VLOOKUP(J47,table1C,2,0) -> 4 | AC47: =VLOOKUP(L47,table2D,2,0) -> 31 | AD47: =VLOOKUP(M47,table2I,2,0) -> 31 | AE47: =VLOOKUP(N47,table2S,2,0) -> 32 | AF47: =VLOOKUP(O47,table2C,2,0) -> 32 | AG47: =VLOOKUP(Q47,table3D,2,0) -> 16 | AH47: =VLOOKUP(R47,table3I,2,0) -> 18 | AI47: =VLOOKUP(S47,table3S,2,0) -> 19 | AJ47: =VLOOKUP(T47,table3C,2,0) -> 19 | AL47: =VALUE(Y47&AL$2) -> 41 | AM47: =VALUE(Z47&AM$2) -> 32 | AN47: =VALUE(AA47&AN$2) -> 53 | AO47: =VALUE(AB47&AO$2) -> 44 | AQ47: =LARGE($AL47:$AO47,AQ$2) -> 53 | AR47: =LARGE($AL47:$AO47,AR$2) -> 44 | AS47: =LARGE($AL47:$AO47,AS$2) -> 41 | AT47: =LARGE($AL47:$AO47,AT$2) -> 32 | AV47: =VLOOKUP(VALUE(RIGHT(AQ47,1)),misc!$A$2:$B$5,2,0) -> S | AW47: =VLOOKUP(VALUE(RIGHT(AR47,1)),misc!$A$2:$B$5,2,0) -> C | AX47: =VLOOKUP(VALUE(RIGHT(AS47,1)),misc!$A$2:$B$5,2,0) -> D | AY47: =VLOOKUP(VALUE(RIGHT(AT47,1)),misc!$A$2:$B$5,2,0) -> I | BA47: =IF(VALUE(AQ47)>=170,AV47,"") | BB47: =IF(VALUE(AR47)>=170,AW47,"") | BC47: =IF(VALUE(AS47)>=170,AX47,"") | BD47: =IF(VALUE(AT47)>=170,AY47,"") | BF47: =IF(VALUE(AQ47)<170,AV47,"") -> S | BG47: =IF(VALUE(AR47)<170,AW47,"") -> C | BH47: =IF(VALUE(AS47)<170,AX47,"") -> D | BI47: =IF(VALUE(AT47)<170,AY47,"") -> I | BJ47: =IF(AND(Y47<17,Z47<17,AA47<17,AB47<17),1,IF(AND(Y47>=17,Z47>=17,AA47>=17,AB47>=17),2,IF(AND(Y47>12,Y47<21,Z47>12,Z47<21,AA47>12,AA47<21,AB47>12,AB47<21),3,4))) -> 1 | BK47: =TRIM(BA47&BB47&BC47&BD47) | BN47: =VALUE(AC47&BN$2) -> 311 | BO47: =VALUE(AD47&BO$2) -> 312 | BP47: =VALUE(AE47&BP$2) -> 323 | BQ47: =VALUE(AF47&BQ$2) -> 324 | BS47: =LARGE($BN47:$BQ47,BS$2) -> 324 | BT47: =LARGE($BN47:$BQ47,BT$2) -> 323 | BU47: =LARGE($BN47:$BQ47,BU$2) -> 312 | BV47: =LARGE($BN47:$BQ47,BV$2) -> 311 | BX47: =VLOOKUP(VALUE(RIGHT(BS47,1)),misc!$A$2:$B$5,2,0) -> C | BY47: =VLOOKUP(VALUE(RIGHT(BT47,1)),misc!$A$2:$B$5,2,0) -> S | BZ47: =VLOOKUP(VALUE(RIGHT(BU47,1)),misc!$A$2:$B$5,2,0) -> I | CA47: =VLOOKUP(VALUE(RIGHT(BV47,1)),misc!$A$2:$B$5,2,0) -> D | CC47: =IF(VALUE(BS47)>=170,BX47,"") -> C | CD47: =IF(VALUE(BT47)>=170,BY47,"") -> S | CE47: =IF(VALUE(BU47)>=170,BZ47,"") -> I | CF47: =IF(VALUE(BV47)>=170,CA47,"") -> D | CH47: =IF(VALUE(BS47)<170,BX47,"") | CI47: =IF(VALUE(BT47)<170,BY47,"") | CJ47: =IF(VALUE(BU47)<170,BZ47,"") | CK47: =IF(VALUE(BV47)<170,CA47,"") | CL47: =IF(AND(AC47<17,AD47<17,AE47<17,AF47<17),1,IF(AND(AC47>=17,AD47>=17,AE47>=17,AF47>=17),2,IF(AND(AC47>12,AC47<21,AD47>12,AD47<21,AE47>12,AE47<21,AF47>12,AF47<21),3,4))) -> 2 | CM47: =TRIM(CC47&CD47&CE47&CF47) -> CSID | CP47: =VALUE(AG47&CP$2) -> 161 | CQ47: =VALUE(AH47&CQ$2) -> 182 | CR47: =VALUE(AI47&CR$2) -> 193 | CS47: =VALUE(AJ47&CS$2) -> 194 | CU47: =LARGE($CP47:$CS47,CU$2) -> 194 | CV47: =LARGE($CP47:$CS47,CV$2) -> 193 | CW47: =LARGE($CP47:$CS47,CW$2) -> 182 | CX47: =LARGE($CP47:$CS47,CX$2) -> 161 | CZ47: =VLOOKUP(VALUE(RIGHT(CU47,1)),misc!$A$2:$B$5,2,0) -> C | DA47: =VLOOKUP(VALUE(RIGHT(CV47,1)),misc!$A$2:$B$5,2,0) -> S | DB47: =VLOOKUP(VALUE(RIGHT(CW47,1)),misc!$A$2:$B$5,2,0) -> I | DC47: =VLOOKUP(VALUE(RIGHT(CX47,1)),misc!$A$2:$B$5,2,0) -> D | DE47: =IF(VALUE(CU47)>=170,CZ47,"") -> C | DF47: =IF(VALUE(CV47)>=170,DA47,"") -> S | DG47: =IF(VALUE(CW47)>=170,DB47,"") -> I | DH47: =IF(VALUE(CX47)>=170,DC47,"") | DJ47: =IF(VALUE(CU47)<170,CZ47,"") | DK47: =IF(VALUE(CV47)<170,DA47,"") | DL47: =IF(VALUE(CW47)<170,DB47,"") | DM47: =IF(VALUE(CX47)<170,DC47,"") -> D | DN47: =IF(AND(AG47<17,AH47<17,AI47<17,AJ47<17),1,IF(AND(AG47>=17,AH47>=17,AI47>=17,AJ47>=17),2,IF(AND(AG47>12,AG47<21,AH47>12,AH47<21,AI47>12,AI47<21,AJ47>12,AJ47<21),3,4))) -> 3 | DO47: =TRIM(DE47&DF47&DG47&DH47) -> CSI | DP47: =BJ47&CL47&DN47 -> 123 | DQ47: =A47&G47&H47&I47&J47&L47&M47&N47&O47 | DR47: =VLOOKUP(G47,tableD1,3,0) -> 1 | DS47: =VLOOKUP(H47,tableI1,3,0) -> 1 | DT47: =VLOOKUP(I47,table1S,3,0) -> 2 | DU47: =VLOOKUP(J47,table1C,3,0) -> 1 | DV47: =VLOOKUP(L47,table2D,3,0) -> 8 | DW47: =VLOOKUP(M47,table2I,3,0) -> 8 | DX47: =VLOOKUP(N47,table2S,3,0) -> 8 | DY47: =VLOOKUP(O47,table2C,3,0) -> 8 | DZ47: =VLOOKUP(Q47,table3D,3,0) -> 4 | EA47: =VLOOKUP(R47,table3I,3,0) -> 5 | EB47: =VLOOKUP(S47,table3S,3,0) -> 5 | EC47: =VLOOKUP(T47,table3C,3,0) -> 5 | ED47: {=VLOOKUP(INDEX(JD,data!$AA$1),key!$J$3:$L$27,3,0)} -> 6 | EE47: {=VLOOKUP(INDEX(JI,data!$AA$1),key!$J$3:$L$27,3,0)} -> 4 | EF47: {=VLOOKUP(INDEX(JS,data!$AA$1),key!$J$3:$L$27,3,0)} -> 4 | EG47: {=VLOOKUP(INDEX(JC,data!$AA$1),key!$J$3:$L$27,3,0)} -> 7 | EH47: =VLOOKUP(DR47,tabel_jpm,ED47+1,0) -> 8 | EI47: =VLOOKUP(DS47,tabel_jpm,EE47+1,0) -> 16 | EJ47: =VLOOKUP(DT47,tabel_jpm,EF47+1,0) -> 20 | EK47: =VLOOKUP(DU47,tabel_jpm,EG47+1,0) -> 4 | EL47: =IF(B47="Pria",VLOOKUP(AVERAGE(EH47:EK47),agreement_p,4),VLOOKUP(AVERAGE(EH47:EK47),agreement_w,4)) -> 32 | EM47: =IF(DP47<>"444","N/A",EL47) -> N/A | EN47: =VLOOKUP(DV47,tabel_jpm,ED47+1,0) -> 20 | EO47: =VLOOKUP(DW47,tabel_jpm,EE47+1,0) -> 12 | EP47: =VLOOKUP(DX47,tabel_jpm,EF47+1,0) -> 12 | EQ47: =VLOOKUP(DY47,tabel_jpm,EG47+1,0) -> 24 | ER47: =IF(B47="Pria",VLOOKUP(AVERAGE(EN47:EQ47),agreement_p,4),VLOOKUP(AVERAGE(EN47:EQ47),agreement_w,4)) -> 50 | ES47: =IF(DP47<>"444","N/A",ER47) -> N/A | ET47: =VLOOKUP(DZ47,tabel_jpm,ED47+1,0) -> 20 | EU47: =VLOOKUP(EA47,tabel_jpm,EE47+1,0) -> 24 | EV47: =VLOOKUP(EB47,tabel_jpm,EF47+1,0) -> 24 | EW47: =VLOOKUP(EC47,tabel_jpm,EG47+1,0) -> 20 | EX47: =IF(B47="Pria",VLOOKUP(AVERAGE(ET47:EW47),agreement_p,4),VLOOKUP(AVERAGE(ET47:EW47),agreement_w,4)) -> 68 | EY47: =IF(DP47<>"444","N/A",EX47) -> N/A
A48: =data!A48 | B48: =data!B48 | C48: =data!C48 | D48: =data!D48 | E48: =data!E48 | F48: =data!F48 -> profiling | G48: =data!G48 | H48: =data!H48 | ... W48: =data!W48 -> 0 | Y48: =VLOOKUP(G48,tableD1,2,0) -> 4 | Z48: =VLOOKUP(H48,tableI1,2,0) -> 3 | AA48: =VLOOKUP(I48,table1S,2,0) -> 5 | AB48: =VLOOKUP(J48,table1C,2,0) -> 4 | AC48: =VLOOKUP(L48,table2D,2,0) -> 31 | AD48: =VLOOKUP(M48,table2I,2,0) -> 31 | AE48: =VLOOKUP(N48,table2S,2,0) -> 32 | AF48: =VLOOKUP(O48,table2C,2,0) -> 32 | AG48: =VLOOKUP(Q48,table3D,2,0) -> 16 | AH48: =VLOOKUP(R48,table3I,2,0) -> 18 | AI48: =VLOOKUP(S48,table3S,2,0) -> 19 | AJ48: =VLOOKUP(T48,table3C,2,0) -> 19 | AL48: =VALUE(Y48&AL$2) -> 41 | AM48: =VALUE(Z48&AM$2) -> 32 | AN48: =VALUE(AA48&AN$2) -> 53 | AO48: =VALUE(AB48&AO$2) -> 44 | AQ48: =LARGE($AL48:$AO48,AQ$2) -> 53 | AR48: =LARGE($AL48:$AO48,AR$2) -> 44 | AS48: =LARGE($AL48:$AO48,AS$2) -> 41 | AT48: =LARGE($AL48:$AO48,AT$2) -> 32 | AV48: =VLOOKUP(VALUE(RIGHT(AQ48,1)),misc!$A$2:$B$5,2,0) -> S | AW48: =VLOOKUP(VALUE(RIGHT(AR48,1)),misc!$A$2:$B$5,2,0) -> C | AX48: =VLOOKUP(VALUE(RIGHT(AS48,1)),misc!$A$2:$B$5,2,0) -> D | AY48: =VLOOKUP(VALUE(RIGHT(AT48,1)),misc!$A$2:$B$5,2,0) -> I | BA48: =IF(VALUE(AQ48)>=170,AV48,"") | BB48: =IF(VALUE(AR48)>=170,AW48,"") | BC48: =IF(VALUE(AS48)>=170,AX48,"") | BD48: =IF(VALUE(AT48)>=170,AY48,"") | BF48: =IF(VALUE(AQ48)<170,AV48,"") -> S | BG48: =IF(VALUE(AR48)<170,AW48,"") -> C | BH48: =IF(VALUE(AS48)<170,AX48,"") -> D | BI48: =IF(VALUE(AT48)<170,AY48,"") -> I | BJ48: =IF(AND(Y48<17,Z48<17,AA48<17,AB48<17),1,IF(AND(Y48>=17,Z48>=17,AA48>=17,AB48>=17),2,IF(AND(Y48>12,Y48<21,Z48>12,Z48<21,AA48>12,AA48<21,AB48>12,AB48<21),3,4))) -> 1 | BK48: =TRIM(BA48&BB48&BC48&BD48) | BN48: =VALUE(AC48&BN$2) -> 311 | BO48: =VALUE(AD48&BO$2) -> 312 | BP48: =VALUE(AE48&BP$2) -> 323 | BQ48: =VALUE(AF48&BQ$2) -> 324 | BS48: =LARGE($BN48:$BQ48,BS$2) -> 324 | BT48: =LARGE($BN48:$BQ48,BT$2) -> 323 | BU48: =LARGE($BN48:$BQ48,BU$2) -> 312 | BV48: =LARGE($BN48:$BQ48,BV$2) -> 311 | BX48: =VLOOKUP(VALUE(RIGHT(BS48,1)),misc!$A$2:$B$5,2,0) -> C | BY48: =VLOOKUP(VALUE(RIGHT(BT48,1)),misc!$A$2:$B$5,2,0) -> S | BZ48: =VLOOKUP(VALUE(RIGHT(BU48,1)),misc!$A$2:$B$5,2,0) -> I | CA48: =VLOOKUP(VALUE(RIGHT(BV48,1)),misc!$A$2:$B$5,2,0) -> D | CC48: =IF(VALUE(BS48)>=170,BX48,"") -> C | CD48: =IF(VALUE(BT48)>=170,BY48,"") -> S | CE48: =IF(VALUE(BU48)>=170,BZ48,"") -> I | CF48: =IF(VALUE(BV48)>=170,CA48,"") -> D | CH48: =IF(VALUE(BS48)<170,BX48,"") | CI48: =IF(VALUE(BT48)<170,BY48,"") | CJ48: =IF(VALUE(BU48)<170,BZ48,"") | CK48: =IF(VALUE(BV48)<170,CA48,"") | CL48: =IF(AND(AC48<17,AD48<17,AE48<17,AF48<17),1,IF(AND(AC48>=17,AD48>=17,AE48>=17,AF48>=17),2,IF(AND(AC48>12,AC48<21,AD48>12,AD48<21,AE48>12,AE48<21,AF48>12,AF48<21),3,4))) -> 2 | CM48: =TRIM(CC48&CD48&CE48&CF48) -> CSID | CP48: =VALUE(AG48&CP$2) -> 161 | CQ48: =VALUE(AH48&CQ$2) -> 182 | CR48: =VALUE(AI48&CR$2) -> 193 | CS48: =VALUE(AJ48&CS$2) -> 194 | CU48: =LARGE($CP48:$CS48,CU$2) -> 194 | CV48: =LARGE($CP48:$CS48,CV$2) -> 193 | CW48: =LARGE($CP48:$CS48,CW$2) -> 182 | CX48: =LARGE($CP48:$CS48,CX$2) -> 161 | CZ48: =VLOOKUP(VALUE(RIGHT(CU48,1)),misc!$A$2:$B$5,2,0) -> C | DA48: =VLOOKUP(VALUE(RIGHT(CV48,1)),misc!$A$2:$B$5,2,0) -> S | DB48: =VLOOKUP(VALUE(RIGHT(CW48,1)),misc!$A$2:$B$5,2,0) -> I | DC48: =VLOOKUP(VALUE(RIGHT(CX48,1)),misc!$A$2:$B$5,2,0) -> D | DE48: =IF(VALUE(CU48)>=170,CZ48,"") -> C | DF48: =IF(VALUE(CV48)>=170,DA48,"") -> S | DG48: =IF(VALUE(CW48)>=170,DB48,"") -> I | DH48: =IF(VALUE(CX48)>=170,DC48,"") | DJ48: =IF(VALUE(CU48)<170,CZ48,"") | DK48: =IF(VALUE(CV48)<170,DA48,"") | DL48: =IF(VALUE(CW48)<170,DB48,"") | DM48: =IF(VALUE(CX48)<170,DC48,"") -> D | DN48: =IF(AND(AG48<17,AH48<17,AI48<17,AJ48<17),1,IF(AND(AG48>=17,AH48>=17,AI48>=17,AJ48>=17),2,IF(AND(AG48>12,AG48<21,AH48>12,AH48<21,AI48>12,AI48<21,AJ48>12,AJ48<21),3,4))) -> 3 | DO48: =TRIM(DE48&DF48&DG48&DH48) -> CSI | DP48: =BJ48&CL48&DN48 -> 123 | DQ48: =A48&G48&H48&I48&J48&L48&M48&N48&O48 | DR48: =VLOOKUP(G48,tableD1,3,0) -> 1 | DS48: =VLOOKUP(H48,tableI1,3,0) -> 1 | DT48: =VLOOKUP(I48,table1S,3,0) -> 2 | DU48: =VLOOKUP(J48,table1C,3,0) -> 1 | DV48: =VLOOKUP(L48,table2D,3,0) -> 8 | DW48: =VLOOKUP(M48,table2I,3,0) -> 8 | DX48: =VLOOKUP(N48,table2S,3,0) -> 8 | DY48: =VLOOKUP(O48,table2C,3,0) -> 8 | DZ48: =VLOOKUP(Q48,table3D,3,0) -> 4 | EA48: =VLOOKUP(R48,table3I,3,0) -> 5 | EB48: =VLOOKUP(S48,table3S,3,0) -> 5 | EC48: =VLOOKUP(T48,table3C,3,0) -> 5 | ED48: {=VLOOKUP(INDEX(JD,data!$AA$1),key!$J$3:$L$27,3,0)} -> 6 | EE48: {=VLOOKUP(INDEX(JI,data!$AA$1),key!$J$3:$L$27,3,0)} -> 4 | EF48: {=VLOOKUP(INDEX(JS,data!$AA$1),key!$J$3:$L$27,3,0)} -> 4 | EG48: {=VLOOKUP(INDEX(JC,data!$AA$1),key!$J$3:$L$27,3,0)} -> 7 | EH48: =VLOOKUP(DR48,tabel_jpm,ED48+1,0) -> 8 | EI48: =VLOOKUP(DS48,tabel_jpm,EE48+1,0) -> 16 | EJ48: =VLOOKUP(DT48,tabel_jpm,EF48+1,0) -> 20 | EK48: =VLOOKUP(DU48,tabel_jpm,EG48+1,0) -> 4 | EL48: =IF(B48="Pria",VLOOKUP(AVERAGE(EH48:EK48),agreement_p,4),VLOOKUP(AVERAGE(EH48:EK48),agreement_w,4)) -> 32 | EM48: =IF(DP48<>"444","N/A",EL48) -> N/A | EN48: =VLOOKUP(DV48,tabel_jpm,ED48+1,0) -> 20 | EO48: =VLOOKUP(DW48,tabel_jpm,EE48+1,0) -> 12 | EP48: =VLOOKUP(DX48,tabel_jpm,EF48+1,0) -> 12 | EQ48: =VLOOKUP(DY48,tabel_jpm,EG48+1,0) -> 24 | ER48: =IF(B48="Pria",VLOOKUP(AVERAGE(EN48:EQ48),agreement_p,4),VLOOKUP(AVERAGE(EN48:EQ48),agreement_w,4)) -> 50 | ES48: =IF(DP48<>"444","N/A",ER48) -> N/A | ET48: =VLOOKUP(DZ48,tabel_jpm,ED48+1,0) -> 20 | EU48: =VLOOKUP(EA48,tabel_jpm,EE48+1,0) -> 24 | EV48: =VLOOKUP(EB48,tabel_jpm,EF48+1,0) -> 24 | EW48: =VLOOKUP(EC48,tabel_jpm,EG48+1,0) -> 20 | EX48: =IF(B48="Pria",VLOOKUP(AVERAGE(ET48:EW48),agreement_p,4),VLOOKUP(AVERAGE(ET48:EW48),agreement_w,4)) -> 68 | EY48: =IF(DP48<>"444","N/A",EX48) -> N/A
A49: =data!A49 | B49: =data!B49 | C49: =data!C49 | D49: =data!D49 | E49: =data!E49 | F49: =data!F49 -> profiling | G49: =data!G49 | H49: =data!H49 | ... W49: =data!W49 -> 0 | Y49: =VLOOKUP(G49,tableD1,2,0) -> 4 | Z49: =VLOOKUP(H49,tableI1,2,0) -> 3 | AA49: =VLOOKUP(I49,table1S,2,0) -> 5 | AB49: =VLOOKUP(J49,table1C,2,0) -> 4 | AC49: =VLOOKUP(L49,table2D,2,0) -> 31 | AD49: =VLOOKUP(M49,table2I,2,0) -> 31 | AE49: =VLOOKUP(N49,table2S,2,0) -> 32 | AF49: =VLOOKUP(O49,table2C,2,0) -> 32 | AG49: =VLOOKUP(Q49,table3D,2,0) -> 16 | AH49: =VLOOKUP(R49,table3I,2,0) -> 18 | AI49: =VLOOKUP(S49,table3S,2,0) -> 19 | AJ49: =VLOOKUP(T49,table3C,2,0) -> 19 | AL49: =VALUE(Y49&AL$2) -> 41 | AM49: =VALUE(Z49&AM$2) -> 32 | AN49: =VALUE(AA49&AN$2) -> 53 | AO49: =VALUE(AB49&AO$2) -> 44 | AQ49: =LARGE($AL49:$AO49,AQ$2) -> 53 | AR49: =LARGE($AL49:$AO49,AR$2) -> 44 | AS49: =LARGE($AL49:$AO49,AS$2) -> 41 | AT49: =LARGE($AL49:$AO49,AT$2) -> 32 | AV49: =VLOOKUP(VALUE(RIGHT(AQ49,1)),misc!$A$2:$B$5,2,0) -> S | AW49: =VLOOKUP(VALUE(RIGHT(AR49,1)),misc!$A$2:$B$5,2,0) -> C | AX49: =VLOOKUP(VALUE(RIGHT(AS49,1)),misc!$A$2:$B$5,2,0) -> D | AY49: =VLOOKUP(VALUE(RIGHT(AT49,1)),misc!$A$2:$B$5,2,0) -> I | BA49: =IF(VALUE(AQ49)>=170,AV49,"") | BB49: =IF(VALUE(AR49)>=170,AW49,"") | BC49: =IF(VALUE(AS49)>=170,AX49,"") | BD49: =IF(VALUE(AT49)>=170,AY49,"") | BF49: =IF(VALUE(AQ49)<170,AV49,"") -> S | BG49: =IF(VALUE(AR49)<170,AW49,"") -> C | BH49: =IF(VALUE(AS49)<170,AX49,"") -> D | BI49: =IF(VALUE(AT49)<170,AY49,"") -> I | BJ49: =IF(AND(Y49<17,Z49<17,AA49<17,AB49<17),1,IF(AND(Y49>=17,Z49>=17,AA49>=17,AB49>=17),2,IF(AND(Y49>12,Y49<21,Z49>12,Z49<21,AA49>12,AA49<21,AB49>12,AB49<21),3,4))) -> 1 | BK49: =TRIM(BA49&BB49&BC49&BD49) | BN49: =VALUE(AC49&BN$2) -> 311 | BO49: =VALUE(AD49&BO$2) -> 312 | BP49: =VALUE(AE49&BP$2) -> 323 | BQ49: =VALUE(AF49&BQ$2) -> 324 | BS49: =LARGE($BN49:$BQ49,BS$2) -> 324 | BT49: =LARGE($BN49:$BQ49,BT$2) -> 323 | BU49: =LARGE($BN49:$BQ49,BU$2) -> 312 | BV49: =LARGE($BN49:$BQ49,BV$2) -> 311 | BX49: =VLOOKUP(VALUE(RIGHT(BS49,1)),misc!$A$2:$B$5,2,0) -> C | BY49: =VLOOKUP(VALUE(RIGHT(BT49,1)),misc!$A$2:$B$5,2,0) -> S | BZ49: =VLOOKUP(VALUE(RIGHT(BU49,1)),misc!$A$2:$B$5,2,0) -> I | CA49: =VLOOKUP(VALUE(RIGHT(BV49,1)),misc!$A$2:$B$5,2,0) -> D | CC49: =IF(VALUE(BS49)>=170,BX49,"") -> C | CD49: =IF(VALUE(BT49)>=170,BY49,"") -> S | CE49: =IF(VALUE(BU49)>=170,BZ49,"") -> I | CF49: =IF(VALUE(BV49)>=170,CA49,"") -> D | CH49: =IF(VALUE(BS49)<170,BX49,"") | CI49: =IF(VALUE(BT49)<170,BY49,"") | CJ49: =IF(VALUE(BU49)<170,BZ49,"") | CK49: =IF(VALUE(BV49)<170,CA49,"") | CL49: =IF(AND(AC49<17,AD49<17,AE49<17,AF49<17),1,IF(AND(AC49>=17,AD49>=17,AE49>=17,AF49>=17),2,IF(AND(AC49>12,AC49<21,AD49>12,AD49<21,AE49>12,AE49<21,AF49>12,AF49<21),3,4))) -> 2 | CM49: =TRIM(CC49&CD49&CE49&CF49) -> CSID | CP49: =VALUE(AG49&CP$2) -> 161 | CQ49: =VALUE(AH49&CQ$2) -> 182 | CR49: =VALUE(AI49&CR$2) -> 193 | CS49: =VALUE(AJ49&CS$2) -> 194 | CU49: =LARGE($CP49:$CS49,CU$2) -> 194 | CV49: =LARGE($CP49:$CS49,CV$2) -> 193 | CW49: =LARGE($CP49:$CS49,CW$2) -> 182 | CX49: =LARGE($CP49:$CS49,CX$2) -> 161 | CZ49: =VLOOKUP(VALUE(RIGHT(CU49,1)),misc!$A$2:$B$5,2,0) -> C | DA49: =VLOOKUP(VALUE(RIGHT(CV49,1)),misc!$A$2:$B$5,2,0) -> S | DB49: =VLOOKUP(VALUE(RIGHT(CW49,1)),misc!$A$2:$B$5,2,0) -> I | DC49: =VLOOKUP(VALUE(RIGHT(CX49,1)),misc!$A$2:$B$5,2,0) -> D | DE49: =IF(VALUE(CU49)>=170,CZ49,"") -> C | DF49: =IF(VALUE(CV49)>=170,DA49,"") -> S | DG49: =IF(VALUE(CW49)>=170,DB49,"") -> I | DH49: =IF(VALUE(CX49)>=170,DC49,"") | DJ49: =IF(VALUE(CU49)<170,CZ49,"") | DK49: =IF(VALUE(CV49)<170,DA49,"") | DL49: =IF(VALUE(CW49)<170,DB49,"") | DM49: =IF(VALUE(CX49)<170,DC49,"") -> D | DN49: =IF(AND(AG49<17,AH49<17,AI49<17,AJ49<17),1,IF(AND(AG49>=17,AH49>=17,AI49>=17,AJ49>=17),2,IF(AND(AG49>12,AG49<21,AH49>12,AH49<21,AI49>12,AI49<21,AJ49>12,AJ49<21),3,4))) -> 3 | DO49: =TRIM(DE49&DF49&DG49&DH49) -> CSI | DP49: =BJ49&CL49&DN49 -> 123 | DQ49: =A49&G49&H49&I49&J49&L49&M49&N49&O49 | DR49: =VLOOKUP(G49,tableD1,3,0) -> 1 | DS49: =VLOOKUP(H49,tableI1,3,0) -> 1 | DT49: =VLOOKUP(I49,table1S,3,0) -> 2 | DU49: =VLOOKUP(J49,table1C,3,0) -> 1 | DV49: =VLOOKUP(L49,table2D,3,0) -> 8 | DW49: =VLOOKUP(M49,table2I,3,0) -> 8 | DX49: =VLOOKUP(N49,table2S,3,0) -> 8 | DY49: =VLOOKUP(O49,table2C,3,0) -> 8 | DZ49: =VLOOKUP(Q49,table3D,3,0) -> 4 | EA49: =VLOOKUP(R49,table3I,3,0) -> 5 | EB49: =VLOOKUP(S49,table3S,3,0) -> 5 | EC49: =VLOOKUP(T49,table3C,3,0) -> 5 | ED49: {=VLOOKUP(INDEX(JD,data!$AA$1),key!$J$3:$L$27,3,0)} -> 6 | EE49: {=VLOOKUP(INDEX(JI,data!$AA$1),key!$J$3:$L$27,3,0)} -> 4 | EF49: {=VLOOKUP(INDEX(JS,data!$AA$1),key!$J$3:$L$27,3,0)} -> 4 | EG49: {=VLOOKUP(INDEX(JC,data!$AA$1),key!$J$3:$L$27,3,0)} -> 7 | EH49: =VLOOKUP(DR49,tabel_jpm,ED49+1,0) -> 8 | EI49: =VLOOKUP(DS49,tabel_jpm,EE49+1,0) -> 16 | EJ49: =VLOOKUP(DT49,tabel_jpm,EF49+1,0) -> 20 | EK49: =VLOOKUP(DU49,tabel_jpm,EG49+1,0) -> 4 | EL49: =IF(B49="Pria",VLOOKUP(AVERAGE(EH49:EK49),agreement_p,4),VLOOKUP(AVERAGE(EH49:EK49),agreement_w,4)) -> 32 | EM49: =IF(DP49<>"444","N/A",EL49) -> N/A | EN49: =VLOOKUP(DV49,tabel_jpm,ED49+1,0) -> 20 | EO49: =VLOOKUP(DW49,tabel_jpm,EE49+1,0) -> 12 | EP49: =VLOOKUP(DX49,tabel_jpm,EF49+1,0) -> 12 | EQ49: =VLOOKUP(DY49,tabel_jpm,EG49+1,0) -> 24 | ER49: =IF(B49="Pria",VLOOKUP(AVERAGE(EN49:EQ49),agreement_p,4),VLOOKUP(AVERAGE(EN49:EQ49),agreement_w,4)) -> 50 | ES49: =IF(DP49<>"444","N/A",ER49) -> N/A | ET49: =VLOOKUP(DZ49,tabel_jpm,ED49+1,0) -> 20 | EU49: =VLOOKUP(EA49,tabel_jpm,EE49+1,0) -> 24 | EV49: =VLOOKUP(EB49,tabel_jpm,EF49+1,0) -> 24 | EW49: =VLOOKUP(EC49,tabel_jpm,EG49+1,0) -> 20 | EX49: =IF(B49="Pria",VLOOKUP(AVERAGE(ET49:EW49),agreement_p,4),VLOOKUP(AVERAGE(ET49:EW49),agreement_w,4)) -> 68 | EY49: =IF(DP49<>"444","N/A",EX49) -> N/A
A50: =data!A50 | B50: =data!B50 | C50: =data!C50 | D50: =data!D50 | E50: =data!E50 | F50: =data!F50 -> profiling | G50: =data!G50 | H50: =data!H50 | ... W50: =data!W50 -> 0 | Y50: =VLOOKUP(G50,tableD1,2,0) -> 4 | Z50: =VLOOKUP(H50,tableI1,2,0) -> 3 | AA50: =VLOOKUP(I50,table1S,2,0) -> 5 | AB50: =VLOOKUP(J50,table1C,2,0) -> 4 | AC50: =VLOOKUP(L50,table2D,2,0) -> 31 | AD50: =VLOOKUP(M50,table2I,2,0) -> 31 | AE50: =VLOOKUP(N50,table2S,2,0) -> 32 | AF50: =VLOOKUP(O50,table2C,2,0) -> 32 | AG50: =VLOOKUP(Q50,table3D,2,0) -> 16 | AH50: =VLOOKUP(R50,table3I,2,0) -> 18 | AI50: =VLOOKUP(S50,table3S,2,0) -> 19 | AJ50: =VLOOKUP(T50,table3C,2,0) -> 19 | AL50: =VALUE(Y50&AL$2) -> 41 | AM50: =VALUE(Z50&AM$2) -> 32 | AN50: =VALUE(AA50&AN$2) -> 53 | AO50: =VALUE(AB50&AO$2) -> 44 | AQ50: =LARGE($AL50:$AO50,AQ$2) -> 53 | AR50: =LARGE($AL50:$AO50,AR$2) -> 44 | AS50: =LARGE($AL50:$AO50,AS$2) -> 41 | AT50: =LARGE($AL50:$AO50,AT$2) -> 32 | AV50: =VLOOKUP(VALUE(RIGHT(AQ50,1)),misc!$A$2:$B$5,2,0) -> S | AW50: =VLOOKUP(VALUE(RIGHT(AR50,1)),misc!$A$2:$B$5,2,0) -> C | AX50: =VLOOKUP(VALUE(RIGHT(AS50,1)),misc!$A$2:$B$5,2,0) -> D | AY50: =VLOOKUP(VALUE(RIGHT(AT50,1)),misc!$A$2:$B$5,2,0) -> I | BA50: =IF(VALUE(AQ50)>=170,AV50,"") | BB50: =IF(VALUE(AR50)>=170,AW50,"") | BC50: =IF(VALUE(AS50)>=170,AX50,"") | BD50: =IF(VALUE(AT50)>=170,AY50,"") | BF50: =IF(VALUE(AQ50)<170,AV50,"") -> S | BG50: =IF(VALUE(AR50)<170,AW50,"") -> C | BH50: =IF(VALUE(AS50)<170,AX50,"") -> D | BI50: =IF(VALUE(AT50)<170,AY50,"") -> I | BJ50: =IF(AND(Y50<17,Z50<17,AA50<17,AB50<17),1,IF(AND(Y50>=17,Z50>=17,AA50>=17,AB50>=17),2,IF(AND(Y50>12,Y50<21,Z50>12,Z50<21,AA50>12,AA50<21,AB50>12,AB50<21),3,4))) -> 1 | BK50: =TRIM(BA50&BB50&BC50&BD50) | BN50: =VALUE(AC50&BN$2) -> 311 | BO50: =VALUE(AD50&BO$2) -> 312 | BP50: =VALUE(AE50&BP$2) -> 323 | BQ50: =VALUE(AF50&BQ$2) -> 324 | BS50: =LARGE($BN50:$BQ50,BS$2) -> 324 | BT50: =LARGE($BN50:$BQ50,BT$2) -> 323 | BU50: =LARGE($BN50:$BQ50,BU$2) -> 312 | BV50: =LARGE($BN50:$BQ50,BV$2) -> 311 | BX50: =VLOOKUP(VALUE(RIGHT(BS50,1)),misc!$A$2:$B$5,2,0) -> C | BY50: =VLOOKUP(VALUE(RIGHT(BT50,1)),misc!$A$2:$B$5,2,0) -> S | BZ50: =VLOOKUP(VALUE(RIGHT(BU50,1)),misc!$A$2:$B$5,2,0) -> I | CA50: =VLOOKUP(VALUE(RIGHT(BV50,1)),misc!$A$2:$B$5,2,0) -> D | CC50: =IF(VALUE(BS50)>=170,BX50,"") -> C | CD50: =IF(VALUE(BT50)>=170,BY50,"") -> S | CE50: =IF(VALUE(BU50)>=170,BZ50,"") -> I | CF50: =IF(VALUE(BV50)>=170,CA50,"") -> D | CH50: =IF(VALUE(BS50)<170,BX50,"") | CI50: =IF(VALUE(BT50)<170,BY50,"") | CJ50: =IF(VALUE(BU50)<170,BZ50,"") | CK50: =IF(VALUE(BV50)<170,CA50,"") | CL50: =IF(AND(AC50<17,AD50<17,AE50<17,AF50<17),1,IF(AND(AC50>=17,AD50>=17,AE50>=17,AF50>=17),2,IF(AND(AC50>12,AC50<21,AD50>12,AD50<21,AE50>12,AE50<21,AF50>12,AF50<21),3,4))) -> 2 | CM50: =TRIM(CC50&CD50&CE50&CF50) -> CSID | CP50: =VALUE(AG50&CP$2) -> 161 | CQ50: =VALUE(AH50&CQ$2) -> 182 | CR50: =VALUE(AI50&CR$2) -> 193 | CS50: =VALUE(AJ50&CS$2) -> 194 | CU50: =LARGE($CP50:$CS50,CU$2) -> 194 | CV50: =LARGE($CP50:$CS50,CV$2) -> 193 | CW50: =LARGE($CP50:$CS50,CW$2) -> 182 | CX50: =LARGE($CP50:$CS50,CX$2) -> 161 | CZ50: =VLOOKUP(VALUE(RIGHT(CU50,1)),misc!$A$2:$B$5,2,0) -> C | DA50: =VLOOKUP(VALUE(RIGHT(CV50,1)),misc!$A$2:$B$5,2,0) -> S | DB50: =VLOOKUP(VALUE(RIGHT(CW50,1)),misc!$A$2:$B$5,2,0) -> I | DC50: =VLOOKUP(VALUE(RIGHT(CX50,1)),misc!$A$2:$B$5,2,0) -> D | DE50: =IF(VALUE(CU50)>=170,CZ50,"") -> C | DF50: =IF(VALUE(CV50)>=170,DA50,"") -> S | DG50: =IF(VALUE(CW50)>=170,DB50,"") -> I | DH50: =IF(VALUE(CX50)>=170,DC50,"") | DJ50: =IF(VALUE(CU50)<170,CZ50,"") | DK50: =IF(VALUE(CV50)<170,DA50,"") | DL50: =IF(VALUE(CW50)<170,DB50,"") | DM50: =IF(VALUE(CX50)<170,DC50,"") -> D | DN50: =IF(AND(AG50<17,AH50<17,AI50<17,AJ50<17),1,IF(AND(AG50>=17,AH50>=17,AI50>=17,AJ50>=17),2,IF(AND(AG50>12,AG50<21,AH50>12,AH50<21,AI50>12,AI50<21,AJ50>12,AJ50<21),3,4))) -> 3 | DO50: =TRIM(DE50&DF50&DG50&DH50) -> CSI | DP50: =BJ50&CL50&DN50 -> 123 | DQ50: =A50&G50&H50&I50&J50&L50&M50&N50&O50 | DR50: =VLOOKUP(G50,tableD1,3,0) -> 1 | DS50: =VLOOKUP(H50,tableI1,3,0) -> 1 | DT50: =VLOOKUP(I50,table1S,3,0) -> 2 | DU50: =VLOOKUP(J50,table1C,3,0) -> 1 | DV50: =VLOOKUP(L50,table2D,3,0) -> 8 | DW50: =VLOOKUP(M50,table2I,3,0) -> 8 | DX50: =VLOOKUP(N50,table2S,3,0) -> 8 | DY50: =VLOOKUP(O50,table2C,3,0) -> 8 | DZ50: =VLOOKUP(Q50,table3D,3,0) -> 4 | EA50: =VLOOKUP(R50,table3I,3,0) -> 5 | EB50: =VLOOKUP(S50,table3S,3,0) -> 5 | EC50: =VLOOKUP(T50,table3C,3,0) -> 5 | ED50: {=VLOOKUP(INDEX(JD,data!$AA$1),key!$J$3:$L$27,3,0)} -> 6 | EE50: {=VLOOKUP(INDEX(JI,data!$AA$1),key!$J$3:$L$27,3,0)} -> 4 | EF50: {=VLOOKUP(INDEX(JS,data!$AA$1),key!$J$3:$L$27,3,0)} -> 4 | EG50: {=VLOOKUP(INDEX(JC,data!$AA$1),key!$J$3:$L$27,3,0)} -> 7 | EH50: =VLOOKUP(DR50,tabel_jpm,ED50+1,0) -> 8 | EI50: =VLOOKUP(DS50,tabel_jpm,EE50+1,0) -> 16 | EJ50: =VLOOKUP(DT50,tabel_jpm,EF50+1,0) -> 20 | EK50: =VLOOKUP(DU50,tabel_jpm,EG50+1,0) -> 4 | EL50: =IF(B50="Pria",VLOOKUP(AVERAGE(EH50:EK50),agreement_p,4),VLOOKUP(AVERAGE(EH50:EK50),agreement_w,4)) -> 32 | EM50: =IF(DP50<>"444","N/A",EL50) -> N/A | EN50: =VLOOKUP(DV50,tabel_jpm,ED50+1,0) -> 20 | EO50: =VLOOKUP(DW50,tabel_jpm,EE50+1,0) -> 12 | EP50: =VLOOKUP(DX50,tabel_jpm,EF50+1,0) -> 12 | EQ50: =VLOOKUP(DY50,tabel_jpm,EG50+1,0) -> 24 | ER50: =IF(B50="Pria",VLOOKUP(AVERAGE(EN50:EQ50),agreement_p,4),VLOOKUP(AVERAGE(EN50:EQ50),agreement_w,4)) -> 50 | ES50: =IF(DP50<>"444","N/A",ER50) -> N/A | ET50: =VLOOKUP(DZ50,tabel_jpm,ED50+1,0) -> 20 | EU50: =VLOOKUP(EA50,tabel_jpm,EE50+1,0) -> 24 | EV50: =VLOOKUP(EB50,tabel_jpm,EF50+1,0) -> 24 | EW50: =VLOOKUP(EC50,tabel_jpm,EG50+1,0) -> 20 | EX50: =IF(B50="Pria",VLOOKUP(AVERAGE(ET50:EW50),agreement_p,4),VLOOKUP(AVERAGE(ET50:EW50),agreement_w,4)) -> 68 | EY50: =IF(DP50<>"444","N/A",EX50) -> N/A
A51: =data!A51 | B51: =data!B51 | C51: =data!C51 | D51: =data!D51 | E51: =data!E51 | F51: =data!F51 -> profiling | G51: =data!G51 | H51: =data!H51 | ... W51: =data!W51 -> 0 | Y51: =VLOOKUP(G51,tableD1,2,0) -> 4 | Z51: =VLOOKUP(H51,tableI1,2,0) -> 3 | AA51: =VLOOKUP(I51,table1S,2,0) -> 5 | AB51: =VLOOKUP(J51,table1C,2,0) -> 4 | AC51: =VLOOKUP(L51,table2D,2,0) -> 31 | AD51: =VLOOKUP(M51,table2I,2,0) -> 31 | AE51: =VLOOKUP(N51,table2S,2,0) -> 32 | AF51: =VLOOKUP(O51,table2C,2,0) -> 32 | AG51: =VLOOKUP(Q51,table3D,2,0) -> 16 | AH51: =VLOOKUP(R51,table3I,2,0) -> 18 | AI51: =VLOOKUP(S51,table3S,2,0) -> 19 | AJ51: =VLOOKUP(T51,table3C,2,0) -> 19 | AL51: =VALUE(Y51&AL$2) -> 41 | AM51: =VALUE(Z51&AM$2) -> 32 | AN51: =VALUE(AA51&AN$2) -> 53 | AO51: =VALUE(AB51&AO$2) -> 44 | AQ51: =LARGE($AL51:$AO51,AQ$2) -> 53 | AR51: =LARGE($AL51:$AO51,AR$2) -> 44 | AS51: =LARGE($AL51:$AO51,AS$2) -> 41 | AT51: =LARGE($AL51:$AO51,AT$2) -> 32 | AV51: =VLOOKUP(VALUE(RIGHT(AQ51,1)),misc!$A$2:$B$5,2,0) -> S | AW51: =VLOOKUP(VALUE(RIGHT(AR51,1)),misc!$A$2:$B$5,2,0) -> C | AX51: =VLOOKUP(VALUE(RIGHT(AS51,1)),misc!$A$2:$B$5,2,0) -> D | AY51: =VLOOKUP(VALUE(RIGHT(AT51,1)),misc!$A$2:$B$5,2,0) -> I | BA51: =IF(VALUE(AQ51)>=170,AV51,"") | BB51: =IF(VALUE(AR51)>=170,AW51,"") | BC51: =IF(VALUE(AS51)>=170,AX51,"") | BD51: =IF(VALUE(AT51)>=170,AY51,"") | BF51: =IF(VALUE(AQ51)<170,AV51,"") -> S | BG51: =IF(VALUE(AR51)<170,AW51,"") -> C | BH51: =IF(VALUE(AS51)<170,AX51,"") -> D | BI51: =IF(VALUE(AT51)<170,AY51,"") -> I | BJ51: =IF(AND(Y51<17,Z51<17,AA51<17,AB51<17),1,IF(AND(Y51>=17,Z51>=17,AA51>=17,AB51>=17),2,IF(AND(Y51>12,Y51<21,Z51>12,Z51<21,AA51>12,AA51<21,AB51>12,AB51<21),3,4))) -> 1 | BK51: =TRIM(BA51&BB51&BC51&BD51) | BN51: =VALUE(AC51&BN$2) -> 311 | BO51: =VALUE(AD51&BO$2) -> 312 | BP51: =VALUE(AE51&BP$2) -> 323 | BQ51: =VALUE(AF51&BQ$2) -> 324 | BS51: =LARGE($BN51:$BQ51,BS$2) -> 324 | BT51: =LARGE($BN51:$BQ51,BT$2) -> 323 | BU51: =LARGE($BN51:$BQ51,BU$2) -> 312 | BV51: =LARGE($BN51:$BQ51,BV$2) -> 311 | BX51: =VLOOKUP(VALUE(RIGHT(BS51,1)),misc!$A$2:$B$5,2,0) -> C | BY51: =VLOOKUP(VALUE(RIGHT(BT51,1)),misc!$A$2:$B$5,2,0) -> S | BZ51: =VLOOKUP(VALUE(RIGHT(BU51,1)),misc!$A$2:$B$5,2,0) -> I | CA51: =VLOOKUP(VALUE(RIGHT(BV51,1)),misc!$A$2:$B$5,2,0) -> D | CC51: =IF(VALUE(BS51)>=170,BX51,"") -> C | CD51: =IF(VALUE(BT51)>=170,BY51,"") -> S | CE51: =IF(VALUE(BU51)>=170,BZ51,"") -> I | CF51: =IF(VALUE(BV51)>=170,CA51,"") -> D | CH51: =IF(VALUE(BS51)<170,BX51,"") | CI51: =IF(VALUE(BT51)<170,BY51,"") | CJ51: =IF(VALUE(BU51)<170,BZ51,"") | CK51: =IF(VALUE(BV51)<170,CA51,"") | CL51: =IF(AND(AC51<17,AD51<17,AE51<17,AF51<17),1,IF(AND(AC51>=17,AD51>=17,AE51>=17,AF51>=17),2,IF(AND(AC51>12,AC51<21,AD51>12,AD51<21,AE51>12,AE51<21,AF51>12,AF51<21),3,4))) -> 2 | CM51: =TRIM(CC51&CD51&CE51&CF51) -> CSID | CP51: =VALUE(AG51&CP$2) -> 161 | CQ51: =VALUE(AH51&CQ$2) -> 182 | CR51: =VALUE(AI51&CR$2) -> 193 | CS51: =VALUE(AJ51&CS$2) -> 194 | CU51: =LARGE($CP51:$CS51,CU$2) -> 194 | CV51: =LARGE($CP51:$CS51,CV$2) -> 193 | CW51: =LARGE($CP51:$CS51,CW$2) -> 182 | CX51: =LARGE($CP51:$CS51,CX$2) -> 161 | CZ51: =VLOOKUP(VALUE(RIGHT(CU51,1)),misc!$A$2:$B$5,2,0) -> C | DA51: =VLOOKUP(VALUE(RIGHT(CV51,1)),misc!$A$2:$B$5,2,0) -> S | DB51: =VLOOKUP(VALUE(RIGHT(CW51,1)),misc!$A$2:$B$5,2,0) -> I | DC51: =VLOOKUP(VALUE(RIGHT(CX51,1)),misc!$A$2:$B$5,2,0) -> D | DE51: =IF(VALUE(CU51)>=170,CZ51,"") -> C | DF51: =IF(VALUE(CV51)>=170,DA51,"") -> S | DG51: =IF(VALUE(CW51)>=170,DB51,"") -> I | DH51: =IF(VALUE(CX51)>=170,DC51,"") | DJ51: =IF(VALUE(CU51)<170,CZ51,"") | DK51: =IF(VALUE(CV51)<170,DA51,"") | DL51: =IF(VALUE(CW51)<170,DB51,"") | DM51: =IF(VALUE(CX51)<170,DC51,"") -> D | DN51: =IF(AND(AG51<17,AH51<17,AI51<17,AJ51<17),1,IF(AND(AG51>=17,AH51>=17,AI51>=17,AJ51>=17),2,IF(AND(AG51>12,AG51<21,AH51>12,AH51<21,AI51>12,AI51<21,AJ51>12,AJ51<21),3,4))) -> 3 | DO51: =TRIM(DE51&DF51&DG51&DH51) -> CSI | DP51: =BJ51&CL51&DN51 -> 123 | DQ51: =A51&G51&H51&I51&J51&L51&M51&N51&O51 | DR51: =VLOOKUP(G51,tableD1,3,0) -> 1 | DS51: =VLOOKUP(H51,tableI1,3,0) -> 1 | DT51: =VLOOKUP(I51,table1S,3,0) -> 2 | DU51: =VLOOKUP(J51,table1C,3,0) -> 1 | DV51: =VLOOKUP(L51,table2D,3,0) -> 8 | DW51: =VLOOKUP(M51,table2I,3,0) -> 8 | DX51: =VLOOKUP(N51,table2S,3,0) -> 8 | DY51: =VLOOKUP(O51,table2C,3,0) -> 8 | DZ51: =VLOOKUP(Q51,table3D,3,0) -> 4 | EA51: =VLOOKUP(R51,table3I,3,0) -> 5 | EB51: =VLOOKUP(S51,table3S,3,0) -> 5 | EC51: =VLOOKUP(T51,table3C,3,0) -> 5 | ED51: {=VLOOKUP(INDEX(JD,data!$AA$1),key!$J$3:$L$27,3,0)} -> 6 | EE51: {=VLOOKUP(INDEX(JI,data!$AA$1),key!$J$3:$L$27,3,0)} -> 4 | EF51: {=VLOOKUP(INDEX(JS,data!$AA$1),key!$J$3:$L$27,3,0)} -> 4 | EG51: {=VLOOKUP(INDEX(JC,data!$AA$1),key!$J$3:$L$27,3,0)} -> 7 | EH51: =VLOOKUP(DR51,tabel_jpm,ED51+1,0) -> 8 | EI51: =VLOOKUP(DS51,tabel_jpm,EE51+1,0) -> 16 | EJ51: =VLOOKUP(DT51,tabel_jpm,EF51+1,0) -> 20 | EK51: =VLOOKUP(DU51,tabel_jpm,EG51+1,0) -> 4 | EL51: =IF(B51="Pria",VLOOKUP(AVERAGE(EH51:EK51),agreement_p,4),VLOOKUP(AVERAGE(EH51:EK51),agreement_w,4)) -> 32 | EM51: =IF(DP51<>"444","N/A",EL51) -> N/A | EN51: =VLOOKUP(DV51,tabel_jpm,ED51+1,0) -> 20 | EO51: =VLOOKUP(DW51,tabel_jpm,EE51+1,0) -> 12 | EP51: =VLOOKUP(DX51,tabel_jpm,EF51+1,0) -> 12 | EQ51: =VLOOKUP(DY51,tabel_jpm,EG51+1,0) -> 24 | ER51: =IF(B51="Pria",VLOOKUP(AVERAGE(EN51:EQ51),agreement_p,4),VLOOKUP(AVERAGE(EN51:EQ51),agreement_w,4)) -> 50 | ES51: =IF(DP51<>"444","N/A",ER51) -> N/A | ET51: =VLOOKUP(DZ51,tabel_jpm,ED51+1,0) -> 20 | EU51: =VLOOKUP(EA51,tabel_jpm,EE51+1,0) -> 24 | EV51: =VLOOKUP(EB51,tabel_jpm,EF51+1,0) -> 24 | EW51: =VLOOKUP(EC51,tabel_jpm,EG51+1,0) -> 20 | EX51: =IF(B51="Pria",VLOOKUP(AVERAGE(ET51:EW51),agreement_p,4),VLOOKUP(AVERAGE(ET51:EW51),agreement_w,4)) -> 68 | EY51: =IF(DP51<>"444","N/A",EX51) -> N/A
